Workbook

Sheet summary
A1: Metric and indicator reference | B1: Metric / Indicator | C1: Question format | D1: Evidence Required | E1: Policy dates required
B2: SDG17: PARTNERSHIP FOR THE GOALS (Mandatory for inclusion in overall Impact Rankings)
A3: 17.2 | B3: Relationships to support the goals
A4: 17.2.1 | B4: Relationships with regional NGOs and government for SDG policy Have direct involvement in, or input into, national government or regional non-government organisations SDG policy development - including identifying problems and challenges, developing policies and strategies, modelling likely futures with and without interventions, monitoring and reporting on interventions, and enabling adaptive management | C4: YES/NO | D4: YES | E4: NO
A5: 17.2.2 | B5: Cross sectoral dialogue about SDGs Initiate and participate in cross-sectoral dialogue about the SDGs, e.g. conferences involving government or NGOs | C5: YES/NO | D5: YES | E5: NO
A6: 17.2.3 | B6: International collaboration data gathering for SDG Participate in international collaboration on gathering or measuring data for the SDGs | C6: YES/NO | D6: YES | E6: NO
A7: 17.2.4 | B7: Collaboration for SDG best practice Through international collaboration and research, review comparative approaches and develop international best practice on tackling the SDGs | C7: YES/NO | D7: YES | E7: NO
A8: 17.2.5 | B8: Collaboration with NGOs for SDGs Collaborate with NGOs to tackle the SDGs through: student volunteering programmes, research programmes, or development of educational resources •student volunteering programmes •research programmes •development of educational resources | C8: Picklist | D8: YES | E8: NO
A9: 17.3 | B9: Publication of SDG reports
A10: 17.3.1 | B10: Publication of SDG reports - per SDG Publish progress against SDG1, either individually or within an annual report ●overall report ●separate report | C10: Picklist | D10: YES | E10: NO
A11: 17.3.2 | B11: Publication of SDG reports - per SDG Publish progress against SDG2, either individually or within an annual report ●overall report ●separate report
A12: 17.3.3 | B12: Publication of SDG reports - per SDG Publish progress against SDG3, either individually or within an annual report ●overall report ●separate report
A13: 17.3.4 | B13: Publication of SDG reports - per SDG Publish progress against SDG4, either individually or within an annual report ●overall report ●separate report
A14: 17.3.5 | B14: Publication of SDG reports - per SDG Publish progress against SDG5, either individually or within an annual report ●overall report ●separate report
A15: 17.3.6 | B15: Publication of SDG reports - per SDG Publish progress against SDG6, either individually or within an annual report ●overall report ●separate report
A16: 17.3.7 | B16: Publication of SDG reports - per SDG Publish progress against SDG7, either individually or within an annual report ●overall report ●separate report
A17: 17.3.8 | B17: Publication of SDG reports - per SDG Publish progress against SDG8, either individually or within an annual report ●overall report ●separate report
A18: 17.3.9 | B18: Publication of SDG reports - per SDG Publish progress against SDG9, either individually or within an annual report ●overall report ●separate report
A19: 17.3.10 | B19: Publication of SDG reports - per SDG Publish progress against SDG10, either individually or within an annual report ●overall report ●separate report
A20: 17.3.11 | B20: Publication of SDG reports - per SDG Publish progress against SDG11, either individually or within an annual report ●overall report ●separate report
A21: 17.3.12 | B21: Publication of SDG reports - per SDG Publish progress against SDG12, either individually or within an annual report ●overall report ●separate report
A22: 17.3.13 | B22: Publication of SDG reports - per SDG Publish progress against SDG13, either individually or within an annual report ●overall report ●separate report
... A26: 17.3.17 | B26: Publication of SDG reports - per SDG Publish progress against SDG17, either individually or within an annual report ●overall report ●separate report
A27: 17.4 | B27: Education for the SDGs
A28: 17.4.1 | B28: Education for SDGs commitment to meaningful education Have a commitment to meaningful education around the SDGs across the university, relevant and applicable to all students • Education integrated across full curriculum • Mandatory education for all •Optional education for all | C28: Picklist | D28: YES | E28: NO
A29: 17.4.2 | B29: Education for SDGs specific courses on sustainability Have dedicated courses (full degrees, or electives) that address sustainability and the SDGs. | C29: YES/NO | D29: YES | E29: NO
A30: 17.4.3 | B30: Education for SDGs in the wider community Have dedicated outreach educational activities for the wider community • Alumni • Local community •Displaced people and refugees | C30: Picklist | D30: YES | E30: NO
A31: 17.4.4 | B31: Sustainable Literacy This question explores how you evaluate your students’ ability to learn and retain key concepts of sustainability. For 2025 we will not score this question but will use it to inform our decisions for 2026. Measure the sustainability literacy of students. | C31: YES/NO | D31: YES | E31: NO
B33: SDG1: NO POVERTY
A34: 1.2 | B34: Proportion of students receiving financial aid to attend university because of poverty
A35: 1.2.1 | B35: Low income students receiving financial aid
B36: Number of students | C36: Continuous | D36: NO | E36: NO
B37: Number of low income students receiving financial aid
A38: 1.3 | B38: University anti-poverty programmes
A39: 1.3.1 | B39: Bottom financial quintile admission target Targets to admit students who fall into the bottom 20% of household income group (or a more tightly defined target) in the country. | C39: YES/NO | D39: YES | E39: NO
A40: 1.3.2 | B40: Bottom financial quintile student success Graduation/completion targets for students who fall into the bottom 20% of household income group (or a more tightly defined target) in the country. | C40: YES/NO | D40: YES | E40: NO
A41: 1.3.3 | B41: Low-income student support Provide support (e.g. food, housing, transportation, legal services) for students from low income families to enable them to complete university. •Free •Subsidised | C41: Picklist | D41: YES | E41: NO
A42: 1.3.4 | B42: Bottom financial quintile student support Programmes or initiatives to assist students who fall into the bottom 20% of household income group (or a more tightly defined target) in the country to successfully complete their studies. | C42: YES/NO | D42: YES | E42: NO
A43: 1.3.5 | B43: Low or lower-middle income countries student support Schemes to support poor students from low or lower-middle income countries (e.g. offering free education, grants). | C43: YES/NO | D43: YES | E43: NO
A44: 1.4 | B44: Community anti-poverty programmes
A45: 1.4.1 | B45: Local start-up assistance Provide assistance in the local community supporting the start-up of financially and socially sustainable businesses through relevant education or resources (e.g. mentorship programmes, training workshops, access to university facilities). •Free •Paid | C45: Picklist | D45: YES | E45: NO
A46: 1.4.2 | B46: Local start-up financial assistance Provide financial assistance to the local community supporting the start-up of financially and socially sustainable businesses. | C46: YES/NO | D46: YES | E46: NO
A47: 1.4.3 | B47: Programmes for services access Organise training or programmes to improve access to basic services for all. •Directly •Indirectly | C47: Picklist | D47: YES | E47: NO
A48: 1.4.4 | B48: Policy addressing poverty Participate in policy making at local, regional, national and/or global level to implement programmes and policies to end poverty in all its dimensions. •Local •Regional •National •Global | C48: Picklist | D48: YES | E48: NO
B50: SDG2: ZERO HUNGER
A51: 2.2 | B51: Campus food waste
A52: 2.2.1 | B52: Campus food waste tracking Measure the amount of food waste generated from food served within the university. • Whole University • Partial measurement | C52: Picklist | D52: YES | E52: NO
A53: 2.2.2 | B53: Campus food waste
B54: Total food waste | C54: Continuous | D54: NO | E54: NO
B55: Campus population
A56: 2.3 | B56: Student hunger
A57: 2.3.1 | B57: Student food insecurity and hunger Have a programme in place on student food insecurity. | C57: YES/NO | D57: YES | E57: NO
A58: 2.3.2 | B58: Studentshunger interventions Provide interventions to prevent or alleviate hunger among students (e.g. including supply and access to food banks/pantries). | C58: YES/NO | D58: YES | E58: NO
A59: 2.3.3 | B59: Sustainable food choices on campus Provide sustainable food choices for all on campus, including vegetarian and vegan food. •All food outlets •Selected food outlets | C59: Picklist | D59: YES | E59: NO
A60: 2.3.4 | B60: Healthy and affordable food choices Provide healthy and affordable food choices for all on campus. •All food outlets •Selected food outlets | C60: Picklist | D60: YES | E60: NO
A61: 2.3.5 | B61: Staff hunger interventions Provide interventions to prevent or alleviate hunger among students (e.g. including supply and access to food banks/pantries). | C61: YES/NO | D61: YES | E61: NO
A62: 2.4 | B62: Proportion of graduates in agriculture and aquaculture including sustainability aspects
A63: 2.4.1 | B63: Proportion of graduates in agriculture and aquaculture
B64: Number of graduates | C64: Continuous | D64: NO | E64: NO
B65: Number of graduates from agriculture and aquaculture courses including sustainability aspects
A66: 2.5 | B66: National hunger
A67: 2.5.1 | B67: Access to food security knowledge Provide access on food security and sustainable agriculture and aquaculture knowledge, skills or technology to local farmers and food producers. •Free •Paid | C67: Picklist | D67: YES | E67: NO
A68: 2.5.2 | B68: Events for local farmers and food producers Provide events for local farmers and food producers to connect and transfer knowledge. •Free •Paid | C68: Picklist | D68: YES | E68: NO
A69: 2.5.3 | B69: University access to local farmers and food producers Provide access to university facilities (e.g. labs, technology, plant stocks) to local farmers and food producers to improve sustainable farming practices. •Free •Paid | C69: Picklist | D69: YES | E69: NO
A70: 2.5.4 | B70: Sustainable food purchases Prioritise purchase of products from local, sustainable sources. | C70: YES/NO | D70: YES | E70: NO
B72: SDG3: GOOD HEALTH AND WELLBEING
A73: 3.2 | B73: Number graduating in health professions
A74: 3.2.1 | B74: Proportion of graduates in health professions
B75: Number of graduates | C75: Continuous | D75: NO | E75: NO
B76: Number of graduates in health professions
A77: 3.3 | B77: Collaborations and health services
A78: 3.3.1 | B78: Current collaborations with health institutions Have current collaborations with local, national, or global health institutions to improve health and well-being outcomes. •local collaboration •national collaboration •global cooperation | C78: Picklist | D78: YES | E78: NO
A79: 3.3.2 | B79: Health outreach programmes Deliver outreach programmes and projects in the local community (which can include student volunteering programmes) to improve or promote health and well-being including hygiene, nutrition, family planning, sports, exercise, aging well, and other health and well-being related topics. •Local communities •Disadvantaged people •Refugee/immigrant communities | C79: Picklist | D79: YES | E79: NO
A80: 3.3.3 | B80: Shared sports facilities Share sports facilities with the local community, for instance with local schools or with the general public •Free access to all facilities •Free access to some facilities •Charged access | C80: Picklist | D80: YES | E80: NO
A81: 3.3.4 | B81: Sexual and reproductive health care services for students Provide students access to sexual and reproductive health-care services including information and education services. •Free Access •Charged Access | C81: Picklist | D81: YES | E81: NO
A82: 3.3.5 | B82: Mental health support for students Provide students with access to mental health support. •Active promotion of good mental health •Access to (or signposting to) free mental health support •Access to (or signposting to) charged mental health support | C82: Picklist | D82: YES | E82: NO
A83: 3.3.6 | B83: Smoke-free policy Have a ‘smoke-free’ policy. •Smoking-free campus •Smoking in designated areas | C83: Picklist | D83: YES | E83: YES
A84: 3.3.7 | B84: Mental health support for staff Provide staff with access to mental health support. •Active promotion of good mental health •Access to (or signposting to) free mental health support •Access to (or signposting to) charged mental health support | C84: Picklist | D84: YES | E84: NO
B86: SDG4: QUALITY EDUCATION
A87: 4.2 | B87: Proportion of graduates with teaching qualification
A88: 4.2.1 | B88: Proportion of graduates with relevant qualification for teaching
B89: Number of graduates | C89: Continuous | D89: NO | E89: NO
B90: Number of graduates who gained a qualification that entitled them to teach at primary school level
A91: 4.3 | B91: Lifelong learning measures
A92: 4.3.1 | B92: Public resources (lifelong learning) Provide free access to educational resources for those not studying at the university. •Free courses leading to certificate or award •Free access to campus facilities and equipment •Free access to online resources | C92: Picklist | D92: YES | E92: NO
A93: 4.3.2 | B93: Public events (lifelong learning) Host educational events at university that are open to the general public. •Free events •Both charged and free | C93: Picklist | D93: YES | E93: NO
A94: 4.3.3 | B94: Vocational training events (lifelong learning) Host events at university that are open to the general public: executive education programmes (this refers to short courses for people who are not attending the university; this specifically excludes courses like MBA) and/or vocational training. •Ad hoc •On programmed basis | C94: Picklist | D94: YES | E94: NO
A95: 4.3.4 | B95: Education outreach activities beyond campus Undertake educational outreach activities (e.g. tailored lectures or demonstrations) beyond campus – in local schools, in the community. This can include voluntary student-run schemes. •Ad hoc •On programmed basis | C95: Picklist | D95: YES | E95: NO
A96: 4.3.5 | B96: Lifelong learning access policy A policy that ensures that access to these activities is accessible to all, regardless of ethnicity, religion, disability, immigration status or gender. | C96: YES/NO | D96: YES | E96: YES
A97: 4.4 | B97: Proportion of first-generation students
A98: 4.4.1 | B98: Proportion of first-generation students
B99: Number of students starting a degree | C99: Continuous | D99: NO | E99: NO
B100: Number of first-generation students starting a degree
B102: SDG5: GENDER EQUALITY
A103: 5.2 | B103: Proportion of first-generation female students
A104: 5.2.1 | B104: Proportion of women first- generation
B105: Number of women starting a degree | C105: Continuous | D105: NO | E105: NO
B106: Number of first-generation women starting a degree
A107: 5.3 | B107: Student access measures
A108: 5.3.1 | B108: Tracking access measures Systematically measure and track women’s application rate, and acceptance or entry rate. | C108: YES/NO | D108: YES | E108: NO
...

Sheet example
A1: Type | B1: Metric and indicator reference | C1: Metric / Indicator | D1: Value (for continuous data) | E1: Yes/No | F1: Evidence1 | G1: Public (Yes/No)
A2: Metric | B2: 1.2 | C2: Proportion of students receiving financial aid to attend university because of poverty
A3: Indicator | B3: 1.2.1 | C3: Students receiving financial aid
C4: Number of students | D4: 20458
C5: Number of low income students receiving financial aid | D5: 5326
A6: Metric | B6: 1.3 | C6: University anti-poverty programmes
A7: Indicator | B7: 1.3.1 | C7: Bottom financial quintile admission target Targets to admit students who fall into the bottom 20% of household income group (or a more tightly defined target) in the country. | E7: no
A8: Indicator | B8: 1.3.2 | C8: Bottom financial quintile student success Graduation/completion targets for students who fall into the bottom 20% of household income group (or a more tightly defined target) in the country. | E8: yes | F8: URL | G8: yes
A9: Indicator | B9: 1.3.3 | C9: Low-income student support Provide support (e.g. food, housing, transportation, legal services) for students from low income families to enable them to complete university. | E9: yes
C10: free | E10: no | F10: URL | G10: yes
C11: subsidised | E11: yes
A12: Indicator | B12: 1.3.4 | C12: Bottom financial quintile student support Programmes or initiatives to assist students who fall into the bottom 20% of household income group (or a more tightly defined target) in the country to successfully complete their studies. | E12: no
A13: Indicator | B13: 1.3.5 | C13: Low or lower-middle income countries student support Schemes to support poor students from low or lower-middle income countries (e.g. offering free education, grants). | E13: no
A14: Metric | B14: 1.4 | C14: Community anti-poverty programmes
A15: Indicator | B15: 1.4.1 | C15: Local start-up assistance Provide assistance in the local community supporting the start-up of sustainable businesses through relevant education or resources (e.g. mentorship programmes, training workshops, access to university facilities). | E15: yes
C16: free | E16: no | F16: URL | G16: yes
C17: paid | E17: yes
A18: Indicator | B18: 1.4.2 | C18: Local start-up financial assistance Provide financial assistance to the local community supporting the start-up of sustainable businesses. | E18: yes | F18: URL | G18: yes
A19: Indicator | B19: 1.4.3 | C19: Programmes for services access Organise training or programmes to improve access to basic services for all. | E19: yes
C20: directly | E20: yes | F20: pdf report | G20: yes
C21: indirectly | E21: no
A22: Indicator | B22: 1.4.4 | C22: Policy addressing poverty Participate in policy making at local, regional, national and/or global level to implement programmes and policies to end poverty in all its dimensions. | E22: yes
C23: local | E23: yes | F23: URL | G23: yes
C24: regional | E24: yes
C25: national | E25: no
C26: global | E26: yes

Sheet SDG1
A1: SDG1: No Poverty
A2: Type | B2: Metric and indicator reference | C2: Metric / Indicator | D2: Value (for continuous data) | E2: Yes/No | F2: Evidence1 | G2: Public (Yes/No)
A3: Metric | B3: 1.2 | C3: Proportion of students receiving financial aid to attend university because of poverty
A4: Indicator | B4: 1.2.1 | C4: Low income students receiving financial aid
C5: Number of students
C6: Number of low income students receiving financial aid
A7: Metric | B7: 1.3 | C7: University anti-poverty programmes
A8: Indicator | B8: 1.3.1 | C8: Bottom financial quintile admission target Targets to admit students who fall into the bottom 20% of household income group (or a more tightly defined target) in the country.
A9: Indicator | B9: 1.3.2 | C9: Bottom financial quintile student success Graduation/completion targets for students who fall into the bottom 20% of household income group (or a more tightly defined target) in the country.
A10: Indicator | B10: 1.3.3 | C10: Low-income student support Provide support (e.g. food, housing, transportation, legal services) for students from low income families to enable them to complete university.
C11: free
C12: subsidised
A13: Indicator | B13: 1.3.4 | C13: Bottom financial quintile student support Programmes or initiatives to assist students who fall into the bottom 20% of household income group (or a more tightly defined target) in the country to successfully complete their studies.
A14: Indicator | B14: 1.3.5 | C14: Low or lower-middle income countries student support Schemes to support poor students from low or lower-middle income countries (e.g. offering free education, grants).
A15: Metric | B15: 1.4 | C15: Community anti-poverty programmes
A16: Indicator | B16: 1.4.1 | C16: Local start-up assistance Provide assistance in the local community supporting the start-up of financially and socially sustainable businesses through relevant education or resources (e.g. mentorship programmes, training workshops, access to university facilities).
C17: free
C18: paid
A19: Indicator | B19: 1.4.2 | C19: Local start-up financial assistance Provide financial assistance to the local community supporting the start-up of financially and socially sustainable businesses.
A20: Indicator | B20: 1.4.3 | C20: Programmes for services access Organise training or programmes to improve access to basic services for all.
C21: directly
C22: indirectly
A23: Indicator | B23: 1.4.4 | C23: Policy addressing poverty Participate in policy making at local, regional, national and/or global level to implement programmes and policies to end poverty in all its dimensions.
C24: local
C25: regional
C26: national
C27: global

Sheet SDG2
A1: SDG2: Zero Hunger
A2: Type | B2: Metric and indicator reference | C2: Metric / Indicator | D2: Value (for continuous data) | E2: Yes/No | F2: Evidence1 | G2: Public (Yes/No)
A3: Metric | B3: 2.2 | C3: Campus food waste
A4: Indicator | B4: 2.2.1 | C4: Campus food waste tracking Measure the amount of food waste generated from food served within the university.
C5: whole university
C6: partial measurement
A7: Indicator | B7: 2.2.2 | C7: Campus food waste
C8: Total food waste
C9: Campus population
A10: Metric | B10: 2.3 | C10: Student hunger
A11: Indicator | B11: 2.3.1 | C11: Student food insecurity and hunger Have a programme in place on student food insecurity.
A12: Indicator | B12: 2.3.2 | C12: Students hunger interventions Provide interventions to prevent or alleviate hunger among students (e.g. including supply and access to food banks/pantries)._x000D_
A13: Indicator | B13: 2.3.3 | C13: Sustainable food choices on campus Provide sustainable food choices for all on campus, including vegetarian and vegan food.
C16: all food outlets
C17: selected food outlets
A18: Indicator | B18: 2.3.4 | C18: Healthy and affordable food choices Provide healthy and affordable food choices for all on campus.
C19: all food outlets
C20: selected food outlets
A21: Indicator | B21: 2.3.5 | C21: Staff hunger interventions Provide interventions to prevent or alleviate hunger among members of staff (e.g. including supply and access to food banks/pantries).
A22: Metric | B22: 2.4 | C22: Proportion of graduates in agriculture and aquaculture including sustainability aspects
A23: Indicator | B23: 2.4.1 | C23: Proportion of graduates in agriculture and aquaculture
C24: Number of graduates
C25: Number of graduates from agriculture and aquaculture courses including sustainability aspects
A26: Metric | B26: 2.5 | C26: National hunger
A27: Indicator | B27: 2.5.1 | C27: Access to food security knowledge Provide access on food security and sustainable agriculture and aquaculture knowledge, skills or technology to local farmers and food producers.
C30: free
C31: paid
A32: Indicator | B32: 2.5.2 | C32: Events for local farmers and food producers Provide events for local farmers and food producers to connect and transfer knowledge
C35: free
C36: paid
A37: Indicator | B37: 2.5.3 | C37: University access to local farmers and food producers Provide access to university facilities (e.g. labs, technology, plant stocks) to local farmers and food producers to improve sustainable farming practices.
C40: free
C41: paid
A42: Indicator | B42: 2.5.4 | C42: Sustainable food purchases Prioritise purchase of products from local, sustainable sources.

Sheet SDG3
A1: SDG3: Good Health and Well-being
A2: Type | B2: Metric and indicator reference | C2: Metric / Indicator | D2: Metrica / Indicado Este año solicitamos información del año académico 2024. | E2: Fuente datos UDES | F2: Value (for continuous data) | G2: Yes/No | H2: Evidence1 | I2: Public (Yes/No) | J2: Comentarios" con una longitud máxima de 1000 caracteres
A3: Metric | B3: 3.2 | C3: Number graduating in health professions | D3: Número de graduados en profesiones de la salud | E3: Analitica
A4: Indicator | B4: 3.2.1 | C4: Proportion of graduates in health professions | D4: Proporción de graduados en profesiones de la salud
C5: Number of graduates | D5: Número de graduados
C6: Number of graduates in health professions | D6: Número de graduados en profesiones de la salud
A7: Metric | B7: 3.3 | C7: Collaborations and health services | D7: Colaboraciones y servicios sanitarios | E7: Convenios V Extensión Masira - PURE red de aliandos (DRNI)
A8: Indicator | B8: 3.3.1 | C8: Current collaborations with health institutions Have current collaborations with local, national, or global health institutions to improve health and well-being outcomes. | D8: Colaboraciones actuales con instituciones de salud Tener colaboraciones actuales con instituciones de salud locales, nacionales o globales para mejorar los resultados de salud y bienestar.
C9: local collaboration | D9: Colaboración local
C10: national collaboration | D10: colaboración nacional
C11: global cooperation | D11: Cooperación global
A12: Indicator | B12: 3.3.2 | C12: Health outreach programmes Deliver outreach programmes and projects in the local community (which can include student volunteering programmes) to improve or promote health and well-being including hygiene, nutrition, family planning, sports, exercise, aging well, and other health and well-being related topics. This can also include outreach programmes to displaced or refugee communities local to the institution. | D12: Programas de extensión sanitaria Ofrecer programas y proyectos de divulgación en la comunidad local (que pueden incluir programas de voluntariado estudiantil) para mejorar o promover la salud y el bienestar, incluida la higiene, la nutrición, la planificación familiar, los deportes, el ejercicio, el envejecimiento saludable y otros temas relacionados con la salud y el bienestar. Esto también puede incluir programas de divulgación para las comunidades desplazadas o refugiadas locales de la institución. | E12: VE = Educon Bienestar Institucional
C13: Local communities | D13: Comunidades locales
C14: Disadvantaged people | D14: Personas desfavorecidas
C15: Refugee/immigrant communities | D15: Comunidades de refugiados/inmigrantes
A16: Indicator | B16: 3.3.3 | C16: Shared sports facilities Share sports facilities with the local community, for instance with local schools or with the general public. | D16: Instalaciones deportivas compartidas Compartir instalaciones deportivas con la comunidad local, por ejemplo, con las escuelas locales o con el público en general. | E16: Planta física Bienestar
C17: Free access to all facilities | D17: Acceso gratuito a todas las instalaciones
C18: Free access to some facilities | D18: Acceso gratuito a algunas instalaciones
C19: Charged access | D19: Acceso de pago
A20: Indicator | B20: 3.3.4 | C20: Sexual and reproductive health care services for students Provide students access to sexual and reproductive health-care services including information and education services. | D20: Servicios de atención de salud sexual y reproductiva para estudiantes Proporcionar a los estudiantes acceso a servicios de atención de salud sexual y reproductiva, incluidos servicios de información y educación. | E20: Bienestar institucional Neurotrauma
C21: Free access | D21: Acceso gratuito
C22: Charged access | D22: Acceso de pago
A23: Indicator | B23: 3.3.5 | C23: Mental health support for students Provide students with access to mental health support. | D23: Apoyo a la salud mental para estudiantes Proporcionar a los estudiantes acceso a apoyo de salud mental. | E23: Bienestar institucional Neurotrauma Programa de Psicología
C24: Active promotion of good mental health | D24: Promoción activa de una buena salud mental
C25: Access to (or signposting to) free mental health support | D25: Acceso a (o señalización de) apoyo gratuito de salud mental
C26: Access to (or signposting to) charged mental health support | D26: Acceso (o señalización de) apoyo de salud mental de pago
A27: Indicator | B27: 3.3.6 | C27: Smoke-free policy Have a ‘smoke-free’ policy. | D27: Política libre de humo Tenga una política "libre de humo". | E27: Bienestar institucional Udes verde
C28: Smoking-free campus | D28: Campus libre de humo
C29: Smoking in designated areas | D29: Fumar en áreas designadas
A30: Indicator | B30: 3.3.7 | C30: Mental health support for staff Provide staff with access to mental health support. | D30: Apoyo de salud mental para el personal Proporcionar al personal acceso a apoyo de salud mental. | E30: Bienestar institucional Neurotrauma Programa de Psicología
C31: Active promotion of good mental health | D31: Promoción activa de una buena salud mental
C32: Access to (or signposting to) free mental health support | D32: Acceso a (o señalización de) apoyo gratuito de salud mental
C33: Access to (or signposting to) charged mental health support | D33: Acceso (o señalización de) apoyo de salud mental de pago

Sheet SDG4
A1: SDG4: Quality Education | K1: Gestión interna UDES 2026
A2: Type | B2: Metric and indicator reference | C2: Metric / Indicator | D2: Metrica / Indicador Este año solicitamos información del año académico 2024. | E2: Fuente datos | F2: Value (for continuous data) | G2: Yes/No | H2: Evidence1 | I2: Public (Yes/No) | J2: Comentarios" con una longitud máxima de 1000 caracteres | K2: Coordinación del reporte | L2: Responsable / fuente principal | M2: Dependencia(s) de apoyo | N2: Tipo de requerimiento | O2: Peso oficial THE | P2: Prioridad | Q2: Estado
A3: Metric | B3: 4.2 | C3: Proportion of graduates with teaching qualification | D3: Proporción de titulados con titulación docente | E3: Planeación Institucional | K3: Planeación Institucional | L3: Planeación Institucional | M3: Registro y Control Académico / Vicerrectoría de Enseñanza | N3: Métrica / bloque de evaluación | O3: 0.154 | P3: =IF(ISBLANK(O3),"",IF(O3=0,"Baja",IF(OR(O3>=10%,ISNUMBER(SEARCH("Política",N3))),"Alta","Media"))) -> Alta | Q3: Pendiente
A4: Indicator | B4: 4.2.1 | C4: Proportion of graduates with relevant qualification for teaching | D4: Proporción de titulados con cualificación pertinente para la docencia | K4: Planeación Institucional | L4: Planeación Institucional | M4: Registro y Control Académico / Vicerrectoría de Enseñanza | N4: Dato cuantitativo 2024 | O4: 0.154 | P4: =IF(ISBLANK(O4),"",IF(O4=0,"Baja",IF(OR(O4>=10%,ISNUMBER(SEARCH("Política",N4))),"Alta","Media"))) -> Alta | Q4: Pendiente
C5: Number of graduates | D5: Número de graduados | K5: Planeación Institucional | L5: Planeación Institucional | M5: Registro y Control Académico / Vicerrectoría de Enseñanza | N5: Dato cuantitativo 2024
C6: Number of graduates who gained a qualification that entitled them to teach at primary school level | D6: Número de titulados que han obtenido un título que les da derecho a la enseñanza primaria | K6: Planeación Institucional | L6: Planeación Institucional | M6: Registro y Control Académico / Vicerrectoría de Enseñanza | N6: Dato cuantitativo 2024
A7: Metric | B7: 4.3 | C7: Lifelong learning measures | D7: Medidas de aprendizaje permanente | E7: EDUCON Campus Virtual UDES Biblioteca | K7: Planeación Institucional | L7: EDUCON | M7: Campus Virtual UDES / Biblioteca | N7: Métrica / bloque de evaluación | O7: 0.268 | P7: =IF(ISBLANK(O7),"",IF(O7=0,"Baja",IF(OR(O7>=10%,ISNUMBER(SEARCH("Política",N7))),"Alta","Media"))) -> Alta | Q7: Pendiente
A8: Indicator | B8: 4.3.1 | C8: Public resources (lifelong learning) Provide free access to educational resources for those not studying at the university. | D8: Recursos públicos (aprendizaje permanente) Proporcionar acceso gratuito a recursos educativos para aquellos que no estudian en la universidad. | K8: Planeación Institucional | L8: EDUCON | M8: Campus Virtual UDES / Biblioteca | N8: Evidencia pública | O8: 0.05 | P8: =IF(ISBLANK(O8),"",IF(O8=0,"Baja",IF(OR(O8>=10%,ISNUMBER(SEARCH("Política",N8))),"Alta","Media"))) -> Media | Q8: Pendiente
C9: Free courses leading to certificate or award | D9: Cursos gratuitos que conducen a certificados o premios | K9: Planeación Institucional | L9: EDUCON | M9: Campus Virtual UDES / Biblioteca | N9: Evidencia pública
C10: Free access to campus facilities and equipment | D10: Acceso gratuito a las instalaciones y equipos del campus | K10: Planeación Institucional | L10: EDUCON | M10: Campus Virtual UDES / Biblioteca | N10: Evidencia pública
C11: Free access to online resources | D11: Acceso gratuito a recursos en línea | K11: Planeación Institucional | L11: EDUCON | M11: Campus Virtual UDES / Biblioteca | N11: Evidencia pública
A12: Indicator | B12: 4.3.2 | C12: Public events (lifelong learning) Host educational events at university that are open to the general public. | D12: Eventos públicos (aprendizaje permanente) Organice eventos educativos en la universidad que estén abiertos al público en general. | E12: EDUCON / Graduados Comunicaciones Biblioteca Programas Campus Virtual UDES Talento Humano | K12: Planeación Institucional | L12: EDUCON / Graduados | M12: Comunicaciones / Biblioteca / Programas / Campus Virtual UDES / Talento Humano | N12: Evidencia pública | O12: 0.05 | P12: =IF(ISBLANK(O12),"",IF(O12=0,"Baja",IF(OR(O12>=10%,ISNUMBER(SEARCH("Política",N12))),"Alta","Media"))) -> Media | Q12: Pendiente
C13: Free events | D13: Eventos gratuitos | K13: Planeación Institucional | L13: EDUCON / Graduados | M13: Comunicaciones / Biblioteca / Programas / Campus Virtual UDES / Talento Humano | N13: Evidencia pública
C14: Both changed and free | D14: Cambiado y libre | K14: Planeación Institucional | L14: EDUCON / Graduados | M14: Comunicaciones / Biblioteca / Programas / Campus Virtual UDES / Talento Humano | N14: Evidencia pública
A15: Indicator | B15: 4.3.3 | C15: Vocational training events (lifelong learning) Host events at university that are open to the general public: executive education programmes (this refers to short courses for people who are not attending the university; this specifically excludes courses like MBA) and/or vocational training. | D15: Eventos de formación profesional (aprendizaje permanente) Organizar eventos en la universidad abiertos al público en general: programas de educación ejecutiva (esto se refiere a cursos cortos para personas que no asisten a la universidad; esto excluye específicamente cursos como MBA) y/o formación profesional. | E15: EDUCON / Graduados Desarrollo Profesoral Comunicaciones Biblioteca Programas Campus Virtual UDES Talento Humano | K15: Planeación Institucional | L15: EDUCON / Graduados | M15: Desarrollo Profesoral / Comunicaciones / Biblioteca / Programas / Campus Virtual UDES / Talento Humano | N15: Evidencia pública | O15: 0.05 | P15: =IF(ISBLANK(O15),"",IF(O15=0,"Baja",IF(OR(O15>=10%,ISNUMBER(SEARCH("Política",N15))),"Alta","Media"))) -> Media | Q15: Pendiente
C16: Ad hoc | D16: Ad hoc | K16: Planeación Institucional | L16: EDUCON / Graduados | M16: Desarrollo Profesoral / Comunicaciones / Biblioteca / Programas / Campus Virtual UDES / Talento Humano | N16: Evidencia pública
C17: On programmed basis | D17: De forma programada | K17: Planeación Institucional | L17: EDUCON / Graduados | M17: Desarrollo Profesoral / Comunicaciones / Biblioteca / Programas / Campus Virtual UDES / Talento Humano | N17: Evidencia pública
A18: Indicator | B18: 4.3.4 | C18: Education outreach activities beyond campus Undertake educational outreach activities (e.g. tailored lectures or demonstrations) beyond campus – in local schools, in the community. This can include voluntary student-run schemes. | D18: Actividades de divulgación educativa más allá del campus Emprender actividades de divulgación educativa (por ejemplo, conferencias o demostraciones personalizadas) más allá del campus, en las escuelas locales, en la comunidad. Esto puede incluir esquemas voluntarios dirigidos por estudiantes. | E18: EDUCON / Graduados Desarrollo Profesoral Comunicaciones Biblioteca Programas Campus Virtual UDES Talento Humano | K18: Planeación Institucional | L18: EDUCON / Graduados | M18: Desarrollo Profesoral / Comunicaciones / Biblioteca / Programas / Campus Virtual UDES / Talento Humano | N18: Evidencia pública | O18: 0.05 | P18: =IF(ISBLANK(O18),"",IF(O18=0,"Baja",IF(OR(O18>=10%,ISNUMBER(SEARCH("Política",N18))),"Alta","Media"))) -> Media | Q18: Pendiente
C19: Ad hoc | D19: Ad hoc | K19: Planeación Institucional | L19: EDUCON / Graduados | M19: Desarrollo Profesoral / Comunicaciones / Biblioteca / Programas / Campus Virtual UDES / Talento Humano | N19: Evidencia pública
C20: On programmed basis | D20: De forma programada | K20: Planeación Institucional | L20: EDUCON / Graduados | M20: Desarrollo Profesoral / Comunicaciones / Biblioteca / Programas / Campus Virtual UDES / Talento Humano | N20: Evidencia pública
A21: Indicator | B21: 4.3.5 | C21: Lifelong learning access policy A policy that ensures that access to these activities is accessible to all, regardless of ethnicity, religion, disability immigration status or gender. | D21: Política de acceso al aprendizaje permanente Una política que garantice que el acceso a estas actividades sea accesible para todos, independientemente de su origen étnico, religión, discapacidad, estado migratorio o género. | E21: Vicerrectoría de Enseñanza Vicerrectoría de Extensión | K21: Planeación Institucional | L21: Vicerrectoría de Enseñanza | M21: Vicerrectoría de Extensión | N21: Política / evidencia pública | O21: 0.068 | P21: =IF(ISBLANK(O21),"",IF(O21=0,"Baja",IF(OR(O21>=10%,ISNUMBER(SEARCH("Política",N21))),"Alta","Media"))) -> Alta | Q21: Pendiente
A22: Metric | B22: 4.4 | C22: Proportion of first-generation students | D22: Proporción de estudiantes de primera generación | E22: Planeación Institucional | K22: Planeación Institucional | L22: Planeación Institucional | M22: Registro y Control Académico | N22: Métrica / bloque de evaluación | O22: 0.308 | P22: =IF(ISBLANK(O22),"",IF(O22=0,"Baja",IF(OR(O22>=10%,ISNUMBER(SEARCH("Política",N22))),"Alta","Media"))) -> Alta | Q22: Pendiente
A23: Indicator | B23: 4.4.1 | C23: Proportion of first-generation students | D23: Proporción de estudiantes de primera generación | K23: Planeación Institucional | L23: Planeación Institucional | M23: Registro y Control Académico | N23: Dato cuantitativo 2024 | O23: 0.308 | P23: =IF(ISBLANK(O23),"",IF(O23=0,"Baja",IF(OR(O23>=10%,ISNUMBER(SEARCH("Política",N23))),"Alta","Media"))) -> Alta | Q23: Pendiente
C24: Number of students starting a degree | D24: Número de estudiantes que inician una carrera | K24: Planeación Institucional | L24: Planeación Institucional | M24: Registro y Control Académico | N24: Dato cuantitativo 2024
C25: Number of first-generation students starting a degree | D25: Número de estudiantes de primera generación que comienzan una carrera | K25: Planeación Institucional | L25: Planeación Institucional | M25: Registro y Control Académico | N25: Dato cuantitativo 2024

Sheet SDG5
A1: SDG5: Gender Equality | K1: Gestión interna UDES 2026
A2: Type | B2: Metric and indicator reference | C2: Metric / Indicator | D2: Métrica / Indicador Este año solicitamos información del año académico 2024. | E2: Fuente datos | F2: Value (for continuous data) | G2: Yes/No | H2: Evidence1 | I2: Public (Yes/No) | J2: Comentarios" con una longitud máxima de 1000 caracteres | K2: Coordinación del reporte | L2: Responsable / fuente principal | M2: Dependencia(s) de apoyo | N2: Tipo de requerimiento | O2: Peso oficial THE | P2: Prioridad | Q2: Estado
A3: Metric | B3: 5.2 | C3: Proportion of first-generation female students | D3: Proporción de alumnas de primera generación | E3: Planeación Institucional | K3: Planeación Institucional | L3: Planeación Institucional | M3: Registro y Control Académico | N3: Métrica / bloque de evaluación | O3: 0.154 | P3: =IF(ISBLANK(O3),"",IF(O3=0,"Baja",IF(OR(O3>=10%,ISNUMBER(SEARCH("Política",N3))),"Alta","Media"))) -> Alta | Q3: Pendiente
A4: Indicator | B4: 5.2.1 | C4: Proportion of women first-generation | D4: Proporción de mujeres de primera generación | K4: Planeación Institucional | L4: Planeación Institucional | M4: Registro y Control Académico | N4: Dato cuantitativo 2024 | O4: 0.154 | P4: =IF(ISBLANK(O4),"",IF(O4=0,"Baja",IF(OR(O4>=10%,ISNUMBER(SEARCH("Política",N4))),"Alta","Media"))) -> Alta | Q4: Pendiente
C5: Number of women starting a degree | D5: Número de mujeres que comienzan una carrera | K5: Planeación Institucional | L5: Planeación Institucional | M5: Registro y Control Académico | N5: Dato cuantitativo 2024
C6: Number of first-generation women starting a degree | D6: Número de mujeres de primera generación que comienzan una carrera | K6: Planeación Institucional | L6: Planeación Institucional | M6: Registro y Control Académico | N6: Dato cuantitativo 2024
A7: Metric | B7: 5.3 | C7: Student access measures | D7: Medidas de acceso de los estudiantes | E7: Planeación Institucional | K7: Planeación Institucional | L7: Planeación Institucional | M7: Vicerrectoría de Enseñanza / Registro y Control Académico | N7: Métrica / bloque de evaluación | O7: 0.154 | P7: =IF(ISBLANK(O7),"",IF(O7=0,"Baja",IF(OR(O7>=10%,ISNUMBER(SEARCH("Política",N7))),"Alta","Media"))) -> Alta | Q7: Pendiente
A8: Indicator | B8: 5.3.1 | C8: Tracking access measures Systematically measure and track women’s application rate, acceptance or entry rate. | D8: Seguimiento de las medidas de acceso Medir y rastrear sistemáticamente la tasa de solicitud, aceptación o entrada de las mujeres. | K8: Planeación Institucional | L8: Planeación Institucional | M8: Vicerrectoría de Enseñanza / Registro y Control Académico | N8: Evidencia pública | O8: 0.016 | P8: =IF(ISBLANK(O8),"",IF(O8=0,"Baja",IF(OR(O8>=10%,ISNUMBER(SEARCH("Política",N8))),"Alta","Media"))) -> Media | Q8: Pendiente
A9: Indicator | B9: 5.3.2 | C9: Policy for women applications and entry Have a policy (e.g. an Access and Participation plan) addressing women’s applications, acceptance, entry, and participation at the university. | D9: Política para las solicitudes y la entrada de mujeres Tener una política (por ejemplo, un plan de acceso y participación) que aborde las solicitudes, la aceptación, el ingreso y la participación de las mujeres en la universidad. | E9: Vicerrectoría de Enseñanza Planeación Institucional | K9: Planeación Institucional | L9: Planeación Institucional | M9: Vicerrectoría de Enseñanza | N9: Política / evidencia pública | O9: 0.046 | P9: =IF(ISBLANK(O9),"",IF(O9=0,"Baja",IF(OR(O9>=10%,ISNUMBER(SEARCH("Política",N9))),"Alta","Media"))) -> Alta | Q9: Pendiente
A10: Indicator | B10: 5.3.3 | C10: Women’s access schemes Provide women’s access schemes, including mentoring, scholarships, or other provision | D10: Planes de acceso de las mujeres Proporcionar esquemas de acceso para mujeres, incluida tutoría, becas u otras disposiciones | E10: Vicerrectoría de Enseñanza Vicerrectoría de Investigaciones (Orquidea de la ciencia, otras mujeres), Conv Minciencias Planeación Institucional Credito y Cartera DRNI | K10: Planeación Institucional | L10: Planeación Institucional | M10: Vicerrectoría de Enseñanza / Vicerrectoría de Investigaciones (Orquidea de la ciencia, otras mujeres), Conv Minciencias / Credito y Cartera / DRNI | N10: Evidencia pública | O10: 0.046 | P10: =IF(ISBLANK(O10),"",IF(O10=0,"Baja",IF(OR(O10>=10%,ISNUMBER(SEARCH("Política",N10))),"Alta","Media"))) -> Media | Q10: Pendiente
C11: Mentoring | D11: Tutoría | K11: Planeación Institucional | L11: Planeación Institucional | M11: Vicerrectoría de Enseñanza / Vicerrectoría de Investigaciones (Orquidea de la ciencia, otras mujeres), Conv Minciencias / Credito y Cartera / DRNI | N11: Evidencia pública
C12: Scholarship | D12: Beca | K12: Planeación Institucional | L12: Planeación Institucional | M12: Vicerrectoría de Enseñanza / Vicerrectoría de Investigaciones (Orquidea de la ciencia, otras mujeres), Conv Minciencias / Credito y Cartera / DRNI | N12: Evidencia pública
C13: Other provision | D13: Otras disposiciones | K13: Planeación Institucional | L13: Planeación Institucional | M13: Vicerrectoría de Enseñanza / Vicerrectoría de Investigaciones (Orquidea de la ciencia, otras mujeres), Conv Minciencias / Credito y Cartera / DRNI | N13: Evidencia pública
A14: Indicator | B14: 5.3.4 | C14: Women’s application in underrepresented subjects Encourage applications by women in subjects where they are underrepresented. Through university outreach or through collaboration with other universities, community groups, government or NGOs in regional or national campaigns. | D14: Solicitud de las mujeres en materias subrepresentadas Fomentar las solicitudes de mujeres en materias en las que están subrepresentadas. A través de la extensión universitaria o mediante la colaboración con otras universidades, grupos comunitarios, gobiernos u ONG en campañas regionales o nacionales. | E14: Vicerrectoría de Extensión Vicerrectoría de Enseñanza Vicerrectoría de Investigaciones (Orquidea de la ciencia, otras mujeres), Conv Minciencias Planeación Institucional Credito y Cartera DRNI Mujer y Hogar / Miudes | K14: Planeación Institucional | L14: Planeación Institucional | M14: Vicerrectoría de Extensión / Vicerrectoría de Enseñanza / Vicerrectoría de Investigaciones (Orquidea de la ciencia, otras mujeres), Conv Minciencias / Credito y Cartera / DRNI / Mujer y Hogar / Miudes | N14: Evidencia pública | O14: 0.046 | P14: =IF(ISBLANK(O14),"",IF(O14=0,"Baja",IF(OR(O14>=10%,ISNUMBER(SEARCH("Política",N14))),"Alta","Media"))) -> Media | Q14: Pendiente
C15: through university outreach | D15: a través de la extensión universitaria | K15: Planeación Institucional | L15: Planeación Institucional | M15: Vicerrectoría de Extensión / Vicerrectoría de Enseñanza / Vicerrectoría de Investigaciones (Orquidea de la ciencia, otras mujeres), Conv Minciencias / Credito y Cartera / DRNI / Mujer y Hogar / Miudes | N15: Evidencia pública
C16: through collaboration with other universities and/or community groups and/or government and/or NGOs in regional or national campaigns | D16: a través de la colaboración con otras universidades y/o grupos comunitarios y/o el gobierno y/o las ONG en campañas regionales o nacionales | K16: Planeación Institucional | L16: Planeación Institucional | M16: Vicerrectoría de Extensión / Vicerrectoría de Enseñanza / Vicerrectoría de Investigaciones (Orquidea de la ciencia, otras mujeres), Conv Minciencias / Credito y Cartera / DRNI / Mujer y Hogar / Miudes | N16: Evidencia pública
A17: Metric | B17: 5.4 | C17: Proportion of senior female academics | D17: Proporción de mujeres académicas de alto nivel | E17: Planeación Institucional | K17: Planeación Institucional | L17: Planeación Institucional | M17: Talento Humano | N17: Métrica / bloque de evaluación | O17: 0.154 | P17: =IF(ISBLANK(O17),"",IF(O17=0,"Baja",IF(OR(O17>=10%,ISNUMBER(SEARCH("Política",N17))),"Alta","Media"))) -> Alta | Q17: Pendiente
A18: Indicator | B18: 5.4.1 | C18: Proportion of senior female academics | D18: Proporción de mujeres académicas de alto nivel | K18: Planeación Institucional | L18: Planeación Institucional | M18: Talento Humano | N18: Dato cuantitativo 2024 | O18: 0.154 | P18: =IF(ISBLANK(O18),"",IF(O18=0,"Baja",IF(OR(O18>=10%,ISNUMBER(SEARCH("Política",N18))),"Alta","Media"))) -> Alta | Q18: Pendiente
C19: Number of senior academic staff | D19: Número de personal académico superior | K19: Planeación Institucional | L19: Planeación Institucional | M19: Talento Humano | N19: Dato cuantitativo 2024
C20: Number of female senior academic staff | D20: Número de mujeres en el personal académico superior | K20: Planeación Institucional | L20: Planeación Institucional | M20: Talento Humano | N20: Dato cuantitativo 2024
A21: Metric | B21: 5.5 | C21: Proportion of women receiving degrees | D21: Proporción de mujeres que reciben títulos | E21: Planeación Institucional | K21: Planeación Institucional | L21: Planeación Institucional | M21: Registro y Control Académico | N21: Métrica / bloque de evaluación | O21: 0.115 | P21: =IF(ISBLANK(O21),"",IF(O21=0,"Baja",IF(OR(O21>=10%,ISNUMBER(SEARCH("Política",N21))),"Alta","Media"))) -> Alta | Q21: Pendiente
A22: Indicator | B22: 5.5.1 | C22: Proportion of female degrees awarded | D22: Proporción de títulos femeninos otorgados | K22: Planeación Institucional | L22: Planeación Institucional | M22: Registro y Control Académico | N22: Dato cuantitativo 2024 | O22: 0.115 | P22: =IF(ISBLANK(O22),"",IF(O22=0,"Baja",IF(OR(O22>=10%,ISNUMBER(SEARCH("Política",N22))),"Alta","Media"))) -> Alta | Q22: Pendiente
C23: Number of graduates: Total | D23: Número de graduados: Total | K23: Planeación Institucional | L23: Planeación Institucional | M23: Registro y Control Académico | N23: Dato cuantitativo 2024
C24: Number of graduates by subject area (STEM, Medicine, Arts & Humanities / Social Sciences): Total | D24: Número de graduados por área temática (STEM, Medicina, Artes y Humanidades / Ciencias Sociales): Total | K24: Planeación Institucional | L24: Planeación Institucional | M24: Registro y Control Académico | N24: Dato cuantitativo 2024
C25: Number of graduates: STEM | D25: Número de graduados: STEM | K25: Planeación Institucional | L25: Planeación Institucional | M25: Registro y Control Académico | N25: Dato cuantitativo 2024
C26: Number of graduates: Medicine | D26: Número de graduados: Medicina | K26: Planeación Institucional | L26: Planeación Institucional | M26: Registro y Control Académico | N26: Dato cuantitativo 2024
C27: Number of graduates: Arts & Humanities / Social Sciences | D27: Número de graduados: Artes y Humanidades / Ciencias Sociales | K27: Planeación Institucional | L27: Planeación Institucional | M27: Registro y Control Académico | N27: Dato cuantitativo 2024
C28: Number of female graduates by subject area (STEM, Medicine, Arts & Humanities / Social Sciences): Total | D28: Número de mujeres graduadas por área temática (STEM, Medicina, Artes y Humanidades / Ciencias Sociales): Total | K28: Planeación Institucional | L28: Planeación Institucional | M28: Registro y Control Académico | N28: Dato cuantitativo 2024
C29: Number of female graduates: STEM | D29: Número de mujeres graduadas: STEM | K29: Planeación Institucional | L29: Planeación Institucional | M29: Registro y Control Académico | N29: Dato cuantitativo 2024
C30: Number of female graduates: Medicine | D30: Número de mujeres graduadas: Medicina | K30: Planeación Institucional | L30: Planeación Institucional | M30: Registro y Control Académico | N30: Dato cuantitativo 2024
C31: Number of female graduates: Arts & Humanities / Social Sciences | D31: Número de mujeres graduadas: Artes y Humanidades / Ciencias Sociales | K31: Planeación Institucional | L31: Planeación Institucional | M31: Registro y Control Académico | N31: Dato cuantitativo 2024
A32: Metric | B32: 5.6 | C32: Women’s progress measures | D32: Medidas de progreso de las mujeres | K32: Planeación Institucional | N32: Métrica / bloque de evaluación | O32: 0.153 | P32: =IF(ISBLANK(O32),"",IF(O32=0,"Baja",IF(OR(O32>=10%,ISNUMBER(SEARCH("Política",N32))),"Alta","Media"))) -> Alta | Q32: Pendiente
A33: Indicator | B33: 5.6.1 | C33: Policy of non-discrimination against women Have a policy of non-discrimination against women | D33: Política de no discriminación contra la mujer Tener una política de no discriminación contra las mujeres | E33: Vicerrectoría de Enseñanza Talento Humano | K33: Planeación Institucional | L33: Vicerrectoría de Enseñanza | M33: Talento Humano | N33: Política / evidencia pública | O33: 0.0195 | P33: =IF(ISBLANK(O33),"",IF(O33=0,"Baja",IF(OR(O33>=10%,ISNUMBER(SEARCH("Política",N33))),"Alta","Media"))) -> Alta | Q33: Pendiente
A34: Indicator | B34: 5.6.2 | C34: Non-discrimination policies for transgender Have a policy of non-discrimination for transgender people. | D34: Políticas de no discriminación para las personas transgénero Tener una política de no discriminación para las personas transgénero. | E34: Vicerrectoría de Enseñanza Talento Humano | K34: Planeación Institucional | L34: Vicerrectoría de Enseñanza | M34: Talento Humano | N34: Política / evidencia pública | O34: 0.0195 | P34: =IF(ISBLANK(O34),"",IF(O34=0,"Baja",IF(OR(O34>=10%,ISNUMBER(SEARCH("Política",N34))),"Alta","Media"))) -> Alta | Q34: Pendiente
A35: Indicator | B35: 5.6.3 | C35: Maternity policy Have a maternity policy that support women’s participation. | D35: Política de maternidad Tener una política de maternidad que apoye la participación de las mujeres. | E35: Vicerrectoría de Enseñanza Talento Humano | K35: Planeación Institucional | L35: Vicerrectoría de Enseñanza | M35: Talento Humano | N35: Política / evidencia pública | O35: 0.0095 | P35: =IF(ISBLANK(O35),"",IF(O35=0,"Baja",IF(OR(O35>=10%,ISNUMBER(SEARCH("Política",N35))),"Alta","Media"))) -> Alta | Q35: Pendiente
A36: Indicator | B36: 5.6.4 | C36: Childcare facilities for students Have accessible childcare facilities for students which allow recent mothers to attend university courses. | D36: Guarderías para estudiantes Tener guarderías accesibles para estudiantes que permitan a las madres recién nacidas asistir a la universidad Cursos. | E36: Vicerrectoría de Enseñanza Talento Humano Bienestar | K36: Planeación Institucional | L36: Vicerrectoría de Enseñanza | M36: Talento Humano / Bienestar | N36: Evidencia pública | O36: 0.019 | P36: =IF(ISBLANK(O36),"",IF(O36=0,"Baja",IF(OR(O36>=10%,ISNUMBER(SEARCH("Política",N36))),"Alta","Media"))) -> Media | Q36: Pendiente
C37: Free | D37: Gratis | K37: Planeación Institucional | L37: Vicerrectoría de Enseñanza | M37: Talento Humano / Bienestar | N37: Evidencia pública
C38: Paid | D38: Pagado | K38: Planeación Institucional | L38: Vicerrectoría de Enseñanza | M38: Talento Humano / Bienestar | N38: Evidencia pública
A39: Indicator | B39: 5.6.5 | C39: Childcare facilities for staff and faculty Have childcare facilities for staff and faculty | D39: Instalaciones de cuidado infantil para el personal y la facultad Tener instalaciones de cuidado infantil para el personal y la facultad. | E39: Vicerrectoría de Enseñanza Talento Humano Bienestar | K39: Planeación Institucional | L39: Vicerrectoría de Enseñanza | M39: Talento Humano / Bienestar | N39: Evidencia pública | O39: 0.019 | P39: =IF(ISBLANK(O39),"",IF(O39=0,"Baja",IF(OR(O39>=10%,ISNUMBER(SEARCH("Política",N39))),"Alta","Media"))) -> Media | Q39: Pendiente
C40: Free | D40: Gratis | K40: Planeación Institucional | L40: Vicerrectoría de Enseñanza | M40: Talento Humano / Bienestar | N40: Evidencia pública
C41: Paid | D41: Pagado | K41: Planeación Institucional | L41: Vicerrectoría de Enseñanza | M41: Talento Humano / Bienestar | N41: Evidencia pública
A42: Indicator | B42: 5.6.6 | C42: Women’s mentoring schemes Have women’s mentoring schemes, in which at least 10% of female students participate. | D42: Programas de tutoría para mujeres Tener programas de tutoría para mujeres, en los que participe al menos el 10% de las estudiantes. | E42: Vicerrectoría de Enseñanza Talento Humano Bienestar Desarrollo Profesoral Desarrollo Estudiantil Campus Virtual UDES Vicerrectoría de Extensión Programa de Psicología y de Salud | K42: Planeación Institucional | L42: Vicerrectoría de Enseñanza | M42: Talento Humano / Bienestar / Desarrollo Profesoral / Desarrollo Estudiantil / Campus Virtual UDES / Vicerrectoría de Extensión / Programa de Psicología y de Salud | N42: Evidencia pública | O42: 0.019 | P42: =IF(ISBLANK(O42),"",IF(O42=0,"Baja",IF(OR(O42>=10%,ISNUMBER(SEARCH("Política",N42))),"Alta","Media"))) -> Media | Q42: Pendiente
A43: Indicator | B43: 5.6.7 | C43: Track women’s graduation rate Have measurement or tracking of women’s likelihood of graduating compared to men’s, and schemes in place to close any gap. | D43: Seguimiento de la tasa de graduación de las mujeres Tener una medición o seguimiento de la probabilidad de graduación de las mujeres en comparación con la de los hombres, y esquemas para cerrar cualquier brecha. | E43: Planeación Institucional | K43: Planeación Institucional | L43: Planeación Institucional | M43: Registro y Control Académico | N43: Evidencia pública | O43: 0.019 | P43: =IF(ISBLANK(O43),"",IF(O43=0,"Baja",IF(OR(O43>=10%,ISNUMBER(SEARCH("Política",N43))),"Alta","Media"))) -> Media | Q43: Pendiente
A44: Indicator | B44: 5.6.8 | C44: Policies protecting those reporting discrimination Have a policy that protects those reporting discrimination from educational or employment disadvantage | D44: Políticas que protegen a quienes denuncian discriminación Tener una política que proteja a quienes denuncian discriminación de desventajas educativas o laborales | E44: Vicerrectoría de Enseñanza Talento Humano Bienestar | K44: Planeación Institucional | L44: Vicerrectoría de Enseñanza | M44: Talento Humano / Bienestar | N44: Política / evidencia pública | O44: 0.019 | P44: =IF(ISBLANK(O44),"",IF(O44=0,"Baja",IF(OR(O44>=10%,ISNUMBER(SEARCH("Política",N44))),"Alta","Media"))) -> Alta | Q44: Pendiente
A45: Indicator | B45: 5.6.9 | C45: Paternity policy Have a paternity policy that supports women’s participation by ensuring that fathers can participate in childcare duties | D45: Política de paternidad Tener una política de paternidad que apoye la participación de las mujeres al garantizar que los padres puedan participar en las tareas de cuidado de los niños. | E45: Vicerrectoría de Enseñanza Talento Humano Bienestar | K45: Planeación Institucional | L45: Vicerrectoría de Enseñanza | M45: Talento Humano / Bienestar | N45: Política / evidencia pública | O45: 0.0095 | P45: =IF(ISBLANK(O45),"",IF(O45=0,"Baja",IF(OR(O45>=10%,ISNUMBER(SEARCH("Política",N45))),"Alta","Media"))) -> Alta | Q45: Pendiente

Sheet SDG6
A1: SDG6: Clean Water and Sanitation
A2: Type | B2: Metric and indicator reference | C2: Metric / Indicator | D2: Value (for continuous data) | E2: Yes/No | F2: Evidence1 | G2: Public (Yes/No)
A3: Metric | B3: 6.2 | C3: Water consumption per person
A4: Indicator | B4: 6.2.1 | C4: Measure the total volume of water used in the university that is taken from mains supply, desalinated, or extracted from rivers, lakes, or aquifers?
C5: Whole university
C6: Partial measurement
A7: Indicator | B7: 6.2.2 | C7: Water consumption per person
C8: Volume of water used in the university: Inbound (treated/extracted water)
C9: Campus population
A10: Metric | B10: 6.3 | C10: Water usage and care
A11: Indicator | B11: 6.3.1 | C11: Wastewater treatment A process in place to treat wastewater.
A12: Indicator | B12: 6.3.2 | C12: Preventing water system pollution Processes to prevent polluted water entering the water system, including pollution caused by accidents and incidents at the university.
A13: Indicator | B13: 6.3.3 | C13: Free drinking water provided Provide free drinking water for students, staff and/or visitors (e.g. drinking water fountains).
A14: Indicator | B14: 6.3.4 | C14: Water-conscious building standards Apply building standards to minimise water use
A15: Indicator | B15: 6.3.5 | C15: Water-conscious planting Plant landscapes to minimise water usage. (e.g. use drought-tolerant plants)
A16: Metric | B16: 6.4 | C16: Water reuse
A17: Indicator | B17: 6.4.1 | C17: Water reuse policy Have a policy to maximise water reuse across the university?
A18: Indicator | B18: 6.4.2 | C18: Water reuse measurement Measure the reuse of water across the university?
A19: Metric | B19: 6.5 | C19: Water in the community
A20: Indicator | B20: 6.5.1 | C20: Water management educational opportunities Provide educational opportunities for local communities to learn about good water management
C21: Free
C22: Paid
A23: Indicator | B23: 6.5.2 | C23: Off-campus water conservation support Support practical water conservation off campus
A24: Indicator | B24: 6.5.3 | C24: Sustainable water extraction on campus Where water is extracted (for example from aquifers, lakes or rivers) utilise sustainable water extraction technologies on associated university grounds on and off campus.
A25: Indicator | B25: 6.5.4 | C25: Cooperation on water security Cooperate with local, regional, national, or global governments on water security.
C26: Local
C27: Regional
C28: National
A29: Indicator | B29: 6.5.5 | C29: Promoting conscious water usage on campus Actively promote conscious water usage on campus,
A30: Indicator | B30: 6.5.6 | C30: Promoting conscious water usage in the wider community. Actively promote conscious water usage in the wider community

Sheet SDG7
B1: SDG7: Affordable and Clean Energy
A2: Type | B2: Metric and indicator reference | C2: Metric / Indicator | D2: Value (for continuous data) | E2: Yes/No | F2: Evidence1 | G2: Public (Yes/No)
A3: Metric | B3: 7.2 | C3: University measures towards affordable and clean energy
A4: Indicator | B4: 7.2.1 | C4: Energy-efficient renovation and building Have a policy in place for ensuring all renovations or new builds are following energy efficiency standards
A5: Indicator | B5: 7.2.2 | C5: Upgrade buildings to higher energy efficiency Have plans to upgrade existing buildings to higher energy efficiency
A6: Indicator | B6: 7.2.3 | C6: Carbon reduction and emission reduction process Have a process for carbon management and reducing carbon dioxide emissions
A7: Indicator | B7: 7.2.4 | C7: Plan to reduce energy consumption Have an energy efficiency plan in place to reduce overall energy consumption
A8: Indicator | B8: 7.2.5 | C8: Energy wastage identification Undergo energy reviews to identify areas where energy waste is highest
A9: Indicator | B9: 7.2.6 | C9: Divestment policy Have a policy on divesting investments from carbon-intensive energy industries notably coal and oil
A10: Metric | B10: 7.3 | C10: Energy use density
A11: Indicator | B11: 7.3.1 | C11: Energy usage per sqm
C12: Total energy used
C13: University floor space
A14: Metric | B14: 7.4 | C14: Energy and the community
A15: Indicator | B15: 7.4.1 | C15: Local community outreach for energy efficiency Provide programmes for local community to learn about importance of energy efficiency and clean energy
A16: Indicator | B16: 7.4.2 | C16: 100% renewable energy pledge Promote a public pledge toward 100% renewable energy beyond the university
A17: Indicator | B17: 7.4.3 | C17: Energy efficiency services for industry Provide direct services to local industry aimed at improving energy efficiency and clean energy (energy efficiency assessments, workshops, research renewable energy options)
C18: Free
C19: Paid
A20: Indicator | B20: 7.4.4 | C20: Policy development for clean energy technology Inform and support governments in clean energy and energy-efficient technology policy development
C21: Local
C22: Regional
C23: National
C24: Global
A25: Indicator | B25: 7.4.5 | C25: Assistance to low-carbon innovation Provide assistance for start-ups that foster and support a low-carbon economy or technology
B26: 7.5 | C26: Low-carbon energy use
C27: Total energy used
C28: Total energy used from low-carbon sources

Sheet SDG8
A1: SDG8: Decent Work and Economic Growth
A2: Type | B2: Metric and indicator reference | C2: Metric / Indicator | D2: Value (for continuous data) | E2: Yes/No | F2: Evidence1 | G2: Public (Yes/No)
A3: Metric | B3: 8.2 | C3: Employment practice
A4: Indicator | B4: 8.2.1 | C4: Employment practice living wage Pay all staff and faculty at least the living wage, defined as the local living wage (if government defines this) or the local financial poverty indicator for a family of four (expressed as an hourly wage)
A5: Indicator | B5: 8.2.2 | C5: Employment practice unions Recognize unions (freedom of association & collective bargaining) for all, including women & international staff
A6: Indicator | B6: 8.2.3 | C6: Employment policy on discrimination Have a policy on ending discrimination in the workplace (including discrimination based on religion, sexuality, gender, age, or refugee status)
A7: Indicator | B7: 8.2.4 | C7: Employment policy modern slavery Have a policy commitment against forced labour, modern slavery, human trafficking and child labour
A8: Indicator | B8: 8.2.5 | C8: Employment practice equivalent rights outsourcing Have a policy on guaranteeing equivalent rights of workers when outsourcing activities to third parties
A9: Indicator | B9: 8.2.6 | C9: Employment policy pay scale equity Have a policy on pay scale equity including a commitment to measurement and elimination of gender pay gaps
A10: Indicator | B10: 8.2.7 | C10: Tracking pay scale for gender equity Measurement or tracking pay scale gender equity
A11: Indicator | B11: 8.2.8 | C11: Employment practice appeal process Have a process for employees to appeal on employee rights and/or pay
A12: Indicator | B12: 8.2.9 | C12: Employment practice labour rights Recognise labour rights (freedom of association and collective bargaining) for all, including women and international staff
A13: Metric | B13: 8.3 | C13: Expenditure per employee
A14: Indicator | B14: 8.3.1 | C14: Expenditure per employee
C15: Number of employees
C16: University expenditure
A17: Metric | B17: 8.4 | C17: Proportion of students taking work placements
A18: Indicator | B18: 8.4.1 | C18: Proportion of students with work placements
C19: Number of students
C20: Number of students with work placements for more than a month
A21: Metric | B21: 8.5 | C21: Proportion of employees on secure contracts
A22: Indicator | B22: 8.5.1 | C22: Proportion of employees on secure contracts
C23: Number of employees
C24: Number of employees on contracts of over 24 months

Sheet SDG9
A1: SDG9: Industry, Innovation and Infrastructure
A2: Type | B2: Metric and indicator reference | C2: Metric / Indicator | D2: Value (for continuous data) | E2: Yes/No | F2: Evidence1 | G2: Public (Yes/No)
A3: Metric | B3: 9.3 | C3: University spin offs
A4: Indicator | B4: 9.3.1 | C4: Number of university spin offs
C5: Number of university spin-offs
A6: Metric | B6: 9.4 | C6: Research income from industry and commerce
A7: Indicator | B7: 9.4.1 | C7: Research income from industry and commerce per academic staff
C8: Research income from industry and commerce by subject area: STEM
C9: Research income from industry and commerce by subject area: Medicine
C10: Research income from industry and commerce by subject area: Arts & Humanities / Social sciences
C11: Number of academic staff by subject area: STEM
C12: Number of academic staff by subject area: Medicine
C13: Number of academic staff by subject area: Arts & Humanities / Social sciences

Sheet SDG10
A1: SDG10: Reduced Inequalities | K1: Gestión interna UDES 2026
A2: Type | B2: Metric and indicator reference | C2: Metric / Indicator | D2: Metrica / Indicador Este año solicitamos información del año académico 2024. | E2: Fuente datos | F2: Value (for continuous data) | G2: Yes/No | H2: Evidence1 | I2: Public (Yes/No) | J2: Comentarios" con una longitud máxima de 1000 caracteres | K2: Coordinación del reporte | L2: Responsable / fuente principal | M2: Dependencia(s) de apoyo | N2: Tipo de requerimiento | O2: Peso oficial THE | P2: Prioridad | Q2: Estado
A3: Metric | B3: 10.2 | C3: First-generation students | D3: Estudiantes de primera generación | E3: Planeación Institucional | K3: Planeación Institucional | L3: Planeación Institucional | M3: Registro y Control Académico | N3: Métrica / bloque de evaluación | O3: 0.155 | P3: =IF(ISBLANK(O3),"",IF(O3=0,"Baja",IF(OR(O3>=10%,ISNUMBER(SEARCH("Política",N3))),"Alta","Media"))) -> Alta | Q3: Pendiente
A4: Indicator | B4: 10.2.1 | C4: Proportion of first-generation students | D4: Proporción de estudiantes de primera generación | K4: Planeación Institucional | L4: Planeación Institucional | M4: Registro y Control Académico | N4: Dato cuantitativo 2024 | O4: 0.155 | P4: =IF(ISBLANK(O4),"",IF(O4=0,"Baja",IF(OR(O4>=10%,ISNUMBER(SEARCH("Política",N4))),"Alta","Media"))) -> Alta | Q4: Pendiente
C5: Number of students starting a degree | D5: Número de estudiantes que inician una carrera | K5: Planeación Institucional | L5: Planeación Institucional | M5: Registro y Control Académico | N5: Dato cuantitativo 2024
C6: Number of first-generation students starting a degree | D6: Número de estudiantes de primera generación que comienzan una carrera | K6: Planeación Institucional | L6: Planeación Institucional | M6: Registro y Control Académico | N6: Dato cuantitativo 2024
A7: Metric | B7: 10.3 | C7: International students from developing countries | D7: Estudiantes internacionales de países en desarrollo | E7: Planeación Institucional DRNI | K7: Planeación Institucional | L7: Planeación Institucional | M7: DRNI | N7: Métrica / bloque de evaluación | O7: 0.155 | P7: =IF(ISBLANK(O7),"",IF(O7=0,"Baja",IF(OR(O7>=10%,ISNUMBER(SEARCH("Política",N7))),"Alta","Media"))) -> Alta | Q7: Pendiente
A8: Indicator | B8: 10.3.1 | C8: Proportion of international students from developing countries | D8: Proporción de estudiantes internacionales de países en desarrollo | K8: Planeación Institucional | L8: Planeación Institucional | M8: DRNI | N8: Dato cuantitativo 2024 | O8: 0.155 | P8: =IF(ISBLANK(O8),"",IF(O8=0,"Baja",IF(OR(O8>=10%,ISNUMBER(SEARCH("Política",N8))),"Alta","Media"))) -> Alta | Q8: Pendiente
C9: Number of students | D9: Número de estudiantes | K9: Planeación Institucional | L9: Planeación Institucional | M9: DRNI | N9: Dato cuantitativo 2024
C10: Number of international students from developing countries | D10: Número de estudiantes internacionales de países en desarrollo | K10: Planeación Institucional | L10: Planeación Institucional | M10: DRNI | N10: Dato cuantitativo 2024
A11: Metric | B11: 10.4 | C11: Proportion of students with disabilities | D11: Proporción de estudiantes con discapacidad | E11: Planeación Institucional | K11: Planeación Institucional | L11: Planeación Institucional | M11: Bienestar / Desarrollo Estudiantil | N11: Métrica / bloque de evaluación | O11: 0.115 | P11: =IF(ISBLANK(O11),"",IF(O11=0,"Baja",IF(OR(O11>=10%,ISNUMBER(SEARCH("Política",N11))),"Alta","Media"))) -> Alta | Q11: Pendiente
A12: Indicator | B12: 10.4.1 | C12: Proportion of students with disabilities | D12: Proporción de estudiantes con discapacidad | K12: Planeación Institucional | L12: Planeación Institucional | M12: Bienestar / Desarrollo Estudiantil | N12: Dato cuantitativo 2024 | O12: 0.115 | P12: =IF(ISBLANK(O12),"",IF(O12=0,"Baja",IF(OR(O12>=10%,ISNUMBER(SEARCH("Política",N12))),"Alta","Media"))) -> Alta | Q12: Pendiente
C13: Number of students | D13: Número de estudiantes | K13: Planeación Institucional | L13: Planeación Institucional | M13: Bienestar / Desarrollo Estudiantil | N13: Dato cuantitativo 2024
C14: Number of students with disability | D14: Número de estudiantes con discapacidad | K14: Planeación Institucional | L14: Planeación Institucional | M14: Bienestar / Desarrollo Estudiantil | N14: Dato cuantitativo 2024
A15: Metric | B15: 10.5 | C15: Proportion of employees with disabilities | D15: Proporción de empleados con discapacidad | E15: Talento Humano | K15: Planeación Institucional | L15: Talento Humano | M15: Planeación Institucional | N15: Métrica / bloque de evaluación | O15: 0.115 | P15: =IF(ISBLANK(O15),"",IF(O15=0,"Baja",IF(OR(O15>=10%,ISNUMBER(SEARCH("Política",N15))),"Alta","Media"))) -> Alta | Q15: Pendiente
A16: Indicator | B16: 10.5.1 | C16: Proportion of employees with disabilities | D16: Proporción de empleados con discapacidad | K16: Planeación Institucional | L16: Talento Humano | M16: Planeación Institucional | N16: Dato cuantitativo 2024 | O16: 0.115 | P16: =IF(ISBLANK(O16),"",IF(O16=0,"Baja",IF(OR(O16>=10%,ISNUMBER(SEARCH("Política",N16))),"Alta","Media"))) -> Alta | Q16: Pendiente
C17: Number of employees | D17: Número de empleados | K17: Planeación Institucional | L17: Talento Humano | M17: Planeación Institucional | N17: Dato cuantitativo 2024
C18: Number of employees with disability | D18: Número de empleados con discapacidad | K18: Planeación Institucional | L18: Talento Humano | M18: Planeación Institucional | N18: Dato cuantitativo 2024
A19: Metric | B19: 10.6 | C19: Measures against discrimination | D19: Medidas contra la discriminación | E19: Vicerrectoría de Enseñanza Talento Humano Bienestar | K19: Planeación Institucional | L19: Vicerrectoría de Enseñanza | M19: Talento Humano / Bienestar | N19: Métrica / bloque de evaluación | O19: 0.19 | P19: =IF(ISBLANK(O19),"",IF(O19=0,"Baja",IF(OR(O19>=10%,ISNUMBER(SEARCH("Política",N19))),"Alta","Media"))) -> Alta | Q19: Pendiente
A20: Indicator | B20: 10.6.1 | C20: Non-discriminatory admissions policy Have an admissions policy which is non-discriminatory or which details and explains the logic for any appropriate positive discrimination policies in admissions | D20: Política de admisión no discriminatoria Tener una política de admisión que no sea discriminatoria o que detalle y explique la lógica de cualquier política de discriminación positiva apropiada en las admisiones. | E20: Vicerrectoría de Enseñanza Talento Humano Registro y Control Académico | K20: Planeación Institucional | L20: Vicerrectoría de Enseñanza | M20: Talento Humano / Registro y Control Académico | N20: Política / evidencia pública | O20: 0.019 | P20: =IF(ISBLANK(O20),"",IF(O20=0,"Baja",IF(OR(O20>=10%,ISNUMBER(SEARCH("Política",N20))),"Alta","Media"))) -> Alta | Q20: Pendiente
A21: Indicator | B21: 10.6.2 | C21: Access to university track underrepresented groups applications Measure and track applications and admissions of underrepresented (and potentially underrepresented) groups including ethnic minorities, low income students, non-traditional students, women, LGBT students, disabled students, and newly settled refugee students. | D21: Acceso a la universidad, seguimiento de solicitudes de grupos subrepresentados Mida y realice un seguimiento de las solicitudes y admisiones de grupos subrepresentados (y potencialmente subrepresentados), incluidas minorías étnicas, estudiantes de bajos ingresos, estudiantes no tradicionales, mujeres, estudiantes LGBT, estudiantes discapacitados y estudiantes refugiados recién establecidos. | E21: Planeación Institucional | K21: Planeación Institucional | L21: Planeación Institucional | M21: Vicerrectoría de Enseñanza / Registro y Control Académico / Bienestar | N21: Evidencia pública | O21: 0.019 | P21: =IF(ISBLANK(O21),"",IF(O21=0,"Baja",IF(OR(O21>=10%,ISNUMBER(SEARCH("Política",N21))),"Alta","Media"))) -> Media | Q21: Pendiente
A22: Indicator | B22: 10.6.3 | C22: Access to university underrepresented groups recruit Take planned actions to recruit students, staff, and faculty from under-represented groups | D22: Acceso a la universidad recluta a grupos subrepresentados Tomar medidas planificadas para reclutar estudiantes, personal y profesores de grupos subrepresentados | E22: Vicerrectoría de Enseñanza Talento Humano Mercadeo Institucional Desarrollo Profesoral | K22: Planeación Institucional | L22: Vicerrectoría de Enseñanza | M22: Talento Humano / Mercadeo Institucional / Desarrollo Profesoral | N22: Evidencia pública | O22: 0.019 | P22: =IF(ISBLANK(O22),"",IF(O22=0,"Baja",IF(OR(O22>=10%,ISNUMBER(SEARCH("Política",N22))),"Alta","Media"))) -> Media | Q22: Pendiente
A23: Indicator | B23: 10.6.4 | C23: Anti-discrimination policies Have an anti-discrimination policy that covers the institution and its operations. | D23: Políticas contra la discriminación Tener una política antidiscriminatoria que abarque a la institución y sus operaciones. | E23: COPASST VAF Comité de Inclusión Talento Humano | K23: Planeación Institucional | L23: COPASST | M23: VAF / Comité de Inclusión / Talento Humano | N23: Política / evidencia pública | O23: 0.0095 | P23: =IF(ISBLANK(O23),"",IF(O23=0,"Baja",IF(OR(O23>=10%,ISNUMBER(SEARCH("Política",N23))),"Alta","Media"))) -> Alta | Q23: Pendiente
A24: Indicator | B24: 10.6.5 | C24: University diversity officer Have a diversity and equality committee, office or officer (or the equivalent) tasked by the administration or governing body to advise on and implement policies, programmes and trainings related to diversity, equity, inclusion and human rights on campus. | D24: Oficial de diversidad universitaria Tener un comité, oficina o funcionario de diversidad e igualdad (o su equivalente) encargado por la administración o el órgano de gobierno de asesorar e implementar políticas, programas y capacitaciones relacionados con la diversidad, la equidad, la inclusión y los derechos humanos en el campus. | E24: Comité de Inclusión | K24: Planeación Institucional | L24: Comité de Inclusión | N24: Evidencia pública | O24: 0.019 | P24: =IF(ISBLANK(O24),"",IF(O24=0,"Baja",IF(OR(O24>=10%,ISNUMBER(SEARCH("Política",N24))),"Alta","Media"))) -> Media | Q24: Pendiente
A25: Indicator | B25: 10.6.6 | C25: Support for underrepresented groups Provide mentoring, counselling, or peer support programmes to support students, staff, and faculty from underrepresented groups. | D25: Apoyo a grupos subrepresentados Proporcionar programas de tutoría, asesoramiento o apoyo entre pares para apoyar a los estudiantes, el personal y el profesorado de grupos subrepresentados. | E25: Bienestar Desarrollo Estudiantil Desarrollo Profesoral Talento Humano | K25: Planeación Institucional | L25: Bienestar | M25: Desarrollo Estudiantil / Desarrollo Profesoral / Talento Humano | N25: Evidencia pública | O25: 0.019 | P25: =IF(ISBLANK(O25),"",IF(O25=0,"Baja",IF(OR(O25>=10%,ISNUMBER(SEARCH("Política",N25))),"Alta","Media"))) -> Media | Q25: Pendiente
A26: Indicator | B26: 10.6.7 | C26: Accessible facilities Provide accessible facilities for people with disabilities. | D26: Instalaciones accesibles Proporcionar instalaciones accesibles para personas con discapacidades. | E26: Planta Física | K26: Planeación Institucional | L26: Planta Física | N26: Evidencia pública | O26: 0.019 | P26: =IF(ISBLANK(O26),"",IF(O26=0,"Baja",IF(OR(O26>=10%,ISNUMBER(SEARCH("Política",N26))),"Alta","Media"))) -> Media | Q26: Pendiente
A27: Indicator | B27: 10.6.8 | C27: Disability support services Support services for people with disabilities. | D27: Servicios de apoyo a la discapacidad Servicios de apoyo para personas con discapacidad. | E27: Bienestar Desarrollo Estudiantil Desarrollo Profesoral Talento Humano Biblioteca Planta Física | K27: Planeación Institucional | L27: Bienestar | M27: Desarrollo Estudiantil / Desarrollo Profesoral / Talento Humano / Biblioteca / Planta Física | N27: Evidencia pública | O27: 0.019 | P27: =IF(ISBLANK(O27),"",IF(O27=0,"Baja",IF(OR(O27>=10%,ISNUMBER(SEARCH("Política",N27))),"Alta","Media"))) -> Media | Q27: Pendiente
A28: Indicator | B28: 10.6.9 | C28: Disability access scheme Provide access schemes for people with disabilities such as mentoring or other targeted support | D28: Esquema de acceso para discapacitados Proporcionar esquemas de acceso para personas con discapacidad, como tutoría u otro apoyo específico. | E28: Bienestar Desarrollo Estudiantil Desarrollo Profesoral Talento Humano Biblioteca Planta Física | K28: Planeación Institucional | L28: Bienestar | M28: Desarrollo Estudiantil / Desarrollo Profesoral / Talento Humano / Biblioteca / Planta Física | N28: Evidencia pública | O28: 0.019 | P28: =IF(ISBLANK(O28),"",IF(O28=0,"Baja",IF(OR(O28>=10%,ISNUMBER(SEARCH("Política",N28))),"Alta","Media"))) -> Media | Q28: Pendiente
C29: Mentoring | D29: Tutoría | K29: Planeación Institucional | L29: Bienestar | M29: Desarrollo Estudiantil / Desarrollo Profesoral / Talento Humano / Biblioteca / Planta Física | N29: Evidencia pública
C30: Other targeted support | D30: Otro soporte específico | K30: Planeación Institucional | L30: Bienestar | M30: Desarrollo Estudiantil / Desarrollo Profesoral / Talento Humano / Biblioteca / Planta Física | N30: Evidencia pública
A31: Indicator | B31: 10.6.10 | C31: Disability accommodation policy Have reasonable accommodation policy or strategy for people with disabilities including adequate funding | D31: Política de adaptación para discapacitados Tener una política o estrategia de adaptación razonable para las personas con discapacidades, incluida la financiación adecuada | E31: Talento Humano Comité de Inclusión Bienestar | K31: Planeación Institucional | L31: Talento Humano | M31: Comité de Inclusión / Bienestar | N31: Evidencia pública | O31: 0.019 | P31: =IF(ISBLANK(O31),"",IF(O31=0,"Baja",IF(OR(O31>=10%,ISNUMBER(SEARCH("Política",N31))),"Alta","Media"))) -> Media | Q31: Pendiente
A32: Indicator | B32: 10.6.11 | C32: Anti-harassment policy Have an anti-harassment policy that covers the institution and its operations_x000D_ | D32: Política contra el acoso Tener una política contra el acoso que cubra la institución y sus operaciones. | E32: Talento Humano Comité de convivencia laboral | K32: Planeación Institucional | L32: Talento Humano | M32: Comité de convivencia laboral | N32: Política / evidencia pública | O32: 0.0095 | P32: =IF(ISBLANK(O32),"",IF(O32=0,"Baja",IF(OR(O32>=10%,ISNUMBER(SEARCH("Política",N32))),"Alta","Media"))) -> Alta | Q32: Pendiente

Sheet SDG11
A1: SDG11: Sustainable Cities and Communities
A2: Type | B2: Metric and indicator reference | C2: Metric / Indicator | D2: Value (for continuous data) | E2: Yes/No | F2: Evidence1 | G2: Public (Yes/No)
A3: Metric | B3: 11.2 | C3: Support of arts and heritage
A4: Indicator | B4: 11.2.1 | C4: Public access to buildings Provide public access to buildings and/or monuments or natural heritage landscapes of cultural significance
C5: Free access to all significant buildings
C6: Some free access
C7: Paid access
A8: Indicator | B8: 11.2.2 | C8: Public access to libraries Provide public access to libraries including books and publications
C9: Automatic free access
C10: Access to all after application
C11: Access in some circumstances
A12: Indicator | B12: 11.2.3 | C12: Public access to museums Provide public access to museums, exhibition spaces or galleries, or works of art and artefacts
C13: Free access to all museums and galleries
C14: Free access to some
C15: Paid access
A16: Indicator | B16: 11.2.4 | C16: Public access to green spaces Provide free public access to open spaces and green spaces
C17: Permanent free access
C18: Occasional free access
C19: Paid access
A20: Indicator | B20: 11.2.5 | C20: Arts and heritage contribution Contribute to local arts, in terms of number of annual public performances of university choirs, theatre groups, orchestras etc… either ad-hoc or as part of an ongoing programme
C21: More than 30 perfomancees
C22: More than 15 perfomances
C23: Ad-hoc only
A24: Indicator | B24: 11.2.6 | C24: Record and preserve cultural heritage Deliver projects to record and preserve intangible cultural heritage such as local folklore, traditions, language, and knowledge. This can include the heritage of displaced communities.
C25: Local or regional cultural heritage
C26: National cultural heritage
C27: Heritage of displaced communities
A28: Metric | B28: 11.3 | C28: Expenditure on arts and heritage
A29: Indicator | B29: 11.3.1 | C29: Arts and heritage expenditure
C30: University expenditure
C31: University expenditure on arts and heritage
A32: Metric | B32: 11.4 | C32: Sustainable practices
A33: Indicator | B33: 11.4.1 | C33: Sustainable practices targets Measure and set targets for more sustainable commuting (walking, cycling or other non-motorized transport, vanpools, carpools, shuttlebus or public transportation, motorcycle, scooter or moped, or electric vehicles)
A34: Indicator | B34: 11.4.2 | C34: Promote sustainable commuting Undertake actions to promote more sustainable commuting
A35: Indicator | B35: 11.4.3 | C35: Allow remote working Promote or allow telecommuting or remote working for employees as a matter of policy or standard practice, or offer a condensed working week to reduce employee commuting
A36: Indicator | B36: 11.4.4 | C36: Affordable housing for employees Provide affordable housing for employees
C37: Evaluating affordability
C38: Providing housing directly
C39: Providing financial support
A40: Indicator | B40: 11.4.5 | C40: Affordable housing for students Provide affordable housing for students
C41: Evaluating affordability
C42: Providing housing directly
C43: Providing financial support
A44: Indicator | B44: 11.4.6 | C44: Pedestrian priority on campus Prioritise pedestrian access on campus
A45: Indicator | B45: 11.4.7 | C45: Local authority collaboration regarding planning and development Work with local authorities to address planning issues and development, including ensuring that local residents are able to access affordable housing
A46: Indicator | B46: 11.4.8 | C46: Planning development - new build standards Build new buildings to sustainable standards
A47: Indicator | B47: 11.4.9 | C47: Building on brownfield sites Build on brownfield sites, where possible

Sheet SDG12
A1: SDG12: Responsible Consumption and Production
A2: Type | B2: Metric and indicator reference | C2: Metric / Indicator | D2: Value (for continuous data) | E2: Yes/No | F2: Evidence1 | G2: Public (Yes/No)
A3: Metric | B3: 12.2 | C3: Operational measures
A4: Indicator | B4: 12.2.1 | C4: Ethical sourcing policy Have a policy on ethical sourcing of food and supplies
A5: Indicator | B5: 12.2.3 | C5: Policy waste disposal - hazardous materials Have a policy, process or practice on waste disposal - Covering hazardous materials
A6: Indicator | B6: 12.2.4 | C6: Policy waste disposal - landfill policy Have a policy on waste disposal - to measure the amount of waste sent to landfill and recycled
A7: Indicator | B7: 12.2.5 | C7: Policy for minimisation of plastic use Have policies around use minimisation of plastic
A8: Indicator | B8: 12.2.6 | C8: Policy for minimisation of disposable items Have policies around use minimisation of disposable items
A9: Indicator | B9: 12.2.7 | C9: Disposable policy: extensions to services Ensuring these policies extend to outsourced services and the supply chain
A10: Indicator | B10: 12.2.8 | C10: Minimisation policies extended to suppliers Ensuring these policies extend to outsourced suppliers and the supply chain - (for example suppliers of equipment, stationery, building contracts)
A11: Metric | B11: 12.3 | C11: Proportion of recycled waste
A12: Indicator | B12: 12.3.1 | C12: Waste tracking Measure the amount of waste generated and recycled across the university
C13: Whole university
C14: Partial measurement
A15: Indicator | B15: 12.3.2 | C15: Proportion of waste recycled
C16: Amount of waste generated
C17: Amount of waste recycled
C18: Amount of waste sent to landfill
A19: Metric | B19: 12.4 | C19: Publication of a sustainability report
A20: Indicator | B20: 12.4.1 | C20: Publication of a sustainability report
C21: Annual
C22: Bi-annual
C23: Less Frequent

Sheet SDG13
A1: SDG13: Climate Action
A2: Type | B2: Metric and indicator reference | C2: Metric / Indicator | D2: Value (for continuous data) | E2: Yes/No | F2: Evidence1 | G2: Public (Yes/No)
A3: Metric | B3: 13.2 | C3: Low-carbon energy use
A4: Indicator | B4: 13.2.1 | C4: Low-carbon energy tracking Measure the amount of low carbon energy used across the university
C5: whole university
C6: partial measurement
A7: Indicator | B7: 13.2.2 | C7: Low-carbon energy use
C8: Total energy used
C9: Total energy used from low-carbon sources
A10: Metric | B10: 13.3 | C10: Environmental education measures
A11: Indicator | B11: 13.3.1 | C11: Local education programmes on climate Provide local education programmes or campaigns on climate change risks, impacts, mitigation, adaptation, impact reduction and early warning
A12: Indicator | B12: 13.3.2 | C12: Climate Action Plan, shared Have a university Climate Action plan, shared with local government and local community groups
A13: Indicator | B13: 13.3.3 | C13: Co-operative planning for climate change disasters Participate in co-operative planning for climate change disasters, that may include the displacement of people both within a country and across borders, working with government
C14: Local
C15: Regional
A16: Indicator | B16: 13.3.4 | C16: Inform and support government Inform and support local or regional government in local climate change disaster or risk early warning and monitoring
A17: Indicator | B17: 13.3.5 | C17: Environmental education collaborate with NGO Collaborate with NGOs on climate adaptation
A18: Metric | B18: 13.4 | C18: Commitment to carbon neutral university
A19: Indicator | B19: 13.4.1 | C19: Commitment to carbon neutral university Have a target date by which it will become carbon neutral according to the Greenhouse Gas Protocols?
C20: scope 1
C21: scope 1 and 2
C22: Scope 1, 2 and 3 (partial)
C23: Scope 1, 2 and 3 (full)
A24: Indicator | B24: 13.4.2 | C24: Achieve by date
C25: Achieve by • Date for achieved prior to 2023 – 4 points • Date for achieved by: 2023-2029 – 3 points • Date for achieved by: 2030-2039 – 2 points • Date for achieved by: 2040-2049 – 1 point • Date for achieved by: 2050 or later – 0.5

Sheet SDG14
A1: SDG14: Life Below Water
A2: Type | B2: Metric and indicator reference | C2: Metric / Indicator | D2: Value (for continuous data) | E2: Yes/No | F2: Evidence1 | G2: Public (Yes/No)
A3: Metric | B3: 14.2 | C3: Supporting aquatic ecosystems through education
A4: Indicator | B4: 14.2.1 | C4: Fresh-water ecosystems (community outreach) Offer educational programmes on fresh-water ecosystems (water irrigation practices, water management/conservation) for local or national communities
C5: Free
C6: Paid
A7: Indicator | B7: 14.2.2 | C7: Sustainable fisheries (community outreach) Offer educational programme or outreach for local or national communities on sustainable management of fisheries, aquaculture and tourism
C8: Free
C9: Paid
A10: Indicator | B10: 14.2.3 | C10: Overfishing (community outreach) Offer educational outreach activities for local or national communities to raise awareness about overfishing, illegal, unreported and unregulated fishing and destructive fishing practices
C11: Free
C12: Paid
A13: Metric | B13: 14.3 | C13: Supporting aquatic ecosystems through action
A14: Indicator | B14: 14.3.1 | C14: Conservation and sustainable utilisation of the oceans (events) Support or organise events aimed to promote conservation and sustainable utilisation of the oceans, seas, lakes, rivers and marine resources
A15: Indicator | B15: 14.3.2 | C15: Food from aquatic ecosystems (policies) Have a policy to ensure that food on campus that comes from aquatic ecosystems is sustainably harvested
A16: Indicator | B16: 14.3.3 | C16: Maintain ecosystems and their biodiversity (direct work) Work directly (research and/or engagement with industries) to maintain and extend existing ecosystems and their biodiversity, of both plants and animals, especially ecosystems under threat
A17: Indicator | B17: 14.3.4 | C17: Technologies towards aquatic ecosystem damage prevention (direct work) Work directly (research and/or engagement with industries) on technologies or practices that enable marine industry to minimise or prevent damage to aquatic ecosystems
A18: Metric | B18: 14.4 | C18: Water sensitive waste disposal
A19: Indicator | B19: 14.4.1 | C19: Water discharge guidelines and standards Have water quality standards and guidelines for water discharges (to uphold water quality in order to protect ecosystems, wildlife, and human health and welfare)
A20: Indicator | B20: 14.4.2 | C20: Action plan to reducing plastic waste Have an action plan in place to reduce plastic waste on campus
A21: Indicator | B21: 14.4.3 | C21: Reducing marine pollution (policy) Have a policy on preventing and reducing marine pollution of all kinds, in particular from land-based activities
A22: Metric | B22: 14.5 | C22: Maintaining a local ecosystem
A23: Indicator | B23: 14.5.1 | C23: Minimizing alteration of aquatic ecosystems (plan) Have a plan to minimise physical, chemical and biological alterations of related aquatic ecosystems
A24: Indicator | B24: 14.5.2 | C24: Monitoring the health of aquatic ecosystems Monitor the health of aquatic ecosystems
A25: Indicator | B25: 14.5.3 | C25: Programs towards good aquatic stewardship practices Develop and support programmes and incentives that encourage and maintain good aquatic stewardship practices
C26: Ad hoc
C27: On-going
A28: Indicator | B28: 14.5.4 | C28: Collaboration for shared aquatic ecosystems Collaborate with the local community in efforts to maintain shared aquatic ecosystems
A29: Indicator | B29: 14.5.5 | C29: Watershed management strategy Have implemented a watershed management strategy based on location specific diversity of aquatic species

Sheet SDG15
A1: SDG15: Life On Land
A2: Type | B2: Metric and indicator reference | C2: Metric / Indicator | D2: Value (for continuous data) | E2: Yes/No | F2: Evidence1 | G2: Public (Yes/No)
A3: Metric | B3: 15.2 | C3: Supporting land ecosystems through education
A4: Indicator | B4: 15.2.1 | C4: Events about sustainable use of land Support or organise events aimed to promote conservation and sustainable utilisation of the land, including forests and wild land
A5: Indicator | B5: 15.2.2 | C5: Sustainably farmed food on campus Have policies to ensure that food on campus is sustainably farmed
A6: Indicator | B6: 15.2.3 | C6: Maintain and extend current ecosystems' biodiversity Work directly to maintain and extend existing ecosystems and their biodiversity, of both plants and animals, especially ecosystems under threat
A7: Indicator | B7: 15.2.4 | C7: Educational programmes on ecosystems Offer educational programmes on ecosystems (looking at wild flora and fauna) for local or national communities?
C8: Free
C9: Paid
A10: Indicator | B10: 15.2.5 | C10: Sustainable management of land for agriculture (educational outreach) Offer educational programme/outreach for local or national communities on sustainable management of land for agriculture
C11: Free
C12: Paid
A13: Indicator | B13: 15.2.6 | C13: Sustainable management of land for tourism (educational outreach) Offer educational programme/outreach for local or national communities on sustainable management of land for tourism
C14: Free
C15: Paid
A16: Metric | B16: 15.3 | C16: Supporting land ecosystems through action
A17: Indicator | B17: 15.3.1 | C17: Sustainable use, conservation and restoration of land (policy) Have a policy to ensure the conservation, restoration and sustainable use of terrestrial ecosystems associated with the university, in particular forests, mountains and drylands
A18: Indicator | B18: 15.3.2 | C18: Monitoring IUCN and other conservation species (policies) Have a policy to identify, monitor and protect any IUCN Red Listed species and national conservation list species with habits in areas affected by the operation of your university
A19: Indicator | B19: 15.3.3 | C19: Local biodiversity included in planning and development Include local biodiversity into any planning and development process (e.g. construction of new buildings)
A20: Indicator | B20: 15.3.4 | C20: Alien species impact reduction (policies) Have a policy to reduce the impact of alien species on Campus
A21: Indicator | B21: 15.3.5 | C21: Collaboration for shared land ecosystems Collaborate with the local community to maintain shared land ecosystems
A22: Metric | B22: 15.4 | C22: Land sensitive waste disposal
A23: Indicator | B23: 15.4.1 | C23: Water discharge guidelines and standards Have water quality standards and guidelines for water discharges (to uphold water quality in order to protect ecosystems, wildlife, and human health and welfare)
A24: Indicator | B24: 15.4.2 | C24: Policy on plastic waste reduction Have a policy on reducing plastic waste on campus
A25: Indicator | B25: 15.4.3 | C25: Policy on hazardous waste disposal Have a policy, process or practice on waste disposal covering hazardous materials

Sheet SDG16
A1: SDG16: Peace, Justice and Strong Institutions
A2: Type | B2: Metric and indicator reference | C2: Metric / Indicator | D2: Value (for continuous data) | E2: Yes/No | F2: Evidence1 | G2: Public (Yes/No)
A3: Metric | B3: 16.2 | C3: University governance measures
A4: Indicator | B4: 16.2.1 | C4: Elected representation Have elected representation on the university’s highest governing body from: students (both undergraduate and graduate), faculty, and staff (non-faculty employees)
C5: students (both undergraduate and graduate)
C6: faculty
C7: staff (non-faculty employees)
A8: Indicator | B8: 16.2.2 | C8: Students' union Recognise an independent students’ union
C9: Union provides governance input to university
C10: Union provides support for students
C11: Union provides social activities
A12: Indicator | B12: 16.2.3 | C12: Identify and engage with local stakeholders Have written policies and procedures to identify local stakeholders external to the university and engage with them
A13: Indicator | B13: 16.2.4 | C13: Participatory bodies for stakeholder engagement Ensure that local stakeholders in the university – including local residents, local government, and civil society representativels (which may include groups such as refugee resettlement agencies) – have a meaningful mechanism or for participating in university decision making.
A14: Indicator | B14: 16.2.5 | C14: University principles on corruption and bribery Publish the university's principles and commitments on organized crime, corruption & bribery
A15: Indicator | B15: 16.2.6 | C15: Academic freedom policy Have a policy on supporting academic freedom (freedom to choose areas of research and to speak and teach publicly about the area of their research)
C16: Research freedom for senior academics
C17: Research freedom for junior academics
C18: Teaching freedom for senior academics
C19: Teaching freedom for junior academics
A20: Indicator | B20: 16.2.7 | C20: Publish financial data Publish university financial data
A21: Metric | B21: 16.3 | C21: Working with government
A22: Indicator | B22: 16.3.1 | C22: Provide expert advice to government Provide specific expert advice to local, regional or national government (for example through policy guidance, participation in committees, provision of evidence)
C23: Local
C24: Regional
C25: National
A26: Indicator | B26: 16.3.2 | C26: Policy- and lawmakers outreach and education Provide outreach, general education, upskilling and capacity-building to policy and lawmakers on relevant topics including economics, law, technology, migration and displacement, and climate change
A27: Indicator | B27: 16.3.3 | C27: Participation in government research Undertake policy-focused research in collaboration with government departments
A28: Indicator | B28: 16.3.4 | C28: Neutral platform to discuss issues Provide a neutral platform and ‘safe’ space for different political stakeholders to come together to frankly discuss challenges
A29: Metric | B29: 16.4 | C29: Proportion of graduates in law and civil enforcement
A30: Indicator | B30: 16.4.1 | C30: Proportion of graduates in law
C31: Number of graduates
C32: Number of graduates from law and enforcement related courses

Sheet SDG17
A1: SDG17: Partnerships for the Goals | K1: Gestión interna UDES 2026
A2: Type | B2: Metric and indicator reference | C2: Metrica / Indicador | D2: Metrica / Indicador Este año solicitamos información del año académico 2024. | E2: Fuente datos | F2: Value (for continuous data) | G2: Yes/No | H2: Evidence1 | I2: Public (Yes/No) | J2: Comentarios" con una longitud máxima de 1000 caracteres | K2: Coordinación del reporte | L2: Responsable / fuente principal | M2: Dependencia(s) de apoyo | N2: Tipo de requerimiento | O2: Peso oficial THE | P2: Prioridad | Q2: Estado
A3: Metric | B3: 17.2 | C3: Relationships to support the goals | D3: Relaciones para apoyar los objetivos | K3: Planeación Institucional | L3: Planeación Institucional | M3: Extensión / Investigaciones / DRNI / Comunicaciones | N3: Métrica / bloque de evaluación | O3: 0.185 | P3: =IF(ISBLANK(O3),"",IF(O3=0,"Baja",IF(OR(O3>=10%,ISNUMBER(SEARCH("Política",N3))),"Alta","Media"))) -> Alta | Q3: Pendiente
A4: Indicator | B4: 17.2.1 | C4: Relationships with regional NGOs and government for SDG policy Have direct involvement in, or input into, national government or regional non-government organisations, SDG policy development - including identifying problems and challenges, developing policies and strategies, modelling likely futures with and without interventions, monitoring and reporting on interventions, and enabling adaptive management | D4: Relaciones con ONG regionales y gobierno para la política de los ODS Tener participación directa o aportes en el gobierno nacional o en organizaciones no gubernamentales regionales, el desarrollo de políticas de los ODS, incluida la identificación de problemas y desafíos, el desarrollo de políticas y estrategias, el modelado de futuros probables con y sin intervenciones, el monitoreo y la presentación de informes sobre las intervenciones, y la habilitación de la gestión adaptativa | E4: Planeación Institucional Comunicaciones | K4: Planeación Institucional | L4: Planeación Institucional | M4: Vicerrectoría de Extensión / Vicerrectoría de Investigaciones / DRNI / Comunicaciones | N4: Evidencia pública | O4: 0.037 | P4: =IF(ISBLANK(O4),"",IF(O4=0,"Baja",IF(OR(O4>=10%,ISNUMBER(SEARCH("Política",N4))),"Alta","Media"))) -> Media | Q4: Pendiente
A5: Indicator | B5: 17.2.2 | C5: Cross sectoral dialogue about SDGs Initiate and participate in cross-sectoral dialogue about the SDGs, e.g. conferences involving government or NGOs | D5: Diálogo intersectorial sobre los ODS Iniciar y participar en un diálogo intersectorial sobre los ODS, por ejemplo, conferencias en las que participen gobiernos u ONG. | E5: Planeación Institucional Comunicaciones | K5: Planeación Institucional | L5: Planeación Institucional | M5: Vicerrectoría de Extensión / Vicerrectoría de Investigaciones / Comunicaciones | N5: Evidencia pública | O5: 0.037 | P5: =IF(ISBLANK(O5),"",IF(O5=0,"Baja",IF(OR(O5>=10%,ISNUMBER(SEARCH("Política",N5))),"Alta","Media"))) -> Media | Q5: Pendiente
A6: Indicator | B6: 17.2.3 | C6: International collaboration data gathering for SDG Participate in international collaboration on gathering or measuring data for the SDGs | D6: Recopilación de datos de colaboración internacional para los ODS Participar en la colaboración internacional en la recopilación o medición de datos para los ODS | E6: Planeación Institucional Comunicaciones | K6: Planeación Institucional | L6: Planeación Institucional | M6: Vicerrectoría de Investigaciones / DRNI | N6: Evidencia pública | O6: 0.037 | P6: =IF(ISBLANK(O6),"",IF(O6=0,"Baja",IF(OR(O6>=10%,ISNUMBER(SEARCH("Política",N6))),"Alta","Media"))) -> Media | Q6: Pendiente
A7: Indicator | B7: 17.2.4 | C7: Collaboration for SDG best practice Through international collaboration and research, review comparative approaches and develop international best practice on tackling the SDGs | D7: Colaboración para las mejores prácticas de los ODS A través de la colaboración y la investigación internacionales, revisar los enfoques comparativos y desarrollar las mejores prácticas internacionales para abordar los ODS. | E7: Planeación Institucional Comunicaciones | K7: Planeación Institucional | L7: Planeación Institucional | M7: Vicerrectoría de Investigaciones / DRNI | N7: Evidencia pública | O7: 0.037 | P7: =IF(ISBLANK(O7),"",IF(O7=0,"Baja",IF(OR(O7>=10%,ISNUMBER(SEARCH("Política",N7))),"Alta","Media"))) -> Media | Q7: Pendiente
A8: Indicator | B8: 17.2.5 | C8: Collaboration with NGOs for SDGs Collaborate with NGOs to tackle the SDGs through: student volunteering programmes, research programmes, or development of educational resources | D8: Colaboración con ONG para los ODS Colaborar con las ONG para abordar los ODS a través de: programas de voluntariado estudiantil, programas de investigación o desarrollo de recursos educativos | E8: Planeación Institucional Comunicaciones | K8: Planeación Institucional | L8: Planeación Institucional | M8: Bienestar / Vicerrectoría de Investigaciones / DRNI / Educación Virtual | N8: Evidencia pública | O8: 0.037 | P8: =IF(ISBLANK(O8),"",IF(O8=0,"Baja",IF(OR(O8>=10%,ISNUMBER(SEARCH("Política",N8))),"Alta","Media"))) -> Media | Q8: Pendiente
C9: student volunteering programmes | D9: Programas de voluntariado estudiantil | E9: Bienestar DRNI | K9: Planeación Institucional | L9: Bienestar | M9: DRNI | N9: Evidencia pública
C10: research programmes | D10: Programas de investigación | E10: Vicerrectoría de Investigaciones | K10: Planeación Institucional | L10: Vicerrectoría de Investigaciones | N10: Evidencia pública
C11: development of educational resources | D11: Desarrollo de recursos educativos | E11: Campus Virtual UDES | K11: Planeación Institucional | L11: Campus Virtual UDES | N11: Evidencia pública
A12: Metric | B12: 17.3 | C12: Publication of SDG reports | D12: informe separado | K12: Planeación Institucional | L12: Planeación Institucional | M12: Comunicaciones / Vicerrectorías y unidades responsables por ODS | N12: Métrica / bloque de evaluación | O12: 0.272 | P12: =IF(ISBLANK(O12),"",IF(O12=0,"Baja",IF(OR(O12>=10%,ISNUMBER(SEARCH("Política",N12))),"Alta","Media"))) -> Alta | Q12: Pendiente
A13: Indicator | B13: 17.3.1 | C13: Publication of SDG reports - per SDG Publish progress against against SDG1, either individually or within an annual report | D13: Publicación de informes sobre los ODS - por ODS Publicar el progreso con respecto al ODS 1, ya sea individualmente o dentro de un informe anual | E13: Planeación Institucional Comunicaciones | K13: Planeación Institucional | L13: Planeación Institucional | M13: Comunicaciones / Vicerrectorías y unidades responsables por ODS | N13: Evidencia pública | O13: 0.016 | P13: =IF(ISBLANK(O13),"",IF(O13=0,"Baja",IF(OR(O13>=10%,ISNUMBER(SEARCH("Política",N13))),"Alta","Media"))) -> Media | Q13: Pendiente
C14: overall report | D14: Informe general | K14: Planeación Institucional | L14: Planeación Institucional | M14: Comunicaciones / Vicerrectorías y unidades responsables por ODS | N14: Evidencia pública
C15: separate report | D15: informe separado | K15: Planeación Institucional | L15: Planeación Institucional | M15: Comunicaciones / Vicerrectorías y unidades responsables por ODS | N15: Evidencia pública
A16: Indicator | B16: 17.3.2 | C16: Publication of SDG reports - per SDG Publish progress against against SDG2, either individually or within an annual report | D16: Publicación de informes sobre los ODS - por ODS Publicar el progreso con respecto al ODS 2, ya sea individualmente o dentro de un informe anual | E16: Planeación Institucional Comunicaciones | K16: Planeación Institucional | L16: Planeación Institucional | M16: Comunicaciones / Vicerrectorías y unidades responsables por ODS | N16: Evidencia pública | O16: 0.016 | P16: =IF(ISBLANK(O16),"",IF(O16=0,"Baja",IF(OR(O16>=10%,ISNUMBER(SEARCH("Política",N16))),"Alta","Media"))) -> Media | Q16: Pendiente
C17: overall report | D17: Informe general | K17: Planeación Institucional | L17: Planeación Institucional | M17: Comunicaciones / Vicerrectorías y unidades responsables por ODS | N17: Evidencia pública
C18: separate report | D18: informe separado | K18: Planeación Institucional | L18: Planeación Institucional | M18: Comunicaciones / Vicerrectorías y unidades responsables por ODS | N18: Evidencia pública
A19: Indicator | B19: 17.3.3 | C19: Publication of SDG reports - per SDG Publish progress against against SDG3, either individually or within an annual report | D19: Publicación de informes sobre los ODS - por ODS Publicar el progreso con respecto al ODS 3, ya sea individualmente o dentro de un informe anual | E19: Planeación Institucional Comunicaciones | K19: Planeación Institucional | L19: Planeación Institucional | M19: Comunicaciones / Vicerrectorías y unidades responsables por ODS | N19: Evidencia pública | O19: 0.016 | P19: =IF(ISBLANK(O19),"",IF(O19=0,"Baja",IF(OR(O19>=10%,ISNUMBER(SEARCH("Política",N19))),"Alta","Media"))) -> Media | Q19: Pendiente
C20: overall report | D20: Informe general | K20: Planeación Institucional | L20: Planeación Institucional | M20: Comunicaciones / Vicerrectorías y unidades responsables por ODS | N20: Evidencia pública
C21: separate report | D21: informe separado | K21: Planeación Institucional | L21: Planeación Institucional | M21: Comunicaciones / Vicerrectorías y unidades responsables por ODS | N21: Evidencia pública
A22: Indicator | B22: 17.3.4 | C22: Publication of SDG reports - per SDG Publish progress against against SDG4, either individually or within an annual report | D22: Publicación de informes sobre los ODS - por ODS Publicar el progreso con respecto al ODS 4, ya sea individualmente o dentro de un informe anual | E22: Planeación Institucional Comunicaciones | K22: Planeación Institucional | L22: Planeación Institucional | M22: Comunicaciones / Vicerrectorías y unidades responsables por ODS | N22: Evidencia pública | O22: 0.016 | P22: =IF(ISBLANK(O22),"",IF(O22=0,"Baja",IF(OR(O22>=10%,ISNUMBER(SEARCH("Política",N22))),"Alta","Media"))) -> Media | Q22: Pendiente
C23: overall report | D23: Informe general | K23: Planeación Institucional | L23: Planeación Institucional | M23: Comunicaciones / Vicerrectorías y unidades responsables por ODS | N23: Evidencia pública
C24: separate report | D24: informe separado | K24: Planeación Institucional | L24: Planeación Institucional | M24: Comunicaciones / Vicerrectorías y unidades responsables por ODS | N24: Evidencia pública
A25: Indicator | B25: 17.3.5 | C25: Publication of SDG reports - per SDG Publish progress against against SDG5, either individually or within an annual report | D25: Publicación de informes sobre los ODS - por ODS Publicar el progreso con respecto al ODS 5, ya sea individualmente o dentro de un informe anual | E25: Planeación Institucional Comunicaciones | K25: Planeación Institucional | L25: Planeación Institucional | M25: Comunicaciones / Vicerrectorías y unidades responsables por ODS | N25: Evidencia pública | O25: 0.016 | P25: =IF(ISBLANK(O25),"",IF(O25=0,"Baja",IF(OR(O25>=10%,ISNUMBER(SEARCH("Política",N25))),"Alta","Media"))) -> Media | Q25: Pendiente
C26: overall report | D26: Informe general | K26: Planeación Institucional | L26: Planeación Institucional | M26: Comunicaciones / Vicerrectorías y unidades responsables por ODS | N26: Evidencia pública
C27: separate report | D27: informe separado | K27: Planeación Institucional | L27: Planeación Institucional | M27: Comunicaciones / Vicerrectorías y unidades responsables por ODS | N27: Evidencia pública
A28: Indicator | B28: 17.3.6 | C28: Publication of SDG reports - per SDG Publish progress against against SDG6, either individually or within an annual report | D28: Publicación de informes sobre los ODS - por ODS Publicar el progreso con respecto al ODS 6, ya sea individualmente o dentro de un informe anual | E28: Planeación Institucional Comunicaciones | K28: Planeación Institucional | L28: Planeación Institucional | M28: Comunicaciones / Vicerrectorías y unidades responsables por ODS | N28: Evidencia pública | O28: 0.016 | P28: =IF(ISBLANK(O28),"",IF(O28=0,"Baja",IF(OR(O28>=10%,ISNUMBER(SEARCH("Política",N28))),"Alta","Media"))) -> Media | Q28: Pendiente
C29: overall report | D29: Informe general | K29: Planeación Institucional | L29: Planeación Institucional | M29: Comunicaciones / Vicerrectorías y unidades responsables por ODS | N29: Evidencia pública
C30: separate report | D30: informe separado | K30: Planeación Institucional | L30: Planeación Institucional | M30: Comunicaciones / Vicerrectorías y unidades responsables por ODS | N30: Evidencia pública
A31: Indicator | B31: 17.3.7 | C31: Publication of SDG reports - per SDG Publish progress against against SDG7, either individually or within an annual report | D31: Publicación de informes sobre los ODS - por ODS Publicar el progreso con respecto al ODS 7, ya sea individualmente o dentro de un informe anual | E31: Planeación Institucional Comunicaciones | K31: Planeación Institucional | L31: Planeación Institucional | M31: Comunicaciones / Vicerrectorías y unidades responsables por ODS | N31: Evidencia pública | O31: 0.016 | P31: =IF(ISBLANK(O31),"",IF(O31=0,"Baja",IF(OR(O31>=10%,ISNUMBER(SEARCH("Política",N31))),"Alta","Media"))) -> Media | Q31: Pendiente
C32: overall report | D32: Informe general | K32: Planeación Institucional | L32: Planeación Institucional | M32: Comunicaciones / Vicerrectorías y unidades responsables por ODS | N32: Evidencia pública
C33: separate report | D33: informe separado | K33: Planeación Institucional | L33: Planeación Institucional | M33: Comunicaciones / Vicerrectorías y unidades responsables por ODS | N33: Evidencia pública
A34: Indicator | B34: 17.3.8 | C34: Publication of SDG reports - per SDG Publish progress against against SDG8, either individually or within an annual report | D34: Publicación de informes sobre los ODS - por ODS Publicar el progreso con respecto al ODS 8, ya sea individualmente o dentro de un informe anual | E34: Planeación Institucional Comunicaciones | K34: Planeación Institucional | L34: Planeación Institucional | M34: Comunicaciones / Vicerrectorías y unidades responsables por ODS | N34: Evidencia pública | O34: 0.016 | P34: =IF(ISBLANK(O34),"",IF(O34=0,"Baja",IF(OR(O34>=10%,ISNUMBER(SEARCH("Política",N34))),"Alta","Media"))) -> Media | Q34: Pendiente
C35: overall report | D35: Informe general | K35: Planeación Institucional | L35: Planeación Institucional | M35: Comunicaciones / Vicerrectorías y unidades responsables por ODS | N35: Evidencia pública
C36: separate report | D36: informe separado | K36: Planeación Institucional | L36: Planeación Institucional | M36: Comunicaciones / Vicerrectorías y unidades responsables por ODS | N36: Evidencia pública
A37: Indicator | B37: 17.3.9 | C37: Publication of SDG reports - per SDG Publish progress against against SDG9, either individually or within an annual report | D37: Publicación de informes sobre los ODS - por ODS Publicar el progreso con respecto al ODS 9, ya sea individualmente o dentro de un informe anual | E37: Planeación Institucional Comunicaciones | K37: Planeación Institucional | L37: Planeación Institucional | M37: Comunicaciones / Vicerrectorías y unidades responsables por ODS | N37: Evidencia pública | O37: 0.016 | P37: =IF(ISBLANK(O37),"",IF(O37=0,"Baja",IF(OR(O37>=10%,ISNUMBER(SEARCH("Política",N37))),"Alta","Media"))) -> Media | Q37: Pendiente
C38: overall report | D38: Informe general | K38: Planeación Institucional | L38: Planeación Institucional | M38: Comunicaciones / Vicerrectorías y unidades responsables por ODS | N38: Evidencia pública
C39: separate report | D39: informe separado | K39: Planeación Institucional | L39: Planeación Institucional | M39: Comunicaciones / Vicerrectorías y unidades responsables por ODS | N39: Evidencia pública
A40: Indicator | B40: 17.3.10 | C40: Publication of SDG reports - per SDG Publish progress against against SDG10, either individually or within an annual report | D40: Publicación de informes sobre los ODS - por ODS Publicar el progreso con respecto al ODS 10, ya sea individualmente o dentro de un informe anual | E40: Planeación Institucional Comunicaciones | K40: Planeación Institucional | L40: Planeación Institucional | M40: Comunicaciones / Vicerrectorías y unidades responsables por ODS | N40: Evidencia pública | O40: 0.016 | P40: =IF(ISBLANK(O40),"",IF(O40=0,"Baja",IF(OR(O40>=10%,ISNUMBER(SEARCH("Política",N40))),"Alta","Media"))) -> Media | Q40: Pendiente
C41: overall report | D41: Informe general | K41: Planeación Institucional | L41: Planeación Institucional | M41: Comunicaciones / Vicerrectorías y unidades responsables por ODS | N41: Evidencia pública
C42: separate report | D42: informe separado | K42: Planeación Institucional | L42: Planeación Institucional | M42: Comunicaciones / Vicerrectorías y unidades responsables por ODS | N42: Evidencia pública
A43: Indicator | B43: 17.3.11 | C43: Publication of SDG reports - per SDG Publish progress against against SDG11, either individually or within an annual report | D43: Publicación de informes sobre los ODS - por ODS Publicar el progreso con respecto al ODS 11, ya sea individualmente o dentro de un informe anual | E43: Planeación Institucional Comunicaciones | K43: Planeación Institucional | L43: Planeación Institucional | M43: Comunicaciones / Vicerrectorías y unidades responsables por ODS | N43: Evidencia pública | O43: 0.016 | P43: =IF(ISBLANK(O43),"",IF(O43=0,"Baja",IF(OR(O43>=10%,ISNUMBER(SEARCH("Política",N43))),"Alta","Media"))) -> Media | Q43: Pendiente
C44: overall report | D44: Informe general | K44: Planeación Institucional | L44: Planeación Institucional | M44: Comunicaciones / Vicerrectorías y unidades responsables por ODS | N44: Evidencia pública
C45: separate report | D45: informe separado | K45: Planeación Institucional | L45: Planeación Institucional | M45: Comunicaciones / Vicerrectorías y unidades responsables por ODS | N45: Evidencia pública
A46: Indicator | B46: 17.3.12 | C46: Publication of SDG reports - per SDG Publish progress against against SDG12, either individually or within an annual report | D46: Publicación de informes sobre los ODS - por ODS Publicar el progreso con respecto al ODS 12, ya sea individualmente o dentro de un informe anual | E46: Planeación Institucional Comunicaciones | K46: Planeación Institucional | L46: Planeación Institucional | M46: Comunicaciones / Vicerrectorías y unidades responsables por ODS | N46: Evidencia pública | O46: 0.016 | P46: =IF(ISBLANK(O46),"",IF(O46=0,"Baja",IF(OR(O46>=10%,ISNUMBER(SEARCH("Política",N46))),"Alta","Media"))) -> Media | Q46: Pendiente
C47: overall report | D47: Informe general | K47: Planeación Institucional | L47: Planeación Institucional | M47: Comunicaciones / Vicerrectorías y unidades responsables por ODS | N47: Evidencia pública
C48: separate report | D48: informe separado | K48: Planeación Institucional | L48: Planeación Institucional | M48: Comunicaciones / Vicerrectorías y unidades responsables por ODS | N48: Evidencia pública
A49: Indicator | B49: 17.3.13 | C49: Publication of SDG reports - per SDG Publish progress against against SDG13, either individually or within an annual report | D49: Publicación de informes sobre los ODS - por ODS Publicar el progreso con respecto al ODS 13, ya sea individualmente o dentro de un informe anual | E49: Planeación Institucional Comunicaciones | K49: Planeación Institucional | L49: Planeación Institucional | M49: Comunicaciones / Vicerrectorías y unidades responsables por ODS | N49: Evidencia pública | O49: 0.016 | P49: =IF(ISBLANK(O49),"",IF(O49=0,"Baja",IF(OR(O49>=10%,ISNUMBER(SEARCH("Política",N49))),"Alta","Media"))) -> Media | Q49: Pendiente
C50: overall report | D50: Informe general | K50: Planeación Institucional | L50: Planeación Institucional | M50: Comunicaciones / Vicerrectorías y unidades responsables por ODS | N50: Evidencia pública
C51: separate report | D51: informe separado | K51: Planeación Institucional | L51: Planeación Institucional | M51: Comunicaciones / Vicerrectorías y unidades responsables por ODS | N51: Evidencia pública
A52: Indicator | B52: 17.3.14 | C52: Publication of SDG reports - per SDG Publish progress against against SDG14, either individually or within an annual report | D52: Publicación de informes sobre los ODS - por ODS Publicar el progreso con respecto al ODS 14, ya sea individualmente o dentro de un informe anual | E52: Planeación Institucional Comunicaciones | K52: Planeación Institucional | L52: Planeación Institucional | M52: Comunicaciones / Vicerrectorías y unidades responsables por ODS | N52: Evidencia pública | O52: 0.016 | P52: =IF(ISBLANK(O52),"",IF(O52=0,"Baja",IF(OR(O52>=10%,ISNUMBER(SEARCH("Política",N52))),"Alta","Media"))) -> Media | Q52: Pendiente
C53: overall report | D53: Informe general | K53: Planeación Institucional | L53: Planeación Institucional | M53: Comunicaciones / Vicerrectorías y unidades responsables por ODS | N53: Evidencia pública
C54: separate report | D54: informe separado | K54: Planeación Institucional | L54: Planeación Institucional | M54: Comunicaciones / Vicerrectorías y unidades responsables por ODS | N54: Evidencia pública
A55: Indicator | B55: 17.3.15 | C55: Publication of SDG reports - per SDG Publish progress against against SDG15, either individually or within an annual report | D55: Publicación de informes sobre los ODS - por ODS Publicar el progreso con respecto al ODS 15, ya sea individualmente o dentro de un informe anual | E55: Planeación Institucional Comunicaciones | K55: Planeación Institucional | L55: Planeación Institucional | M55: Comunicaciones / Vicerrectorías y unidades responsables por ODS | N55: Evidencia pública | O55: 0.016 | P55: =IF(ISBLANK(O55),"",IF(O55=0,"Baja",IF(OR(O55>=10%,ISNUMBER(SEARCH("Política",N55))),"Alta","Media"))) -> Media | Q55: Pendiente
C56: overall report | D56: Informe general | K56: Planeación Institucional | L56: Planeación Institucional | M56: Comunicaciones / Vicerrectorías y unidades responsables por ODS | N56: Evidencia pública
C57: separate report | D57: informe separado | K57: Planeación Institucional | L57: Planeación Institucional | M57: Comunicaciones / Vicerrectorías y unidades responsables por ODS | N57: Evidencia pública
A58: Indicator | B58: 17.3.16 | C58: Publication of SDG reports - per SDG Publish progress against against SDG16, either individually or within an annual report | D58: Publicación de informes sobre los ODS - por ODS Publicar el progreso con respecto al ODS 16, ya sea individualmente o dentro de un informe anual | E58: Planeación Institucional Comunicaciones | K58: Planeación Institucional | L58: Planeación Institucional | M58: Comunicaciones / Vicerrectorías y unidades responsables por ODS | N58: Evidencia pública | O58: 0.016 | P58: =IF(ISBLANK(O58),"",IF(O58=0,"Baja",IF(OR(O58>=10%,ISNUMBER(SEARCH("Política",N58))),"Alta","Media"))) -> Media | Q58: Pendiente
C59: overall report | D59: Informe general | K59: Planeación Institucional | L59: Planeación Institucional | M59: Comunicaciones / Vicerrectorías y unidades responsables por ODS | N59: Evidencia pública
C60: separate report | D60: informe separado | K60: Planeación Institucional | L60: Planeación Institucional | M60: Comunicaciones / Vicerrectorías y unidades responsables por ODS | N60: Evidencia pública
A61: Indicator | B61: 17.3.17 | C61: Publication of SDG reports - per SDG Publish progress against against SDG17, either individually or within an annual report | D61: Publicación de informes sobre los ODS - por ODS Publicar el progreso con respecto al ODS 17, ya sea individualmente o dentro de un informe anual | E61: Planeación Institucional Comunicaciones | K61: Planeación Institucional | L61: Planeación Institucional | M61: Comunicaciones / Vicerrectorías y unidades responsables por ODS | N61: Evidencia pública | O61: 0.016 | P61: =IF(ISBLANK(O61),"",IF(O61=0,"Baja",IF(OR(O61>=10%,ISNUMBER(SEARCH("Política",N61))),"Alta","Media"))) -> Media | Q61: Pendiente
C62: overall report | D62: Informe general | K62: Planeación Institucional | L62: Planeación Institucional | M62: Comunicaciones / Vicerrectorías y unidades responsables por ODS | N62: Evidencia pública
C63: separate report | D63: informe separado | K63: Planeación Institucional | L63: Planeación Institucional | M63: Comunicaciones / Vicerrectorías y unidades responsables por ODS | N63: Evidencia pública
A64: Metric | B64: 17.4 | C64: Education for the SDGs | D64: Educación para los ODS | K64: Planeación Institucional | L64: Planeación Institucional | M64: Vicerrectoría de Enseñanza / Extensión / DRNI / Desarrollo Profesoral | N64: Métrica / bloque de evaluación | O64: 0.272 | P64: =IF(ISBLANK(O64),"",IF(O64=0,"Baja",IF(OR(O64>=10%,ISNUMBER(SEARCH("Política",N64))),"Alta","Media"))) -> Alta | Q64: Pendiente
A65: Indicator | B65: 17.4.1 | C65: Education for SDGs commitment to meaningful education Have a commitment to meaningful education around the SDGs across the university, relevant and applicable to all students | D65: Educación para los ODS: compromiso con una educación significativa Tener un compromiso con una educación significativa en torno a los ODS en toda la universidad, relevante y aplicable a todos los estudiantes | E65: Planeación Institucional Comunicaciones | K65: Planeación Institucional | L65: Planeación Institucional | M65: Vicerrectoría de Enseñanza / Comunicaciones | N65: Evidencia pública | O65: 0.0906 | P65: =IF(ISBLANK(O65),"",IF(O65=0,"Baja",IF(OR(O65>=10%,ISNUMBER(SEARCH("Política",N65))),"Alta","Media"))) -> Media | Q65: Pendiente
C66: education integrated across full curriculum | D66: Educación integrada en todo el plan de estudios | K66: Planeación Institucional | L66: Planeación Institucional | M66: Vicerrectoría de Enseñanza / Comunicaciones | N66: Evidencia pública
C67: mandatory education for all | D67: Educación obligatoria para todos | K67: Planeación Institucional | L67: Planeación Institucional | M67: Vicerrectoría de Enseñanza / Comunicaciones | N67: Evidencia pública
C68: optional education for all | D68: Educación opcional para todos | K68: Planeación Institucional | L68: Planeación Institucional | M68: Vicerrectoría de Enseñanza / Comunicaciones | N68: Evidencia pública
A69: Indicator | B69: 17.4.2 | C69: Education for SDGs specific courses on sustainability Have dedicated courses (full degrees, or electives) that address sustainability and the SDGs. | D69: Cursos específicos de educación para los ODS sobre sostenibilidad Tener cursos dedicados (títulos completos u optativos) que aborden la sostenibilidad y los ODS. | E69: Planeación Institucional EDUCON DRNI Desarrollo Profesoral | K69: Planeación Institucional | L69: Planeación Institucional | M69: EDUCON / DRNI / Desarrollo Profesoral | N69: Evidencia pública | O69: 0.0906 | P69: =IF(ISBLANK(O69),"",IF(O69=0,"Baja",IF(OR(O69>=10%,ISNUMBER(SEARCH("Política",N69))),"Alta","Media"))) -> Media | Q69: Pendiente
A70: Indicator | B70: 17.4.3 | C70: Education for SDGs in the wider community Have dedicated outreach educational activities for the wider community, which could include alumni, local residents, displaced people | D70: Educación para los ODS en la comunidad en general Tener actividades educativas de divulgación dedicadas para la comunidad en general, que podrían incluir ex alumnos, residentes locales, personas desplazadas | E70: UDES Verde Graduados EDUCON Desarrollo Profesoral | K70: Planeación Institucional | L70: UDES Verde | M70: Graduados / EDUCON / Desarrollo Profesoral / Planeación Institucional | N70: Evidencia pública | O70: 0.0906 | P70: =IF(ISBLANK(O70),"",IF(O70=0,"Baja",IF(OR(O70>=10%,ISNUMBER(SEARCH("Política",N70))),"Alta","Media"))) -> Media | Q70: Pendiente
C71: Alumni | D71: Egresados | K71: Planeación Institucional | L71: UDES Verde | M71: Graduados / EDUCON / Desarrollo Profesoral / Planeación Institucional | N71: Evidencia pública
C72: Local community | D72: Comunidad local | K72: Planeación Institucional | L72: UDES Verde | M72: Graduados / EDUCON / Desarrollo Profesoral / Planeación Institucional | N72: Evidencia pública
C73: Displaced people and refugees | D73: Personas desplazadas y refugiadas | K73: Planeación Institucional | L73: UDES Verde | M73: Graduados / EDUCON / Desarrollo Profesoral / Planeación Institucional | N73: Evidencia pública
B74: 17.4.4 | C74: Sustainability Literacy This question explores how you evaluate your students’ ability to learn and retain key concepts of sustainability. For 2026 this question is not scored. Measure the sustainability literacy of students. | D74: Alfabetización en sostenibilidad Esta pregunta explora cómo evalúa la capacidad de sus estudiantes para aprender y retener conceptos clave de sostenibilidad. Para 2026, esta pregunta no puntúa. Medir la alfabetización en sostenibilidad de los estudiantes. | E74: sistema Sulitest TASK DRNI | J74: Indicador sin puntaje en la edición 2026. Herramienta identificada: Sulitest TASK. | K74: Planeación Institucional | L74: DRNI | M74: Planeación Institucional | N74: Evidencia (sin puntaje 2026) | O74: 0 | P74: =IF(ISBLANK(O74),"",IF(O74=0,"Baja",IF(OR(O74>=10%,ISNUMBER(SEARCH("Política",N74))),"Alta","Media"))) -> Baja | Q74: Pendiente

Sheet CONTROL UDES 2026
A1: Control UDES – Sustainability Impact Ratings 2026
A2: ODS seleccionados: 4, 5, 10 y 17 | Coordinación institucional: Planeación Institucional | Año de información: 2024
A3: Planeación Institucional coordina el reporte y, según el indicador, también busca, consolida, valida o produce directamente los datos y evidencias.
A4: Vista consolidada de seguimiento. Diligencie datos, respuestas y evidencias en las hojas SDG4, SDG5, SDG10 y SDG17; esta hoja se actualiza automáticamente.
A5: Indicadores | C5: Alta prioridad | E5: Media | G5: Baja | I5: Completos | K5: Fuente metodológica
A6: =COUNTA(B9:B72) -> 64 | C6: =COUNTIF(I9:I72,"Alta") -> 19 | E6: =COUNTIF(I9:I72,"Media") -> 44 | G6: =COUNTIF(I9:I72,"Baja") -> 1 | I6: =COUNTIF(J9:J72,"Completo") -> 0 | K6: https://www.timeshighereducation.com/cms-academic/sites/default/files/2025-08/THE.SustainabilityImpactRatings.METHODOLOGY.2026.v2.pdf
A8: ODS | B8: Indicador | C8: Descripción | D8: Peso THE | E8: Tipo de requerimiento | F8: Coordinación | G8: Responsable principal | H8: Dependencia(s) de apoyo | I8: Prioridad | J8: Estado | K8: Dato / valor | L8: Respuesta | M8: Evidencia / URL | N8: Pública | O8: Comentarios
A9: ="ODS 4" -> ODS 4 | B9: ='SDG4'!B4 -> 4.2.1 | C9: ='SDG4'!D4 -> Proporción de titulados con cualificación pertinente para la docencia | D9: ='SDG4'!O4 -> 0.154 | E9: ='SDG4'!N4 -> Dato cuantitativo 2024 | F9: ='SDG4'!K4 -> Planeación Institucional | G9: =IF('SDG4'!L4="","",'SDG4'!L4) -> Planeación Institucional | H9: =IF('SDG4'!M4="","",'SDG4'!M4) -> Registro y Control Académico / Vicerrectoría de Enseñanza | I9: ='SDG4'!P4 -> Alta | J9: ='SDG4'!Q4 -> Pendiente | K9: =IF('SDG4'!F4="","",'SDG4'!F4) | L9: =IF('SDG4'!G4="","",'SDG4'!G4) | M9: =IF('SDG4'!H4="","",'SDG4'!H4) | N9: =IF('SDG4'!I4="","",'SDG4'!I4) | O9: =IF('SDG4'!J4="","",'SDG4'!J4)
A10: ="ODS 4" -> ODS 4 | B10: ='SDG4'!B8 -> 4.3.1 | C10: ='SDG4'!D8 -> Recursos públicos (aprendizaje permanente) Proporcionar acceso gratuito a recursos educativos para aquellos que no estudian en la universidad. | D10: ='SDG4'!O8 -> 0.05 | E10: ='SDG4'!N8 -> Evidencia pública | F10: ='SDG4'!K8 -> Planeación Institucional | G10: =IF('SDG4'!L8="","",'SDG4'!L8) -> EDUCON | H10: =IF('SDG4'!M8="","",'SDG4'!M8) -> Campus Virtual UDES / Biblioteca | I10: ='SDG4'!P8 -> Media | J10: ='SDG4'!Q8 -> Pendiente | K10: =IF('SDG4'!F8="","",'SDG4'!F8) | L10: =IF('SDG4'!G8="","",'SDG4'!G8) | M10: =IF('SDG4'!H8="","",'SDG4'!H8) | N10: =IF('SDG4'!I8="","",'SDG4'!I8) | O10: =IF('SDG4'!J8="","",'SDG4'!J8)
A11: ="ODS 4" -> ODS 4 | B11: ='SDG4'!B12 -> 4.3.2 | C11: ='SDG4'!D12 -> Eventos públicos (aprendizaje permanente) Organice eventos educativos en la universidad que estén abiertos al público en general. | D11: ='SDG4'!O12 -> 0.05 | E11: ='SDG4'!N12 -> Evidencia pública | F11: ='SDG4'!K12 -> Planeación Institucional | G11: =IF('SDG4'!L12="","",'SDG4'!L12) -> EDUCON / Graduados | H11: =IF('SDG4'!M12="","",'SDG4'!M12) -> Comunicaciones / Biblioteca / Programas / Campus Virtual UDES / Talento Humano | I11: ='SDG4'!P12 -> Media | J11: ='SDG4'!Q12 -> Pendiente | K11: =IF('SDG4'!F12="","",'SDG4'!F12) | L11: =IF('SDG4'!G12="","",'SDG4'!G12) | M11: =IF('SDG4'!H12="","",'SDG4'!H12) | N11: =IF('SDG4'!I12="","",'SDG4'!I12) | O11: =IF('SDG4'!J12="","",'SDG4'!J12)
A12: ="ODS 4" -> ODS 4 | B12: ='SDG4'!B15 -> 4.3.3 | C12: ='SDG4'!D15 -> Eventos de formación profesional (aprendizaje permanente) Organizar eventos en la universidad abiertos al público en general: programas de educación ejecutiva (esto se refiere a cursos cortos para personas que no asisten a la universidad; esto excluye específicamente cursos como MBA) y/o formación profesional. | D12: ='SDG4'!O15 -> 0.05 | E12: ='SDG4'!N15 -> Evidencia pública | F12: ='SDG4'!K15 -> Planeación Institucional | G12: =IF('SDG4'!L15="","",'SDG4'!L15) -> EDUCON / Graduados | H12: =IF('SDG4'!M15="","",'SDG4'!M15) -> Desarrollo Profesoral / Comunicaciones / Biblioteca / Programas / Campus Virtual UDES / Talento Humano | I12: ='SDG4'!P15 -> Media | J12: ='SDG4'!Q15 -> Pendiente | K12: =IF('SDG4'!F15="","",'SDG4'!F15) | L12: =IF('SDG4'!G15="","",'SDG4'!G15) | M12: =IF('SDG4'!H15="","",'SDG4'!H15) | N12: =IF('SDG4'!I15="","",'SDG4'!I15) | O12: =IF('SDG4'!J15="","",'SDG4'!J15)
A13: ="ODS 4" -> ODS 4 | B13: ='SDG4'!B18 -> 4.3.4 | C13: ='SDG4'!D18 -> Actividades de divulgación educativa más allá del campus Emprender actividades de divulgación educativa (por ejemplo, conferencias o demostraciones personalizadas) más allá del campus, en las escuelas locales, en la comunidad. Esto puede incluir esquemas voluntarios dirigidos por estudiantes. | D13: ='SDG4'!O18 -> 0.05 | E13: ='SDG4'!N18 -> Evidencia pública | F13: ='SDG4'!K18 -> Planeación Institucional | G13: =IF('SDG4'!L18="","",'SDG4'!L18) -> EDUCON / Graduados | H13: =IF('SDG4'!M18="","",'SDG4'!M18) -> Desarrollo Profesoral / Comunicaciones / Biblioteca / Programas / Campus Virtual UDES / Talento Humano | I13: ='SDG4'!P18 -> Media | J13: ='SDG4'!Q18 -> Pendiente | K13: =IF('SDG4'!F18="","",'SDG4'!F18) | L13: =IF('SDG4'!G18="","",'SDG4'!G18) | M13: =IF('SDG4'!H18="","",'SDG4'!H18) | N13: =IF('SDG4'!I18="","",'SDG4'!I18) | O13: =IF('SDG4'!J18="","",'SDG4'!J18)
A14: ="ODS 4" -> ODS 4 | B14: ='SDG4'!B21 -> 4.3.5 | C14: ='SDG4'!D21 -> Política de acceso al aprendizaje permanente Una política que garantice que el acceso a estas actividades sea accesible para todos, independientemente de su origen étnico, religión, discapacidad, estado migratorio o género. | D14: ='SDG4'!O21 -> 0.068 | E14: ='SDG4'!N21 -> Política / evidencia pública | F14: ='SDG4'!K21 -> Planeación Institucional | G14: =IF('SDG4'!L21="","",'SDG4'!L21) -> Vicerrectoría de Enseñanza | H14: =IF('SDG4'!M21="","",'SDG4'!M21) -> Vicerrectoría de Extensión | I14: ='SDG4'!P21 -> Alta | J14: ='SDG4'!Q21 -> Pendiente | K14: =IF('SDG4'!F21="","",'SDG4'!F21) | L14: =IF('SDG4'!G21="","",'SDG4'!G21) | M14: =IF('SDG4'!H21="","",'SDG4'!H21) | N14: =IF('SDG4'!I21="","",'SDG4'!I21) | O14: =IF('SDG4'!J21="","",'SDG4'!J21)
A15: ="ODS 4" -> ODS 4 | B15: ='SDG4'!B23 -> 4.4.1 | C15: ='SDG4'!D23 -> Proporción de estudiantes de primera generación | D15: ='SDG4'!O23 -> 0.308 | E15: ='SDG4'!N23 -> Dato cuantitativo 2024 | F15: ='SDG4'!K23 -> Planeación Institucional | G15: =IF('SDG4'!L23="","",'SDG4'!L23) -> Planeación Institucional | H15: =IF('SDG4'!M23="","",'SDG4'!M23) -> Registro y Control Académico | I15: ='SDG4'!P23 -> Alta | J15: ='SDG4'!Q23 -> Pendiente | K15: =IF('SDG4'!F23="","",'SDG4'!F23) | L15: =IF('SDG4'!G23="","",'SDG4'!G23) | M15: =IF('SDG4'!H23="","",'SDG4'!H23) | N15: =IF('SDG4'!I23="","",'SDG4'!I23) | O15: =IF('SDG4'!J23="","",'SDG4'!J23)
A16: ="ODS 5" -> ODS 5 | B16: ='SDG5'!B4 -> 5.2.1 | C16: ='SDG5'!D4 -> Proporción de mujeres de primera generación | D16: ='SDG5'!O4 -> 0.154 | E16: ='SDG5'!N4 -> Dato cuantitativo 2024 | F16: ='SDG5'!K4 -> Planeación Institucional | G16: =IF('SDG5'!L4="","",'SDG5'!L4) -> Planeación Institucional | H16: =IF('SDG5'!M4="","",'SDG5'!M4) -> Registro y Control Académico | I16: ='SDG5'!P4 -> Alta | J16: ='SDG5'!Q4 -> Pendiente | K16: =IF('SDG5'!F4="","",'SDG5'!F4) | L16: =IF('SDG5'!G4="","",'SDG5'!G4) | M16: =IF('SDG5'!H4="","",'SDG5'!H4) | N16: =IF('SDG5'!I4="","",'SDG5'!I4) | O16: =IF('SDG5'!J4="","",'SDG5'!J4)
A17: ="ODS 5" -> ODS 5 | B17: ='SDG5'!B8 -> 5.3.1 | C17: ='SDG5'!D8 -> Seguimiento de las medidas de acceso Medir y rastrear sistemáticamente la tasa de solicitud, aceptación o entrada de las mujeres. | D17: ='SDG5'!O8 -> 0.016 | E17: ='SDG5'!N8 -> Evidencia pública | F17: ='SDG5'!K8 -> Planeación Institucional | G17: =IF('SDG5'!L8="","",'SDG5'!L8) -> Planeación Institucional | H17: =IF('SDG5'!M8="","",'SDG5'!M8) -> Vicerrectoría de Enseñanza / Registro y Control Académico | I17: ='SDG5'!P8 -> Media | J17: ='SDG5'!Q8 -> Pendiente | K17: =IF('SDG5'!F8="","",'SDG5'!F8) | L17: =IF('SDG5'!G8="","",'SDG5'!G8) | M17: =IF('SDG5'!H8="","",'SDG5'!H8) | N17: =IF('SDG5'!I8="","",'SDG5'!I8) | O17: =IF('SDG5'!J8="","",'SDG5'!J8)
A18: ="ODS 5" -> ODS 5 | B18: ='SDG5'!B9 -> 5.3.2 | C18: ='SDG5'!D9 -> Política para las solicitudes y la entrada de mujeres Tener una política (por ejemplo, un plan de acceso y participación) que aborde las solicitudes, la aceptación, el ingreso y la participación de las mujeres en la universidad. | D18: ='SDG5'!O9 -> 0.046 | E18: ='SDG5'!N9 -> Política / evidencia pública | F18: ='SDG5'!K9 -> Planeación Institucional | G18: =IF('SDG5'!L9="","",'SDG5'!L9) -> Planeación Institucional | H18: =IF('SDG5'!M9="","",'SDG5'!M9) -> Vicerrectoría de Enseñanza | I18: ='SDG5'!P9 -> Alta | J18: ='SDG5'!Q9 -> Pendiente | K18: =IF('SDG5'!F9="","",'SDG5'!F9) | L18: =IF('SDG5'!G9="","",'SDG5'!G9) | M18: =IF('SDG5'!H9="","",'SDG5'!H9) | N18: =IF('SDG5'!I9="","",'SDG5'!I9) | O18: =IF('SDG5'!J9="","",'SDG5'!J9)
A19: ="ODS 5" -> ODS 5 | B19: ='SDG5'!B10 -> 5.3.3 | C19: ='SDG5'!D10 -> Planes de acceso de las mujeres Proporcionar esquemas de acceso para mujeres, incluida tutoría, becas u otras disposiciones | D19: ='SDG5'!O10 -> 0.046 | E19: ='SDG5'!N10 -> Evidencia pública | F19: ='SDG5'!K10 -> Planeación Institucional | G19: =IF('SDG5'!L10="","",'SDG5'!L10) -> Planeación Institucional | H19: =IF('SDG5'!M10="","",'SDG5'!M10) -> Vicerrectoría de Enseñanza / Vicerrectoría de Investigaciones (Orquidea de la ciencia, otras mujeres), Conv Minciencias / Credito y Cartera / DRNI | I19: ='SDG5'!P10 -> Media | J19: ='SDG5'!Q10 -> Pendiente | K19: =IF('SDG5'!F10="","",'SDG5'!F10) | L19: =IF('SDG5'!G10="","",'SDG5'!G10) | M19: =IF('SDG5'!H10="","",'SDG5'!H10) | N19: =IF('SDG5'!I10="","",'SDG5'!I10) | O19: =IF('SDG5'!J10="","",'SDG5'!J10)
A20: ="ODS 5" -> ODS 5 | B20: ='SDG5'!B14 -> 5.3.4 | C20: ='SDG5'!D14 -> Solicitud de las mujeres en materias subrepresentadas Fomentar las solicitudes de mujeres en materias en las que están subrepresentadas. A través de la extensión universitaria o mediante la colaboración con otras universidades, grupos comunitarios, gobiernos u ONG en campañas regionales o nacionales. | D20: ='SDG5'!O14 -> 0.046 | E20: ='SDG5'!N14 -> Evidencia pública | F20: ='SDG5'!K14 -> Planeación Institucional | G20: =IF('SDG5'!L14="","",'SDG5'!L14) -> Planeación Institucional | H20: =IF('SDG5'!M14="","",'SDG5'!M14) -> Vicerrectoría de Extensión / Vicerrectoría de Enseñanza / Vicerrectoría de Investigaciones (Orquidea de la ciencia, otras mujeres), Conv Minciencias / Credito y Cartera / DRNI / Mujer y Hogar / Miudes | I20: ='SDG5'!P14 -> Media | J20: ='SDG5'!Q14 -> Pendiente | K20: =IF('SDG5'!F14="","",'SDG5'!F14) | L20: =IF('SDG5'!G14="","",'SDG5'!G14) | M20: =IF('SDG5'!H14="","",'SDG5'!H14) | N20: =IF('SDG5'!I14="","",'SDG5'!I14) | O20: =IF('SDG5'!J14="","",'SDG5'!J14)
A21: ="ODS 5" -> ODS 5 | B21: ='SDG5'!B18 -> 5.4.1 | C21: ='SDG5'!D18 -> Proporción de mujeres académicas de alto nivel | D21: ='SDG5'!O18 -> 0.154 | E21: ='SDG5'!N18 -> Dato cuantitativo 2024 | F21: ='SDG5'!K18 -> Planeación Institucional | G21: =IF('SDG5'!L18="","",'SDG5'!L18) -> Planeación Institucional | H21: =IF('SDG5'!M18="","",'SDG5'!M18) -> Talento Humano | I21: ='SDG5'!P18 -> Alta | J21: ='SDG5'!Q18 -> Pendiente | K21: =IF('SDG5'!F18="","",'SDG5'!F18) | L21: =IF('SDG5'!G18="","",'SDG5'!G18) | M21: =IF('SDG5'!H18="","",'SDG5'!H18) | N21: =IF('SDG5'!I18="","",'SDG5'!I18) | O21: =IF('SDG5'!J18="","",'SDG5'!J18)
A22: ="ODS 5" -> ODS 5 | B22: ='SDG5'!B22 -> 5.5.1 | C22: ='SDG5'!D22 -> Proporción de títulos femeninos otorgados | D22: ='SDG5'!O22 -> 0.115 | E22: ='SDG5'!N22 -> Dato cuantitativo 2024 | F22: ='SDG5'!K22 -> Planeación Institucional | G22: =IF('SDG5'!L22="","",'SDG5'!L22) -> Planeación Institucional | H22: =IF('SDG5'!M22="","",'SDG5'!M22) -> Registro y Control Académico | I22: ='SDG5'!P22 -> Alta | J22: ='SDG5'!Q22 -> Pendiente | K22: =IF('SDG5'!F22="","",'SDG5'!F22) | L22: =IF('SDG5'!G22="","",'SDG5'!G22) | M22: =IF('SDG5'!H22="","",'SDG5'!H22) | N22: =IF('SDG5'!I22="","",'SDG5'!I22) | O22: =IF('SDG5'!J22="","",'SDG5'!J22)
A23: ="ODS 5" -> ODS 5 | B23: ='SDG5'!B33 -> 5.6.1 | C23: ='SDG5'!D33 -> Política de no discriminación contra la mujer Tener una política de no discriminación contra las mujeres | D23: ='SDG5'!O33 -> 0.0195 | E23: ='SDG5'!N33 -> Política / evidencia pública | F23: ='SDG5'!K33 -> Planeación Institucional | G23: =IF('SDG5'!L33="","",'SDG5'!L33) -> Vicerrectoría de Enseñanza | H23: =IF('SDG5'!M33="","",'SDG5'!M33) -> Talento Humano | I23: ='SDG5'!P33 -> Alta | J23: ='SDG5'!Q33 -> Pendiente | K23: =IF('SDG5'!F33="","",'SDG5'!F33) | L23: =IF('SDG5'!G33="","",'SDG5'!G33) | M23: =IF('SDG5'!H33="","",'SDG5'!H33) | N23: =IF('SDG5'!I33="","",'SDG5'!I33) | O23: =IF('SDG5'!J33="","",'SDG5'!J33)
A24: ="ODS 5" -> ODS 5 | B24: ='SDG5'!B34 -> 5.6.2 | C24: ='SDG5'!D34 -> Políticas de no discriminación para las personas transgénero Tener una política de no discriminación para las personas transgénero. | D24: ='SDG5'!O34 -> 0.0195 | E24: ='SDG5'!N34 -> Política / evidencia pública | F24: ='SDG5'!K34 -> Planeación Institucional | G24: =IF('SDG5'!L34="","",'SDG5'!L34) -> Vicerrectoría de Enseñanza | H24: =IF('SDG5'!M34="","",'SDG5'!M34) -> Talento Humano | I24: ='SDG5'!P34 -> Alta | J24: ='SDG5'!Q34 -> Pendiente | K24: =IF('SDG5'!F34="","",'SDG5'!F34) | L24: =IF('SDG5'!G34="","",'SDG5'!G34) | M24: =IF('SDG5'!H34="","",'SDG5'!H34) | N24: =IF('SDG5'!I34="","",'SDG5'!I34) | O24: =IF('SDG5'!J34="","",'SDG5'!J34)
A25: ="ODS 5" -> ODS 5 | B25: ='SDG5'!B35 -> 5.6.3 | C25: ='SDG5'!D35 -> Política de maternidad Tener una política de maternidad que apoye la participación de las mujeres. | D25: ='SDG5'!O35 -> 0.0095 | E25: ='SDG5'!N35 -> Política / evidencia pública | F25: ='SDG5'!K35 -> Planeación Institucional | G25: =IF('SDG5'!L35="","",'SDG5'!L35) -> Vicerrectoría de Enseñanza | H25: =IF('SDG5'!M35="","",'SDG5'!M35) -> Talento Humano | I25: ='SDG5'!P35 -> Alta | J25: ='SDG5'!Q35 -> Pendiente | K25: =IF('SDG5'!F35="","",'SDG5'!F35) | L25: =IF('SDG5'!G35="","",'SDG5'!G35) | M25: =IF('SDG5'!H35="","",'SDG5'!H35) | N25: =IF('SDG5'!I35="","",'SDG5'!I35) | O25: =IF('SDG5'!J35="","",'SDG5'!J35)
A26: ="ODS 5" -> ODS 5 | B26: ='SDG5'!B36 -> 5.6.4 | C26: ='SDG5'!D36 -> Guarderías para estudiantes Tener guarderías accesibles para estudiantes que permitan a las madres recién nacidas asistir a la universidad Cursos. | D26: ='SDG5'!O36 -> 0.019 | E26: ='SDG5'!N36 -> Evidencia pública | F26: ='SDG5'!K36 -> Planeación Institucional | G26: =IF('SDG5'!L36="","",'SDG5'!L36) -> Vicerrectoría de Enseñanza | H26: =IF('SDG5'!M36="","",'SDG5'!M36) -> Talento Humano / Bienestar | I26: ='SDG5'!P36 -> Media | J26: ='SDG5'!Q36 -> Pendiente | K26: =IF('SDG5'!F36="","",'SDG5'!F36) | L26: =IF('SDG5'!G36="","",'SDG5'!G36) | M26: =IF('SDG5'!H36="","",'SDG5'!H36) | N26: =IF('SDG5'!I36="","",'SDG5'!I36) | O26: =IF('SDG5'!J36="","",'SDG5'!J36)
A27: ="ODS 5" -> ODS 5 | B27: ='SDG5'!B39 -> 5.6.5 | C27: ='SDG5'!D39 -> Instalaciones de cuidado infantil para el personal y la facultad Tener instalaciones de cuidado infantil para el personal y la facultad. | D27: ='SDG5'!O39 -> 0.019 | E27: ='SDG5'!N39 -> Evidencia pública | F27: ='SDG5'!K39 -> Planeación Institucional | G27: =IF('SDG5'!L39="","",'SDG5'!L39) -> Vicerrectoría de Enseñanza | H27: =IF('SDG5'!M39="","",'SDG5'!M39) -> Talento Humano / Bienestar | I27: ='SDG5'!P39 -> Media | J27: ='SDG5'!Q39 -> Pendiente | K27: =IF('SDG5'!F39="","",'SDG5'!F39) | L27: =IF('SDG5'!G39="","",'SDG5'!G39) | M27: =IF('SDG5'!H39="","",'SDG5'!H39) | N27: =IF('SDG5'!I39="","",'SDG5'!I39) | O27: =IF('SDG5'!J39="","",'SDG5'!J39)
A28: ="ODS 5" -> ODS 5 | B28: ='SDG5'!B42 -> 5.6.6 | C28: ='SDG5'!D42 -> Programas de tutoría para mujeres Tener programas de tutoría para mujeres, en los que participe al menos el 10% de las estudiantes. | D28: ='SDG5'!O42 -> 0.019 | E28: ='SDG5'!N42 -> Evidencia pública | F28: ='SDG5'!K42 -> Planeación Institucional | G28: =IF('SDG5'!L42="","",'SDG5'!L42) -> Vicerrectoría de Enseñanza | H28: =IF('SDG5'!M42="","",'SDG5'!M42) -> Talento Humano / Bienestar / Desarrollo Profesoral / Desarrollo Estudiantil / Campus Virtual UDES / Vicerrectoría de Extensión / Programa de Psicología y de Salud | I28: ='SDG5'!P42 -> Media | J28: ='SDG5'!Q42 -> Pendiente | K28: =IF('SDG5'!F42="","",'SDG5'!F42) | L28: =IF('SDG5'!G42="","",'SDG5'!G42) | M28: =IF('SDG5'!H42="","",'SDG5'!H42) | N28: =IF('SDG5'!I42="","",'SDG5'!I42) | O28: =IF('SDG5'!J42="","",'SDG5'!J42)
A29: ="ODS 5" -> ODS 5 | B29: ='SDG5'!B43 -> 5.6.7 | C29: ='SDG5'!D43 -> Seguimiento de la tasa de graduación de las mujeres Tener una medición o seguimiento de la probabilidad de graduación de las mujeres en comparación con la de los hombres, y esquemas para cerrar cualquier brecha. | D29: ='SDG5'!O43 -> 0.019 | E29: ='SDG5'!N43 -> Evidencia pública | F29: ='SDG5'!K43 -> Planeación Institucional | G29: =IF('SDG5'!L43="","",'SDG5'!L43) -> Planeación Institucional | H29: =IF('SDG5'!M43="","",'SDG5'!M43) -> Registro y Control Académico | I29: ='SDG5'!P43 -> Media | J29: ='SDG5'!Q43 -> Pendiente | K29: =IF('SDG5'!F43="","",'SDG5'!F43) | L29: =IF('SDG5'!G43="","",'SDG5'!G43) | M29: =IF('SDG5'!H43="","",'SDG5'!H43) | N29: =IF('SDG5'!I43="","",'SDG5'!I43) | O29: =IF('SDG5'!J43="","",'SDG5'!J43)
A30: ="ODS 5" -> ODS 5 | B30: ='SDG5'!B44 -> 5.6.8 | C30: ='SDG5'!D44 -> Políticas que protegen a quienes denuncian discriminación Tener una política que proteja a quienes denuncian discriminación de desventajas educativas o laborales | D30: ='SDG5'!O44 -> 0.019 | E30: ='SDG5'!N44 -> Política / evidencia pública | F30: ='SDG5'!K44 -> Planeación Institucional | G30: =IF('SDG5'!L44="","",'SDG5'!L44) -> Vicerrectoría de Enseñanza | H30: =IF('SDG5'!M44="","",'SDG5'!M44) -> Talento Humano / Bienestar | I30: ='SDG5'!P44 -> Alta | J30: ='SDG5'!Q44 -> Pendiente | K30: =IF('SDG5'!F44="","",'SDG5'!F44) | L30: =IF('SDG5'!G44="","",'SDG5'!G44) | M30: =IF('SDG5'!H44="","",'SDG5'!H44) | N30: =IF('SDG5'!I44="","",'SDG5'!I44) | O30: =IF('SDG5'!J44="","",'SDG5'!J44)
A31: ="ODS 5" -> ODS 5 | B31: ='SDG5'!B45 -> 5.6.9 | C31: ='SDG5'!D45 -> Política de paternidad Tener una política de paternidad que apoye la participación de las mujeres al garantizar que los padres puedan participar en las tareas de cuidado de los niños. | D31: ='SDG5'!O45 -> 0.0095 | E31: ='SDG5'!N45 -> Política / evidencia pública | F31: ='SDG5'!K45 -> Planeación Institucional | G31: =IF('SDG5'!L45="","",'SDG5'!L45) -> Vicerrectoría de Enseñanza | H31: =IF('SDG5'!M45="","",'SDG5'!M45) -> Talento Humano / Bienestar | I31: ='SDG5'!P45 -> Alta | J31: ='SDG5'!Q45 -> Pendiente | K31: =IF('SDG5'!F45="","",'SDG5'!F45) | L31: =IF('SDG5'!G45="","",'SDG5'!G45) | M31: =IF('SDG5'!H45="","",'SDG5'!H45) | N31: =IF('SDG5'!I45="","",'SDG5'!I45) | O31: =IF('SDG5'!J45="","",'SDG5'!J45)
A32: ="ODS 10" -> ODS 10 | B32: ='SDG10'!B4 -> 10.2.1 | C32: ='SDG10'!D4 -> Proporción de estudiantes de primera generación | D32: ='SDG10'!O4 -> 0.155 | E32: ='SDG10'!N4 -> Dato cuantitativo 2024 | F32: ='SDG10'!K4 -> Planeación Institucional | G32: =IF('SDG10'!L4="","",'SDG10'!L4) -> Planeación Institucional | H32: =IF('SDG10'!M4="","",'SDG10'!M4) -> Registro y Control Académico | I32: ='SDG10'!P4 -> Alta | J32: ='SDG10'!Q4 -> Pendiente | K32: =IF('SDG10'!F4="","",'SDG10'!F4) | L32: =IF('SDG10'!G4="","",'SDG10'!G4) | M32: =IF('SDG10'!H4="","",'SDG10'!H4) | N32: =IF('SDG10'!I4="","",'SDG10'!I4) | O32: =IF('SDG10'!J4="","",'SDG10'!J4)
A33: ="ODS 10" -> ODS 10 | B33: ='SDG10'!B8 -> 10.3.1 | C33: ='SDG10'!D8 -> Proporción de estudiantes internacionales de países en desarrollo | D33: ='SDG10'!O8 -> 0.155 | E33: ='SDG10'!N8 -> Dato cuantitativo 2024 | F33: ='SDG10'!K8 -> Planeación Institucional | G33: =IF('SDG10'!L8="","",'SDG10'!L8) -> Planeación Institucional | H33: =IF('SDG10'!M8="","",'SDG10'!M8) -> DRNI | I33: ='SDG10'!P8 -> Alta | J33: ='SDG10'!Q8 -> Pendiente | K33: =IF('SDG10'!F8="","",'SDG10'!F8) | L33: =IF('SDG10'!G8="","",'SDG10'!G8) | M33: =IF('SDG10'!H8="","",'SDG10'!H8) | N33: =IF('SDG10'!I8="","",'SDG10'!I8) | O33: =IF('SDG10'!J8="","",'SDG10'!J8)
A34: ="ODS 10" -> ODS 10 | B34: ='SDG10'!B12 -> 10.4.1 | C34: ='SDG10'!D12 -> Proporción de estudiantes con discapacidad | D34: ='SDG10'!O12 -> 0.115 | E34: ='SDG10'!N12 -> Dato cuantitativo 2024 | F34: ='SDG10'!K12 -> Planeación Institucional | G34: =IF('SDG10'!L12="","",'SDG10'!L12) -> Planeación Institucional | H34: =IF('SDG10'!M12="","",'SDG10'!M12) -> Bienestar / Desarrollo Estudiantil | I34: ='SDG10'!P12 -> Alta | J34: ='SDG10'!Q12 -> Pendiente | K34: =IF('SDG10'!F12="","",'SDG10'!F12) | L34: =IF('SDG10'!G12="","",'SDG10'!G12) | M34: =IF('SDG10'!H12="","",'SDG10'!H12) | N34: =IF('SDG10'!I12="","",'SDG10'!I12) | O34: =IF('SDG10'!J12="","",'SDG10'!J12)
A35: ="ODS 10" -> ODS 10 | B35: ='SDG10'!B16 -> 10.5.1 | C35: ='SDG10'!D16 -> Proporción de empleados con discapacidad | D35: ='SDG10'!O16 -> 0.115 | E35: ='SDG10'!N16 -> Dato cuantitativo 2024 | F35: ='SDG10'!K16 -> Planeación Institucional | G35: =IF('SDG10'!L16="","",'SDG10'!L16) -> Talento Humano | H35: =IF('SDG10'!M16="","",'SDG10'!M16) -> Planeación Institucional | I35: ='SDG10'!P16 -> Alta | J35: ='SDG10'!Q16 -> Pendiente | K35: =IF('SDG10'!F16="","",'SDG10'!F16) | L35: =IF('SDG10'!G16="","",'SDG10'!G16) | M35: =IF('SDG10'!H16="","",'SDG10'!H16) | N35: =IF('SDG10'!I16="","",'SDG10'!I16) | O35: =IF('SDG10'!J16="","",'SDG10'!J16)
A36: ="ODS 10" -> ODS 10 | B36: ='SDG10'!B20 -> 10.6.1 | C36: ='SDG10'!D20 -> Política de admisión no discriminatoria Tener una política de admisión que no sea discriminatoria o que detalle y explique la lógica de cualquier política de discriminación positiva apropiada en las admisiones. | D36: ='SDG10'!O20 -> 0.019 | E36: ='SDG10'!N20 -> Política / evidencia pública | F36: ='SDG10'!K20 -> Planeación Institucional | G36: =IF('SDG10'!L20="","",'SDG10'!L20) -> Vicerrectoría de Enseñanza | H36: =IF('SDG10'!M20="","",'SDG10'!M20) -> Talento Humano / Registro y Control Académico | I36: ='SDG10'!P20 -> Alta | J36: ='SDG10'!Q20 -> Pendiente | K36: =IF('SDG10'!F20="","",'SDG10'!F20) | L36: =IF('SDG10'!G20="","",'SDG10'!G20) | M36: =IF('SDG10'!H20="","",'SDG10'!H20) | N36: =IF('SDG10'!I20="","",'SDG10'!I20) | O36: =IF('SDG10'!J20="","",'SDG10'!J20)
A37: ="ODS 10" -> ODS 10 | B37: ='SDG10'!B21 -> 10.6.2 | C37: ='SDG10'!D21 -> Acceso a la universidad, seguimiento de solicitudes de grupos subrepresentados Mida y realice un seguimiento de las solicitudes y admisiones de grupos subrepresentados (y potencialmente subrepresentados), incluidas minorías étnicas, estudiantes de bajos ingresos, estudiantes no tradicionales, mujeres, estudiantes LGBT, estudiantes discapacitados y estudiantes refugiados recién establecidos. | D37: ='SDG10'!O21 -> 0.019 | E37: ='SDG10'!N21 -> Evidencia pública | F37: ='SDG10'!K21 -> Planeación Institucional | G37: =IF('SDG10'!L21="","",'SDG10'!L21) -> Planeación Institucional | H37: =IF('SDG10'!M21="","",'SDG10'!M21) -> Vicerrectoría de Enseñanza / Registro y Control Académico / Bienestar | I37: ='SDG10'!P21 -> Media | J37: ='SDG10'!Q21 -> Pendiente | K37: =IF('SDG10'!F21="","",'SDG10'!F21) | L37: =IF('SDG10'!G21="","",'SDG10'!G21) | M37: =IF('SDG10'!H21="","",'SDG10'!H21) | N37: =IF('SDG10'!I21="","",'SDG10'!I21) | O37: =IF('SDG10'!J21="","",'SDG10'!J21)
A38: ="ODS 10" -> ODS 10 | B38: ='SDG10'!B22 -> 10.6.3 | C38: ='SDG10'!D22 -> Acceso a la universidad recluta a grupos subrepresentados Tomar medidas planificadas para reclutar estudiantes, personal y profesores de grupos subrepresentados | D38: ='SDG10'!O22 -> 0.019 | E38: ='SDG10'!N22 -> Evidencia pública | F38: ='SDG10'!K22 -> Planeación Institucional | G38: =IF('SDG10'!L22="","",'SDG10'!L22) -> Vicerrectoría de Enseñanza | H38: =IF('SDG10'!M22="","",'SDG10'!M22) -> Talento Humano / Mercadeo Institucional / Desarrollo Profesoral | I38: ='SDG10'!P22 -> Media | J38: ='SDG10'!Q22 -> Pendiente | K38: =IF('SDG10'!F22="","",'SDG10'!F22) | L38: =IF('SDG10'!G22="","",'SDG10'!G22) | M38: =IF('SDG10'!H22="","",'SDG10'!H22) | N38: =IF('SDG10'!I22="","",'SDG10'!I22) | O38: =IF('SDG10'!J22="","",'SDG10'!J22)
A39: ="ODS 10" -> ODS 10 | B39: ='SDG10'!B23 -> 10.6.4 | C39: ='SDG10'!D23 -> Políticas contra la discriminación Tener una política antidiscriminatoria que abarque a la institución y sus operaciones. | D39: ='SDG10'!O23 -> 0.0095 | E39: ='SDG10'!N23 -> Política / evidencia pública | F39: ='SDG10'!K23 -> Planeación Institucional | G39: =IF('SDG10'!L23="","",'SDG10'!L23) -> COPASST | H39: =IF('SDG10'!M23="","",'SDG10'!M23) -> VAF / Comité de Inclusión / Talento Humano | I39: ='SDG10'!P23 -> Alta | J39: ='SDG10'!Q23 -> Pendiente | K39: =IF('SDG10'!F23="","",'SDG10'!F23) | L39: =IF('SDG10'!G23="","",'SDG10'!G23) | M39: =IF('SDG10'!H23="","",'SDG10'!H23) | N39: =IF('SDG10'!I23="","",'SDG10'!I23) | O39: =IF('SDG10'!J23="","",'SDG10'!J23)
A40: ="ODS 10" -> ODS 10 | B40: ='SDG10'!B24 -> 10.6.5 | C40: ='SDG10'!D24 -> Oficial de diversidad universitaria Tener un comité, oficina o funcionario de diversidad e igualdad (o su equivalente) encargado por la administración o el órgano de gobierno de asesorar e implementar políticas, programas y capacitaciones relacionados con la diversidad, la equidad, la inclusión y los derechos humanos en el campus. | D40: ='SDG10'!O24 -> 0.019 | E40: ='SDG10'!N24 -> Evidencia pública | F40: ='SDG10'!K24 -> Planeación Institucional | G40: =IF('SDG10'!L24="","",'SDG10'!L24) -> Comité de Inclusión | H40: =IF('SDG10'!M24="","",'SDG10'!M24) | I40: ='SDG10'!P24 -> Media | J40: ='SDG10'!Q24 -> Pendiente | K40: =IF('SDG10'!F24="","",'SDG10'!F24) | L40: =IF('SDG10'!G24="","",'SDG10'!G24) | M40: =IF('SDG10'!H24="","",'SDG10'!H24) | N40: =IF('SDG10'!I24="","",'SDG10'!I24) | O40: =IF('SDG10'!J24="","",'SDG10'!J24)
A41: ="ODS 10" -> ODS 10 | B41: ='SDG10'!B25 -> 10.6.6 | C41: ='SDG10'!D25 -> Apoyo a grupos subrepresentados Proporcionar programas de tutoría, asesoramiento o apoyo entre pares para apoyar a los estudiantes, el personal y el profesorado de grupos subrepresentados. | D41: ='SDG10'!O25 -> 0.019 | E41: ='SDG10'!N25 -> Evidencia pública | F41: ='SDG10'!K25 -> Planeación Institucional | G41: =IF('SDG10'!L25="","",'SDG10'!L25) -> Bienestar | H41: =IF('SDG10'!M25="","",'SDG10'!M25) -> Desarrollo Estudiantil / Desarrollo Profesoral / Talento Humano | I41: ='SDG10'!P25 -> Media | J41: ='SDG10'!Q25 -> Pendiente | K41: =IF('SDG10'!F25="","",'SDG10'!F25) | L41: =IF('SDG10'!G25="","",'SDG10'!G25) | M41: =IF('SDG10'!H25="","",'SDG10'!H25) | N41: =IF('SDG10'!I25="","",'SDG10'!I25) | O41: =IF('SDG10'!J25="","",'SDG10'!J25)
A42: ="ODS 10" -> ODS 10 | B42: ='SDG10'!B26 -> 10.6.7 | C42: ='SDG10'!D26 -> Instalaciones accesibles Proporcionar instalaciones accesibles para personas con discapacidades. | D42: ='SDG10'!O26 -> 0.019 | E42: ='SDG10'!N26 -> Evidencia pública | F42: ='SDG10'!K26 -> Planeación Institucional | G42: =IF('SDG10'!L26="","",'SDG10'!L26) -> Planta Física | H42: =IF('SDG10'!M26="","",'SDG10'!M26) | I42: ='SDG10'!P26 -> Media | J42: ='SDG10'!Q26 -> Pendiente | K42: =IF('SDG10'!F26="","",'SDG10'!F26) | L42: =IF('SDG10'!G26="","",'SDG10'!G26) | M42: =IF('SDG10'!H26="","",'SDG10'!H26) | N42: =IF('SDG10'!I26="","",'SDG10'!I26) | O42: =IF('SDG10'!J26="","",'SDG10'!J26)
A43: ="ODS 10" -> ODS 10 | B43: ='SDG10'!B27 -> 10.6.8 | C43: ='SDG10'!D27 -> Servicios de apoyo a la discapacidad Servicios de apoyo para personas con discapacidad. | D43: ='SDG10'!O27 -> 0.019 | E43: ='SDG10'!N27 -> Evidencia pública | F43: ='SDG10'!K27 -> Planeación Institucional | G43: =IF('SDG10'!L27="","",'SDG10'!L27) -> Bienestar | H43: =IF('SDG10'!M27="","",'SDG10'!M27) -> Desarrollo Estudiantil / Desarrollo Profesoral / Talento Humano / Biblioteca / Planta Física | I43: ='SDG10'!P27 -> Media | J43: ='SDG10'!Q27 -> Pendiente | K43: =IF('SDG10'!F27="","",'SDG10'!F27) | L43: =IF('SDG10'!G27="","",'SDG10'!G27) | M43: =IF('SDG10'!H27="","",'SDG10'!H27) | N43: =IF('SDG10'!I27="","",'SDG10'!I27) | O43: =IF('SDG10'!J27="","",'SDG10'!J27)
A44: ="ODS 10" -> ODS 10 | B44: ='SDG10'!B28 -> 10.6.9 | C44: ='SDG10'!D28 -> Esquema de acceso para discapacitados Proporcionar esquemas de acceso para personas con discapacidad, como tutoría u otro apoyo específico. | D44: ='SDG10'!O28 -> 0.019 | E44: ='SDG10'!N28 -> Evidencia pública | F44: ='SDG10'!K28 -> Planeación Institucional | G44: =IF('SDG10'!L28="","",'SDG10'!L28) -> Bienestar | H44: =IF('SDG10'!M28="","",'SDG10'!M28) -> Desarrollo Estudiantil / Desarrollo Profesoral / Talento Humano / Biblioteca / Planta Física | I44: ='SDG10'!P28 -> Media | J44: ='SDG10'!Q28 -> Pendiente | K44: =IF('SDG10'!F28="","",'SDG10'!F28) | L44: =IF('SDG10'!G28="","",'SDG10'!G28) | M44: =IF('SDG10'!H28="","",'SDG10'!H28) | N44: =IF('SDG10'!I28="","",'SDG10'!I28) | O44: =IF('SDG10'!J28="","",'SDG10'!J28)
A45: ="ODS 10" -> ODS 10 | B45: ='SDG10'!B31 -> 10.6.10 | C45: ='SDG10'!D31 -> Política de adaptación para discapacitados Tener una política o estrategia de adaptación razonable para las personas con discapacidades, incluida la financiación adecuada | D45: ='SDG10'!O31 -> 0.019 | E45: ='SDG10'!N31 -> Evidencia pública | F45: ='SDG10'!K31 -> Planeación Institucional | G45: =IF('SDG10'!L31="","",'SDG10'!L31) -> Talento Humano | H45: =IF('SDG10'!M31="","",'SDG10'!M31) -> Comité de Inclusión / Bienestar | I45: ='SDG10'!P31 -> Media | J45: ='SDG10'!Q31 -> Pendiente | K45: =IF('SDG10'!F31="","",'SDG10'!F31) | L45: =IF('SDG10'!G31="","",'SDG10'!G31) | M45: =IF('SDG10'!H31="","",'SDG10'!H31) | N45: =IF('SDG10'!I31="","",'SDG10'!I31) | O45: =IF('SDG10'!J31="","",'SDG10'!J31)
A46: ="ODS 10" -> ODS 10 | B46: ='SDG10'!B32 -> 10.6.11 | C46: ='SDG10'!D32 -> Política contra el acoso Tener una política contra el acoso que cubra la institución y sus operaciones. | D46: ='SDG10'!O32 -> 0.0095 | E46: ='SDG10'!N32 -> Política / evidencia pública | F46: ='SDG10'!K32 -> Planeación Institucional | G46: =IF('SDG10'!L32="","",'SDG10'!L32) -> Talento Humano | H46: =IF('SDG10'!M32="","",'SDG10'!M32) -> Comité de convivencia laboral | I46: ='SDG10'!P32 -> Alta | J46: ='SDG10'!Q32 -> Pendiente | K46: =IF('SDG10'!F32="","",'SDG10'!F32) | L46: =IF('SDG10'!G32="","",'SDG10'!G32) | M46: =IF('SDG10'!H32="","",'SDG10'!H32) | N46: =IF('SDG10'!I32="","",'SDG10'!I32) | O46: =IF('SDG10'!J32="","",'SDG10'!J32)
A47: ="ODS 17" -> ODS 17 | B47: ='SDG17'!B4 -> 17.2.1 | C47: ='SDG17'!D4 -> Relaciones con ONG regionales y gobierno para la política de los ODS Tener participación directa o aportes en el gobierno nacional o en organizaciones no gubernamentales regionales, el desarrollo de políticas de los ODS, incluida la identificación de problemas y desafíos, el desarrollo de políticas y estrategias, el modelado de futuros probables con y sin intervenciones, el monitoreo y la presentación de informes sobre las intervenciones, y la habilitación de la gestión adaptativa | D47: ='SDG17'!O4 -> 0.037 | E47: ='SDG17'!N4 -> Evidencia pública | F47: ='SDG17'!K4 -> Planeación Institucional | G47: =IF('SDG17'!L4="","",'SDG17'!L4) -> Planeación Institucional | H47: =IF('SDG17'!M4="","",'SDG17'!M4) -> Vicerrectoría de Extensión / Vicerrectoría de Investigaciones / DRNI / Comunicaciones | I47: ='SDG17'!P4 -> Media | J47: ='SDG17'!Q4 -> Pendiente | K47: =IF('SDG17'!F4="","",'SDG17'!F4) | L47: =IF('SDG17'!G4="","",'SDG17'!G4) | M47: =IF('SDG17'!H4="","",'SDG17'!H4) | N47: =IF('SDG17'!I4="","",'SDG17'!I4) | O47: =IF('SDG17'!J4="","",'SDG17'!J4)
A48: ="ODS 17" -> ODS 17 | B48: ='SDG17'!B5 -> 17.2.2 | C48: ='SDG17'!D5 -> Diálogo intersectorial sobre los ODS Iniciar y participar en un diálogo intersectorial sobre los ODS, por ejemplo, conferencias en las que participen gobiernos u ONG. | D48: ='SDG17'!O5 -> 0.037 | E48: ='SDG17'!N5 -> Evidencia pública | F48: ='SDG17'!K5 -> Planeación Institucional | G48: =IF('SDG17'!L5="","",'SDG17'!L5) -> Planeación Institucional | H48: =IF('SDG17'!M5="","",'SDG17'!M5) -> Vicerrectoría de Extensión / Vicerrectoría de Investigaciones / Comunicaciones | I48: ='SDG17'!P5 -> Media | J48: ='SDG17'!Q5 -> Pendiente | K48: =IF('SDG17'!F5="","",'SDG17'!F5) | L48: =IF('SDG17'!G5="","",'SDG17'!G5) | M48: =IF('SDG17'!H5="","",'SDG17'!H5) | N48: =IF('SDG17'!I5="","",'SDG17'!I5) | O48: =IF('SDG17'!J5="","",'SDG17'!J5)
A49: ="ODS 17" -> ODS 17 | B49: ='SDG17'!B6 -> 17.2.3 | C49: ='SDG17'!D6 -> Recopilación de datos de colaboración internacional para los ODS Participar en la colaboración internacional en la recopilación o medición de datos para los ODS | D49: ='SDG17'!O6 -> 0.037 | E49: ='SDG17'!N6 -> Evidencia pública | F49: ='SDG17'!K6 -> Planeación Institucional | G49: =IF('SDG17'!L6="","",'SDG17'!L6) -> Planeación Institucional | H49: =IF('SDG17'!M6="","",'SDG17'!M6) -> Vicerrectoría de Investigaciones / DRNI | I49: ='SDG17'!P6 -> Media | J49: ='SDG17'!Q6 -> Pendiente | K49: =IF('SDG17'!F6="","",'SDG17'!F6) | L49: =IF('SDG17'!G6="","",'SDG17'!G6) | M49: =IF('SDG17'!H6="","",'SDG17'!H6) | N49: =IF('SDG17'!I6="","",'SDG17'!I6) | O49: =IF('SDG17'!J6="","",'SDG17'!J6)
A50: ="ODS 17" -> ODS 17 | B50: ='SDG17'!B7 -> 17.2.4 | C50: ='SDG17'!D7 -> Colaboración para las mejores prácticas de los ODS A través de la colaboración y la investigación internacionales, revisar los enfoques comparativos y desarrollar las mejores prácticas internacionales para abordar los ODS. | D50: ='SDG17'!O7 -> 0.037 | E50: ='SDG17'!N7 -> Evidencia pública | F50: ='SDG17'!K7 -> Planeación Institucional | G50: =IF('SDG17'!L7="","",'SDG17'!L7) -> Planeación Institucional | H50: =IF('SDG17'!M7="","",'SDG17'!M7) -> Vicerrectoría de Investigaciones / DRNI | I50: ='SDG17'!P7 -> Media | J50: ='SDG17'!Q7 -> Pendiente | K50: =IF('SDG17'!F7="","",'SDG17'!F7) | L50: =IF('SDG17'!G7="","",'SDG17'!G7) | M50: =IF('SDG17'!H7="","",'SDG17'!H7) | N50: =IF('SDG17'!I7="","",'SDG17'!I7) | O50: =IF('SDG17'!J7="","",'SDG17'!J7)
A51: ="ODS 17" -> ODS 17 | B51: ='SDG17'!B8 -> 17.2.5 | C51: ='SDG17'!D8 -> Colaboración con ONG para los ODS Colaborar con las ONG para abordar los ODS a través de: programas de voluntariado estudiantil, programas de investigación o desarrollo de recursos educativos | D51: ='SDG17'!O8 -> 0.037 | E51: ='SDG17'!N8 -> Evidencia pública | F51: ='SDG17'!K8 -> Planeación Institucional | G51: =IF('SDG17'!L8="","",'SDG17'!L8) -> Planeación Institucional | H51: =IF('SDG17'!M8="","",'SDG17'!M8) -> Bienestar / Vicerrectoría de Investigaciones / DRNI / Educación Virtual | I51: ='SDG17'!P8 -> Media | J51: ='SDG17'!Q8 -> Pendiente | K51: =IF('SDG17'!F8="","",'SDG17'!F8) | L51: =IF('SDG17'!G8="","",'SDG17'!G8) | M51: =IF('SDG17'!H8="","",'SDG17'!H8) | N51: =IF('SDG17'!I8="","",'SDG17'!I8) | O51: =IF('SDG17'!J8="","",'SDG17'!J8)
A52: ="ODS 17" -> ODS 17 | B52: ='SDG17'!B13 -> 17.3.1 | C52: ='SDG17'!D13 -> Publicación de informes sobre los ODS - por ODS Publicar el progreso con respecto al ODS 1, ya sea individualmente o dentro de un informe anual | D52: ='SDG17'!O13 -> 0.016 | E52: ='SDG17'!N13 -> Evidencia pública | F52: ='SDG17'!K13 -> Planeación Institucional | G52: =IF('SDG17'!L13="","",'SDG17'!L13) -> Planeación Institucional | H52: =IF('SDG17'!M13="","",'SDG17'!M13) -> Comunicaciones / Vicerrectorías y unidades responsables por ODS | I52: ='SDG17'!P13 -> Media | J52: ='SDG17'!Q13 -> Pendiente | K52: =IF('SDG17'!F13="","",'SDG17'!F13) | L52: =IF('SDG17'!G13="","",'SDG17'!G13) | M52: =IF('SDG17'!H13="","",'SDG17'!H13) | N52: =IF('SDG17'!I13="","",'SDG17'!I13) | O52: =IF('SDG17'!J13="","",'SDG17'!J13)
A53: ="ODS 17" -> ODS 17 | B53: ='SDG17'!B16 -> 17.3.2 | C53: ='SDG17'!D16 -> Publicación de informes sobre los ODS - por ODS Publicar el progreso con respecto al ODS 2, ya sea individualmente o dentro de un informe anual | D53: ='SDG17'!O16 -> 0.016 | E53: ='SDG17'!N16 -> Evidencia pública | F53: ='SDG17'!K16 -> Planeación Institucional | G53: =IF('SDG17'!L16="","",'SDG17'!L16) -> Planeación Institucional | H53: =IF('SDG17'!M16="","",'SDG17'!M16) -> Comunicaciones / Vicerrectorías y unidades responsables por ODS | I53: ='SDG17'!P16 -> Media | J53: ='SDG17'!Q16 -> Pendiente | K53: =IF('SDG17'!F16="","",'SDG17'!F16) | L53: =IF('SDG17'!G16="","",'SDG17'!G16) | M53: =IF('SDG17'!H16="","",'SDG17'!H16) | N53: =IF('SDG17'!I16="","",'SDG17'!I16) | O53: =IF('SDG17'!J16="","",'SDG17'!J16)
A54: ="ODS 17" -> ODS 17 | B54: ='SDG17'!B19 -> 17.3.3 | C54: ='SDG17'!D19 -> Publicación de informes sobre los ODS - por ODS Publicar el progreso con respecto al ODS 3, ya sea individualmente o dentro de un informe anual | D54: ='SDG17'!O19 -> 0.016 | E54: ='SDG17'!N19 -> Evidencia pública | F54: ='SDG17'!K19 -> Planeación Institucional | G54: =IF('SDG17'!L19="","",'SDG17'!L19) -> Planeación Institucional | H54: =IF('SDG17'!M19="","",'SDG17'!M19) -> Comunicaciones / Vicerrectorías y unidades responsables por ODS | I54: ='SDG17'!P19 -> Media | J54: ='SDG17'!Q19 -> Pendiente | K54: =IF('SDG17'!F19="","",'SDG17'!F19) | L54: =IF('SDG17'!G19="","",'SDG17'!G19) | M54: =IF('SDG17'!H19="","",'SDG17'!H19) | N54: =IF('SDG17'!I19="","",'SDG17'!I19) | O54: =IF('SDG17'!J19="","",'SDG17'!J19)
A55: ="ODS 17" -> ODS 17 | B55: ='SDG17'!B22 -> 17.3.4 | C55: ='SDG17'!D22 -> Publicación de informes sobre los ODS - por ODS Publicar el progreso con respecto al ODS 4, ya sea individualmente o dentro de un informe anual | D55: ='SDG17'!O22 -> 0.016 | E55: ='SDG17'!N22 -> Evidencia pública | F55: ='SDG17'!K22 -> Planeación Institucional | G55: =IF('SDG17'!L22="","",'SDG17'!L22) -> Planeación Institucional | H55: =IF('SDG17'!M22="","",'SDG17'!M22) -> Comunicaciones / Vicerrectorías y unidades responsables por ODS | I55: ='SDG17'!P22 -> Media | J55: ='SDG17'!Q22 -> Pendiente | K55: =IF('SDG17'!F22="","",'SDG17'!F22) | L55: =IF('SDG17'!G22="","",'SDG17'!G22) | M55: =IF('SDG17'!H22="","",'SDG17'!H22) | N55: =IF('SDG17'!I22="","",'SDG17'!I22) | O55: =IF('SDG17'!J22="","",'SDG17'!J22)
A56: ="ODS 17" -> ODS 17 | B56: ='SDG17'!B25 -> 17.3.5 | C56: ='SDG17'!D25 -> Publicación de informes sobre los ODS - por ODS Publicar el progreso con respecto al ODS 5, ya sea individualmente o dentro de un informe anual | D56: ='SDG17'!O25 -> 0.016 | E56: ='SDG17'!N25 -> Evidencia pública | F56: ='SDG17'!K25 -> Planeación Institucional | G56: =IF('SDG17'!L25="","",'SDG17'!L25) -> Planeación Institucional | H56: =IF('SDG17'!M25="","",'SDG17'!M25) -> Comunicaciones / Vicerrectorías y unidades responsables por ODS | I56: ='SDG17'!P25 -> Media | J56: ='SDG17'!Q25 -> Pendiente | K56: =IF('SDG17'!F25="","",'SDG17'!F25) | L56: =IF('SDG17'!G25="","",'SDG17'!G25) | M56: =IF('SDG17'!H25="","",'SDG17'!H25) | N56: =IF('SDG17'!I25="","",'SDG17'!I25) | O56: =IF('SDG17'!J25="","",'SDG17'!J25)
A57: ="ODS 17" -> ODS 17 | B57: ='SDG17'!B28 -> 17.3.6 | C57: ='SDG17'!D28 -> Publicación de informes sobre los ODS - por ODS Publicar el progreso con respecto al ODS 6, ya sea individualmente o dentro de un informe anual | D57: ='SDG17'!O28 -> 0.016 | E57: ='SDG17'!N28 -> Evidencia pública | F57: ='SDG17'!K28 -> Planeación Institucional | G57: =IF('SDG17'!L28="","",'SDG17'!L28) -> Planeación Institucional | H57: =IF('SDG17'!M28="","",'SDG17'!M28) -> Comunicaciones / Vicerrectorías y unidades responsables por ODS | I57: ='SDG17'!P28 -> Media | J57: ='SDG17'!Q28 -> Pendiente | K57: =IF('SDG17'!F28="","",'SDG17'!F28) | L57: =IF('SDG17'!G28="","",'SDG17'!G28) | M57: =IF('SDG17'!H28="","",'SDG17'!H28) | N57: =IF('SDG17'!I28="","",'SDG17'!I28) | O57: =IF('SDG17'!J28="","",'SDG17'!J28)
A58: ="ODS 17" -> ODS 17 | B58: ='SDG17'!B31 -> 17.3.7 | C58: ='SDG17'!D31 -> Publicación de informes sobre los ODS - por ODS Publicar el progreso con respecto al ODS 7, ya sea individualmente o dentro de un informe anual | D58: ='SDG17'!O31 -> 0.016 | E58: ='SDG17'!N31 -> Evidencia pública | F58: ='SDG17'!K31 -> Planeación Institucional | G58: =IF('SDG17'!L31="","",'SDG17'!L31) -> Planeación Institucional | H58: =IF('SDG17'!M31="","",'SDG17'!M31) -> Comunicaciones / Vicerrectorías y unidades responsables por ODS | I58: ='SDG17'!P31 -> Media | J58: ='SDG17'!Q31 -> Pendiente | K58: =IF('SDG17'!F31="","",'SDG17'!F31) | L58: =IF('SDG17'!G31="","",'SDG17'!G31) | M58: =IF('SDG17'!H31="","",'SDG17'!H31) | N58: =IF('SDG17'!I31="","",'SDG17'!I31) | O58: =IF('SDG17'!J31="","",'SDG17'!J31)
A59: ="ODS 17" -> ODS 17 | B59: ='SDG17'!B34 -> 17.3.8 | C59: ='SDG17'!D34 -> Publicación de informes sobre los ODS - por ODS Publicar el progreso con respecto al ODS 8, ya sea individualmente o dentro de un informe anual | D59: ='SDG17'!O34 -> 0.016 | E59: ='SDG17'!N34 -> Evidencia pública | F59: ='SDG17'!K34 -> Planeación Institucional | G59: =IF('SDG17'!L34="","",'SDG17'!L34) -> Planeación Institucional | H59: =IF('SDG17'!M34="","",'SDG17'!M34) -> Comunicaciones / Vicerrectorías y unidades responsables por ODS | I59: ='SDG17'!P34 -> Media | J59: ='SDG17'!Q34 -> Pendiente | K59: =IF('SDG17'!F34="","",'SDG17'!F34) | L59: =IF('SDG17'!G34="","",'SDG17'!G34) | M59: =IF('SDG17'!H34="","",'SDG17'!H34) | N59: =IF('SDG17'!I34="","",'SDG17'!I34) | O59: =IF('SDG17'!J34="","",'SDG17'!J34)
A60: ="ODS 17" -> ODS 17 | B60: ='SDG17'!B37 -> 17.3.9 | C60: ='SDG17'!D37 -> Publicación de informes sobre los ODS - por ODS Publicar el progreso con respecto al ODS 9, ya sea individualmente o dentro de un informe anual | D60: ='SDG17'!O37 -> 0.016 | E60: ='SDG17'!N37 -> Evidencia pública | F60: ='SDG17'!K37 -> Planeación Institucional | G60: =IF('SDG17'!L37="","",'SDG17'!L37) -> Planeación Institucional | H60: =IF('SDG17'!M37="","",'SDG17'!M37) -> Comunicaciones / Vicerrectorías y unidades responsables por ODS | I60: ='SDG17'!P37 -> Media | J60: ='SDG17'!Q37 -> Pendiente | K60: =IF('SDG17'!F37="","",'SDG17'!F37) | L60: =IF('SDG17'!G37="","",'SDG17'!G37) | M60: =IF('SDG17'!H37="","",'SDG17'!H37) | N60: =IF('SDG17'!I37="","",'SDG17'!I37) | O60: =IF('SDG17'!J37="","",'SDG17'!J37)
A61: ="ODS 17" -> ODS 17 | B61: ='SDG17'!B40 -> 17.3.10 | C61: ='SDG17'!D40 -> Publicación de informes sobre los ODS - por ODS Publicar el progreso con respecto al ODS 10, ya sea individualmente o dentro de un informe anual | D61: ='SDG17'!O40 -> 0.016 | E61: ='SDG17'!N40 -> Evidencia pública | F61: ='SDG17'!K40 -> Planeación Institucional | G61: =IF('SDG17'!L40="","",'SDG17'!L40) -> Planeación Institucional | H61: =IF('SDG17'!M40="","",'SDG17'!M40) -> Comunicaciones / Vicerrectorías y unidades responsables por ODS | I61: ='SDG17'!P40 -> Media | J61: ='SDG17'!Q40 -> Pendiente | K61: =IF('SDG17'!F40="","",'SDG17'!F40) | L61: =IF('SDG17'!G40="","",'SDG17'!G40) | M61: =IF('SDG17'!H40="","",'SDG17'!H40) | N61: =IF('SDG17'!I40="","",'SDG17'!I40) | O61: =IF('SDG17'!J40="","",'SDG17'!J40)
A62: ="ODS 17" -> ODS 17 | B62: ='SDG17'!B43 -> 17.3.11 | C62: ='SDG17'!D43 -> Publicación de informes sobre los ODS - por ODS Publicar el progreso con respecto al ODS 11, ya sea individualmente o dentro de un informe anual | D62: ='SDG17'!O43 -> 0.016 | E62: ='SDG17'!N43 -> Evidencia pública | F62: ='SDG17'!K43 -> Planeación Institucional | G62: =IF('SDG17'!L43="","",'SDG17'!L43) -> Planeación Institucional | H62: =IF('SDG17'!M43="","",'SDG17'!M43) -> Comunicaciones / Vicerrectorías y unidades responsables por ODS | I62: ='SDG17'!P43 -> Media | J62: ='SDG17'!Q43 -> Pendiente | K62: =IF('SDG17'!F43="","",'SDG17'!F43) | L62: =IF('SDG17'!G43="","",'SDG17'!G43) | M62: =IF('SDG17'!H43="","",'SDG17'!H43) | N62: =IF('SDG17'!I43="","",'SDG17'!I43) | O62: =IF('SDG17'!J43="","",'SDG17'!J43)
A63: ="ODS 17" -> ODS 17 | B63: ='SDG17'!B46 -> 17.3.12 | C63: ='SDG17'!D46 -> Publicación de informes sobre los ODS - por ODS Publicar el progreso con respecto al ODS 12, ya sea individualmente o dentro de un informe anual | D63: ='SDG17'!O46 -> 0.016 | E63: ='SDG17'!N46 -> Evidencia pública | F63: ='SDG17'!K46 -> Planeación Institucional | G63: =IF('SDG17'!L46="","",'SDG17'!L46) -> Planeación Institucional | H63: =IF('SDG17'!M46="","",'SDG17'!M46) -> Comunicaciones / Vicerrectorías y unidades responsables por ODS | I63: ='SDG17'!P46 -> Media | J63: ='SDG17'!Q46 -> Pendiente | K63: =IF('SDG17'!F46="","",'SDG17'!F46) | L63: =IF('SDG17'!G46="","",'SDG17'!G46) | M63: =IF('SDG17'!H46="","",'SDG17'!H46) | N63: =IF('SDG17'!I46="","",'SDG17'!I46) | O63: =IF('SDG17'!J46="","",'SDG17'!J46)
A64: ="ODS 17" -> ODS 17 | B64: ='SDG17'!B49 -> 17.3.13 | C64: ='SDG17'!D49 -> Publicación de informes sobre los ODS - por ODS Publicar el progreso con respecto al ODS 13, ya sea individualmente o dentro de un informe anual | D64: ='SDG17'!O49 -> 0.016 | E64: ='SDG17'!N49 -> Evidencia pública | F64: ='SDG17'!K49 -> Planeación Institucional | G64: =IF('SDG17'!L49="","",'SDG17'!L49) -> Planeación Institucional | H64: =IF('SDG17'!M49="","",'SDG17'!M49) -> Comunicaciones / Vicerrectorías y unidades responsables por ODS | I64: ='SDG17'!P49 -> Media | J64: ='SDG17'!Q49 -> Pendiente | K64: =IF('SDG17'!F49="","",'SDG17'!F49) | L64: =IF('SDG17'!G49="","",'SDG17'!G49) | M64: =IF('SDG17'!H49="","",'SDG17'!H49) | N64: =IF('SDG17'!I49="","",'SDG17'!I49) | O64: =IF('SDG17'!J49="","",'SDG17'!J49)
A65: ="ODS 17" -> ODS 17 | B65: ='SDG17'!B52 -> 17.3.14 | C65: ='SDG17'!D52 -> Publicación de informes sobre los ODS - por ODS Publicar el progreso con respecto al ODS 14, ya sea individualmente o dentro de un informe anual | D65: ='SDG17'!O52 -> 0.016 | E65: ='SDG17'!N52 -> Evidencia pública | F65: ='SDG17'!K52 -> Planeación Institucional | G65: =IF('SDG17'!L52="","",'SDG17'!L52) -> Planeación Institucional | H65: =IF('SDG17'!M52="","",'SDG17'!M52) -> Comunicaciones / Vicerrectorías y unidades responsables por ODS | I65: ='SDG17'!P52 -> Media | J65: ='SDG17'!Q52 -> Pendiente | K65: =IF('SDG17'!F52="","",'SDG17'!F52) | L65: =IF('SDG17'!G52="","",'SDG17'!G52) | M65: =IF('SDG17'!H52="","",'SDG17'!H52) | N65: =IF('SDG17'!I52="","",'SDG17'!I52) | O65: =IF('SDG17'!J52="","",'SDG17'!J52)
A66: ="ODS 17" -> ODS 17 | B66: ='SDG17'!B55 -> 17.3.15 | C66: ='SDG17'!D55 -> Publicación de informes sobre los ODS - por ODS Publicar el progreso con respecto al ODS 15, ya sea individualmente o dentro de un informe anual | D66: ='SDG17'!O55 -> 0.016 | E66: ='SDG17'!N55 -> Evidencia pública | F66: ='SDG17'!K55 -> Planeación Institucional | G66: =IF('SDG17'!L55="","",'SDG17'!L55) -> Planeación Institucional | H66: =IF('SDG17'!M55="","",'SDG17'!M55) -> Comunicaciones / Vicerrectorías y unidades responsables por ODS | I66: ='SDG17'!P55 -> Media | J66: ='SDG17'!Q55 -> Pendiente | K66: =IF('SDG17'!F55="","",'SDG17'!F55) | L66: =IF('SDG17'!G55="","",'SDG17'!G55) | M66: =IF('SDG17'!H55="","",'SDG17'!H55) | N66: =IF('SDG17'!I55="","",'SDG17'!I55) | O66: =IF('SDG17'!J55="","",'SDG17'!J55)
A67: ="ODS 17" -> ODS 17 | B67: ='SDG17'!B58 -> 17.3.16 | C67: ='SDG17'!D58 -> Publicación de informes sobre los ODS - por ODS Publicar el progreso con respecto al ODS 16, ya sea individualmente o dentro de un informe anual | D67: ='SDG17'!O58 -> 0.016 | E67: ='SDG17'!N58 -> Evidencia pública | F67: ='SDG17'!K58 -> Planeación Institucional | G67: =IF('SDG17'!L58="","",'SDG17'!L58) -> Planeación Institucional | H67: =IF('SDG17'!M58="","",'SDG17'!M58) -> Comunicaciones / Vicerrectorías y unidades responsables por ODS | I67: ='SDG17'!P58 -> Media | J67: ='SDG17'!Q58 -> Pendiente | K67: =IF('SDG17'!F58="","",'SDG17'!F58) | L67: =IF('SDG17'!G58="","",'SDG17'!G58) | M67: =IF('SDG17'!H58="","",'SDG17'!H58) | N67: =IF('SDG17'!I58="","",'SDG17'!I58) | O67: =IF('SDG17'!J58="","",'SDG17'!J58)
A68: ="ODS 17" -> ODS 17 | B68: ='SDG17'!B61 -> 17.3.17 | C68: ='SDG17'!D61 -> Publicación de informes sobre los ODS - por ODS Publicar el progreso con respecto al ODS 17, ya sea individualmente o dentro de un informe anual | D68: ='SDG17'!O61 -> 0.016 | E68: ='SDG17'!N61 -> Evidencia pública | F68: ='SDG17'!K61 -> Planeación Institucional | G68: =IF('SDG17'!L61="","",'SDG17'!L61) -> Planeación Institucional | H68: =IF('SDG17'!M61="","",'SDG17'!M61) -> Comunicaciones / Vicerrectorías y unidades responsables por ODS | I68: ='SDG17'!P61 -> Media | J68: ='SDG17'!Q61 -> Pendiente | K68: =IF('SDG17'!F61="","",'SDG17'!F61) | L68: =IF('SDG17'!G61="","",'SDG17'!G61) | M68: =IF('SDG17'!H61="","",'SDG17'!H61) | N68: =IF('SDG17'!I61="","",'SDG17'!I61) | O68: =IF('SDG17'!J61="","",'SDG17'!J61)
A69: ="ODS 17" -> ODS 17 | B69: ='SDG17'!B65 -> 17.4.1 | C69: ='SDG17'!D65 -> Educación para los ODS: compromiso con una educación significativa Tener un compromiso con una educación significativa en torno a los ODS en toda la universidad, relevante y aplicable a todos los estudiantes | D69: ='SDG17'!O65 -> 0.0906 | E69: ='SDG17'!N65 -> Evidencia pública | F69: ='SDG17'!K65 -> Planeación Institucional | G69: =IF('SDG17'!L65="","",'SDG17'!L65) -> Planeación Institucional | H69: =IF('SDG17'!M65="","",'SDG17'!M65) -> Vicerrectoría de Enseñanza / Comunicaciones | I69: ='SDG17'!P65 -> Media | J69: ='SDG17'!Q65 -> Pendiente | K69: =IF('SDG17'!F65="","",'SDG17'!F65) | L69: =IF('SDG17'!G65="","",'SDG17'!G65) | M69: =IF('SDG17'!H65="","",'SDG17'!H65) | N69: =IF('SDG17'!I65="","",'SDG17'!I65) | O69: =IF('SDG17'!J65="","",'SDG17'!J65)
A70: ="ODS 17" -> ODS 17 | B70: ='SDG17'!B69 -> 17.4.2 | C70: ='SDG17'!D69 -> Cursos específicos de educación para los ODS sobre sostenibilidad Tener cursos dedicados (títulos completos u optativos) que aborden la sostenibilidad y los ODS. | D70: ='SDG17'!O69 -> 0.0906 | E70: ='SDG17'!N69 -> Evidencia pública | F70: ='SDG17'!K69 -> Planeación Institucional | G70: =IF('SDG17'!L69="","",'SDG17'!L69) -> Planeación Institucional | H70: =IF('SDG17'!M69="","",'SDG17'!M69) -> EDUCON / DRNI / Desarrollo Profesoral | I70: ='SDG17'!P69 -> Media | J70: ='SDG17'!Q69 -> Pendiente | K70: =IF('SDG17'!F69="","",'SDG17'!F69) | L70: =IF('SDG17'!G69="","",'SDG17'!G69) | M70: =IF('SDG17'!H69="","",'SDG17'!H69) | N70: =IF('SDG17'!I69="","",'SDG17'!I69) | O70: =IF('SDG17'!J69="","",'SDG17'!J69)
A71: ="ODS 17" -> ODS 17 | B71: ='SDG17'!B70 -> 17.4.3 | C71: ='SDG17'!D70 -> Educación para los ODS en la comunidad en general Tener actividades educativas de divulgación dedicadas para la comunidad en general, que podrían incluir ex alumnos, residentes locales, personas desplazadas | D71: ='SDG17'!O70 -> 0.0906 | E71: ='SDG17'!N70 -> Evidencia pública | F71: ='SDG17'!K70 -> Planeación Institucional | G71: =IF('SDG17'!L70="","",'SDG17'!L70) -> UDES Verde | H71: =IF('SDG17'!M70="","",'SDG17'!M70) -> Graduados / EDUCON / Desarrollo Profesoral / Planeación Institucional | I71: ='SDG17'!P70 -> Media | J71: ='SDG17'!Q70 -> Pendiente | K71: =IF('SDG17'!F70="","",'SDG17'!F70) | L71: =IF('SDG17'!G70="","",'SDG17'!G70) | M71: =IF('SDG17'!H70="","",'SDG17'!H70) | N71: =IF('SDG17'!I70="","",'SDG17'!I70) | O71: =IF('SDG17'!J70="","",'SDG17'!J70)
A72: ="ODS 17" -> ODS 17 | B72: ='SDG17'!B74 -> 17.4.4 | C72: ='SDG17'!D74 -> Alfabetización en sostenibilidad Esta pregunta explora cómo evalúa la capacidad de sus estudiantes para aprender y retener conceptos clave de sostenibilidad. Para 2026, esta pregunta no puntúa. Medir la alfabetización en sostenibilidad de los estudiantes. | D72: ='SDG17'!O74 -> 0 | E72: ='SDG17'!N74 -> Evidencia (sin puntaje 2026) | F72: ='SDG17'!K74 -> Planeación Institucional | G72: =IF('SDG17'!L74="","",'SDG17'!L74) -> DRNI | H72: =IF('SDG17'!M74="","",'SDG17'!M74) -> Planeación Institucional | I72: ='SDG17'!P74 -> Baja | J72: ='SDG17'!Q74 -> Pendiente | K72: =IF('SDG17'!F74="","",'SDG17'!F74) | L72: =IF('SDG17'!G74="","",'SDG17'!G74) | M72: =IF('SDG17'!H74="","",'SDG17'!H74) | N72: =IF('SDG17'!I74="","",'SDG17'!I74) | O72: =IF('SDG17'!J74="","",'SDG17'!J74) -> Indicador sin puntaje en la edición 2026. Herramienta identificada: Sulitest TASK.
